{
  "pages": [
    {
      "page_num": 1,
      "blocks": [
        {
          "type": "text",
          "content": "IS :  9459  -  1980\n( Reaffirmed\n1992 )",
          "bbox": [
            276.72,
            34.54,
            350.4,
            55.41
          ],
          "block_id": "b1_0",
          "font_size": 9.1,
          "is_bold": true,
          "is_heading": true
        },
        {
          "type": "text",
          "content": "( Reaffirmed 1999 )",
          "bbox": [
            274.0,
            56.96,
            354.52,
            69.35
          ],
          "block_id": "b1_9",
          "font_size": 9.0,
          "is_bold": true,
          "is_heading": true
        },
        {
          "type": "text",
          "content": "Indian Standard",
          "bbox": [
            128.4,
            81.81,
            250.98,
            100.06
          ],
          "block_id": "b1_1",
          "font_size": 15.1,
          "is_bold": true,
          "is_heading": true
        },
        {
          "type": "text",
          "content": "SPECIFICATION\nFOR\nAPPARATUS\nFOR USE IN MEASUREMENT\nOF\nLENGTH CHANGE\nOF HARDENED\nCEMENT\nPASTE, MORTAR\nAND CONCRETE",
          "bbox": [
            36.96,
            107.26,
            350.24,
            171.81
          ],
          "block_id": "b1_2",
          "font_size": 11.5,
          "is_bold": false,
          "is_heading": false
        },
        {
          "type": "text",
          "content": "( Second Reprint JUNE 1998 )",
          "bbox": [
            132.24,
            191.52,
            255.36,
            203.04
          ],
          "block_id": "b1_3",
          "font_size": 8.6,
          "is_bold": false,
          "is_heading": false
        },
        {
          "type": "text",
          "content": "UDC\n666.97.015.7\n:  620.192.52.05",
          "bbox": [
            108.24,
            254.45,
            261.12,
            266.32
          ],
          "block_id": "b1_4",
          "font_size": 8.6,
          "is_bold": false,
          "is_heading": false
        },
        {
          "type": "text",
          "content": "@Copyright\n1980",
          "bbox": [
            157.92,
            462.93,
            235.68,
            472.77
          ],
          "block_id": "b1_5",
          "font_size": 8.6,
          "is_bold": true,
          "is_heading": true
        },
        {
          "type": "text",
          "content": "BUREAU\nOF\nINDIAN\nSTANDARDS",
          "bbox": [
            78.24,
            483.09,
            282.72,
            492.93
          ],
          "block_id": "b1_6",
          "font_size": 8.6,
          "is_bold": true,
          "is_heading": true
        },
        {
          "type": "text",
          "content": "MANAK\nBHAVAN,\n9 BAHADUR\nSHAH\nZAFAR\nMARG\nNEW DELHI\n110002",
          "bbox": [
            78.24,
            494.76,
            311.54,
            512.86
          ],
          "block_id": "b1_7",
          "font_size": 7.0,
          "is_bold": false,
          "is_heading": false
        },
        {
          "type": "text",
          "content": "Gr  2\nJuly 1980",
          "bbox": [
            39.84,
            529.73,
            355.2,
            542.16
          ],
          "block_id": "b1_8",
          "font_size": 8.6,
          "is_bold": true,
          "is_heading": true
        }
      ],
      "images": [],
      "dimensions": {
        "width": 417.6400146484375,
        "height": 565.89599609375
      },
      "image_id_map": {}
    },
    {
      "page_num": 2,
      "blocks": [
        {
          "type": "text",
          "content": "c",
          "bbox": [
            303.12,
            -5.02,
            307.16,
            1.91
          ],
          "block_id": "b2_0",
          "font_size": 5.0,
          "is_bold": false,
          "is_heading": false
        },
        {
          "type": "text",
          "content": "IS :  9459 -  1980",
          "bbox": [
            294.48,
            27.35,
            362.92,
            39.22
          ],
          "block_id": "b2_1",
          "font_size": 8.2,
          "is_bold": false,
          "is_heading": false
        },
        {
          "type": "text",
          "content": "Indian Standard",
          "bbox": [
            139.44,
            50.19,
            270.18,
            70.76
          ],
          "block_id": "b2_2",
          "font_size": 17.0,
          "is_bold": true,
          "is_heading": true
        },
        {
          "type": "text",
          "content": "SPECTFICATION\nFOR\nAPPARATUS\nFOR USE IN MEASUREMENT\nOF\nLENGTH CHANGE\nOF HARDENED\nCEMENT\nPASTE, MORTAR\nAND CONCRETE",
          "bbox": [
            44.4,
            80.8,
            363.44,
            144.64
          ],
          "block_id": "b2_3",
          "font_size": 11.5,
          "is_bold": false,
          "is_heading": false
        },
        {
          "type": "text",
          "content": "Cement\nand Concrete\nSectional\nCommittee,\nBDC\n2",
          "bbox": [
            87.84,
            165.52,
            318.06,
            175.36
          ],
          "block_id": "b2_4",
          "font_size": 7.9,
          "is_bold": false,
          "is_heading": false
        },
        {
          "type": "text",
          "content": "Chairman",
          "bbox": [
            78.48,
            182.91,
            106.62,
            192.2
          ],
          "block_id": "b2_5",
          "font_size": 7.0,
          "is_bold": false,
          "is_heading": false
        },
        {
          "type": "text",
          "content": "Representing",
          "bbox": [
            229.44,
            184.0,
            268.38,
            192.16
          ],
          "block_id": "b2_8",
          "font_size": 7.0,
          "is_bold": false,
          "is_heading": false
        },
        {
          "type": "text",
          "content": "DIG  H. C. VISVESVARAY.~",
          "bbox": [
            42.24,
            194.8,
            139.26,
            202.96
          ],
          "block_id": "b2_6",
          "font_size": 7.0,
          "is_bold": true,
          "is_heading": true
        },
        {
          "type": "text",
          "content": "Cement Research Institute of India, New Delhi",
          "bbox": [
            174.0,
            194.8,
            349.26,
            202.72
          ],
          "block_id": "b2_9",
          "font_size": 7.0,
          "is_bold": true,
          "is_heading": true
        },
        {
          "type": "text",
          "content": "Members",
          "bbox": [
            78.96,
            208.48,
            106.38,
            216.64
          ],
          "block_id": "b2_7",
          "font_size": 7.0,
          "is_bold": false,
          "is_heading": false
        },
        {
          "type": "text",
          "content": "ADDITIONAL DIRECTOR, STAND- Research,\nDesigns\n&\nStandards\nOrganization\nARDS ( R & s  )\nDILPUTY DIRECTOR. STAND-\n(  Ministry of Railways  )",
          "bbox": [
            43.2,
            219.76,
            363.18,
            243.28
          ],
          "block_id": "b2_10",
          "font_size": 8.1,
          "is_bold": true,
          "is_heading": true
        },
        {
          "type": "text",
          "content": "ARDS\n( B & s )\n( ,\u2018iiter,,afr\n1",
          "bbox": [
            66.48,
            245.0,
            166.86,
            250.73
          ],
          "block_id": "b2_11",
          "font_size": 5.0,
          "is_bold": true,
          "is_heading": true
        },
        {
          "type": "text",
          "content": "Sam\nK. C. A~GARWAL\nHindustan Prefab Ltd, New Delhi\nSHRI C. L. KASLIWA~, (  Alternate  )\nSHRI S. K. RANERJEE:\nNational Test House, Calcutta\nSHHI Ii. P. BANERJEF:\nLarsen & Toubro Ltd, Bombay\nSRHI HARISH N. MALANI  (  Alternate )\nSHRT R. N. BANSAL\nSH~II T. C. GARQ (  Altern& )\nCBIEF ENGINEER  (  DESIGNS  )\nEXECUTIVE\nE N o I N E E R\n( DESIQNS  I  III (  Alternate )\nCEIEF  ENGINEER ( PHOJECTS  )\nDIRECTOR, IPRI (  Alternate )\nDIRIWTOR (  CSMRS )\nDEPUTY DIRECTOR ( CSMRS )\n(  Alternate )",
          "bbox": [
            43.2,
            250.96,
            299.82,
            369.76
          ],
          "block_id": "b2_12",
          "font_size": 7.8,
          "is_bold": true,
          "is_heading": false
        },
        {
          "type": "text",
          "content": "Bras besigns Organization,\nNangal Township",
          "bbox": [
            174.72,
            290.32,
            340.62,
            298.24
          ],
          "block_id": "b2_13",
          "font_size": 7.0,
          "is_bold": true,
          "is_heading": true
        },
        {
          "type": "text",
          "content": "Central Public Works Department,\nNew Delhi",
          "bbox": [
            175.2,
            306.16,
            343.74,
            314.08
          ],
          "block_id": "b2_14",
          "font_size": 7.0,
          "is_bold": true,
          "is_heading": true
        },
        {
          "type": "text",
          "content": "Irrigation\nDepartmcnt,~Gcvernmcnt\nof Punjab",
          "bbox": [
            175.2,
            329.92,
            346.38,
            337.84
          ],
          "block_id": "b2_15",
          "font_size": 7.0,
          "is_bold": true,
          "is_heading": true
        },
        {
          "type": "text",
          "content": "Central Water Commission, New Delhi",
          "bbox": [
            175.2,
            345.52,
            319.74,
            353.44
          ],
          "block_id": "b2_16",
          "font_size": 7.0,
          "is_bold": true,
          "is_heading": true
        },
        {
          "type": "text",
          "content": "lh\nR. K. GHOSH\nCent;ralhyoad\nResearch\nInstitute\n( CSIR ), New",
          "bbox": [
            44.16,
            369.28,
            368.46,
            377.44
          ],
          "block_id": "b2_17",
          "font_size": 7.0,
          "is_bold": true,
          "is_heading": true
        },
        {
          "type": "text",
          "content": "SHRI Y. R.  PHULL (  Alfernaie I  j\nSHR I M. DINAKA~AN ( Allcrnole II )\nDR R. K. GHOSH\nIndian Roads Congress, New Delhi\nSRRI B. R. GOVIND\nSHRI P. C. JAIN (  Aftsrnotc )\nEngineer-in-Chief\u2019s\nBranch,\nArmy Headquarters",
          "bbox": [
            43.92,
            383.92,
            351.66,
            424.48
          ],
          "block_id": "b2_18",
          "font_size": 7.2,
          "is_bold": true,
          "is_heading": false
        },
        {
          "type": "text",
          "content": "SHRI  A. K.  GUPTA\nHyderabad\nAsbestos\nCement",
          "bbox": [
            44.4,
            424.0,
            295.02,
            432.4
          ],
          "block_id": "b2_19",
          "font_size": 7.0,
          "is_bold": true,
          "is_heading": true
        },
        {
          "type": "text",
          "content": "DR R. R. HATTIANOADI\nHydcrabad\nProducts\nLtd,",
          "bbox": [
            44.4,
            424.96,
            366.3,
            448.24
          ],
          "block_id": "b2_20",
          "font_size": 7.0,
          "is_bold": true,
          "is_heading": true
        },
        {
          "type": "text",
          "content": "S~RI P. J.  JAWS ( AIfcrnatr )\nThe Associated Cement Companies Ltd, Bombay",
          "bbox": [
            60.24,
            440.32,
            354.78,
            456.4
          ],
          "block_id": "b2_21",
          "font_size": 7.0,
          "is_bold": true,
          "is_heading": true
        },
        {
          "type": "text",
          "content": "(  Continued on page 2 )",
          "bbox": [
            290.88,
            459.28,
            368.94,
            467.68
          ],
          "block_id": "b2_23",
          "font_size": 7.0,
          "is_bold": true,
          "is_heading": true
        },
        {
          "type": "text",
          "content": ",\n@ Copyrighr 1980",
          "bbox": [
            44.88,
            467.2,
            231.66,
            484.24
          ],
          "block_id": "b2_22",
          "font_size": 7.0,
          "is_bold": true,
          "is_heading": true
        },
        {
          "type": "text",
          "content": "BUREAU\nOF\nINDIAN\nSTANDARDS",
          "bbox": [
            132.72,
            486.16,
            277.98,
            494.08
          ],
          "block_id": "b2_24",
          "font_size": 7.0,
          "is_bold": true,
          "is_heading": true
        },
        {
          "type": "text",
          "content": "This publication\nis protected\nurder the  Indian\nCopyrigL:  Act  ( XIV\nof 1957 ) and\nreproduction\nin whole or in part by any means except with written permission of the\npublisher shall be deemed to be an infringement\nof copyright under the said Act.",
          "bbox": [
            52.8,
            496.48,
            362.22,
            520.72
          ],
          "block_id": "b2_25",
          "font_size": 7.0,
          "is_bold": true,
          "is_heading": false
        }
      ],
      "images": [],
      "dimensions": {
        "width": 392.79998779296875,
        "height": 564.4000244140625
      },
      "image_id_map": {}
    },
    {
      "page_num": 3,
      "blocks": [
        {
          "type": "text",
          "content": "IS 8  9459 -  1980",
          "bbox": [
            44.16,
            38.73,
            121.44,
            51.06
          ],
          "block_id": "b3_0",
          "font_size": 9.0,
          "is_bold": true,
          "is_heading": true
        },
        {
          "type": "text",
          "content": "( Continued from page  1 )",
          "bbox": [
            43.2,
            59.87,
            129.57,
            67.93
          ],
          "block_id": "b3_1",
          "font_size": 6.6,
          "is_bold": true,
          "is_heading": true
        },
        {
          "type": "text",
          "content": "Members\nR@wenting",
          "bbox": [
            78.72,
            73.94,
            264.55,
            81.62
          ],
          "block_id": "b3_2",
          "font_size": 6.2,
          "is_bold": true,
          "is_heading": true
        },
        {
          "type": "text",
          "content": "DR IQSAL ALI\nEngineering Research Laboratories, Hydcrabad\nSARI S. R. KULKARNI\nM. N. Dastur & Co  (  Pvt ) Ltd, Calcutta\nSHRI S. K. Larry\nThe Institution of Engineers ( India ), Calcutta\nSRRI 8. T. UNWALLA ( AlfefMfs )\nDB MOEAN RAI\nCentral\nBuilding\nResearch\nInstitute\n( CSIR ),\nRoorkee\nDR S. S. REHSI ( Altrrnare )\nSHRI K. K. NAMBIAR\nIn personal capacity\n(  \u2018Ramanalqya\u2019 II First Crescent",
          "bbox": [
            43.2,
            83.92,
            366.3,
            147.62
          ],
          "block_id": "b3_3",
          "font_size": 7.5,
          "is_bold": true,
          "is_heading": false
        },
        {
          "type": "text",
          "content": "DR M. RAMA:AH\nPark Road, pndbinapr,\nAdyar, Madras )\nStru;~;ct~e.ugmcermg\nResearch Centre\n( CSTR ),",
          "bbox": [
            43.44,
            147.47,
            366.01,
            163.22
          ],
          "block_id": "b3_4",
          "font_size": 7.0,
          "is_bold": true,
          "is_heading": true
        },
        {
          "type": "text",
          "content": "DR N. S.  BAAL (  Altsrnatc )\nSHRI G.  RAMDAS\nDirectorate\nGeneral\nof\nSupplier\n& Disposals,\nNew Delhi\nDR A. V. R.  RAO\nNational\nBuildings\nOrganization,\nNew Delhi",
          "bbox": [
            43.92,
            171.04,
            364.09,
            203.29
          ],
          "block_id": "b3_5",
          "font_size": 7.0,
          "is_bold": true,
          "is_heading": true
        },
        {
          "type": "text",
          "content": "SHFCI  J. SEN GUPT~  ( Alternate)\nSERI R. V. CHALAP~THI RAO\nGeological\nSurvey of India, Calcutta\nSHRI S. ROY (  Alfernate )\nSHRI T. N. S. RAO\nGammon India Ltd, Bombay\nSHRI S. R. PINHEIRO (  Alternate 1\nSHRI ARJUN RIJHSINGHANI\nCement Corporation of IndiaLtd,\nNew D \u2018hi\nSHRI K. VITHAL RAO ( Alters& )\nSECRETARY\nCentral Board of Irrigation and Power, N* N Delhi\nDEPUTY SECRETARY ( I ) (  Alternate )\nSHRI N. Stv~~uRu\nRoads Wing, Ministry of Shipping arid Trai *port",
          "bbox": [
            44.16,
            202.48,
            361.22,
            282.02
          ],
          "block_id": "b3_6",
          "font_size": 7.0,
          "is_bold": true,
          "is_heading": false
        },
        {
          "type": "text",
          "content": "SHRI\nR. L.  KAPOOR  ( Altomate )",
          "bbox": [
            60.48,
            281.68,
            178.14,
            290.17
          ],
          "block_id": "b3_7",
          "font_size": 6.7,
          "is_bold": true,
          "is_heading": true
        },
        {
          "type": "text",
          "content": "SHRI\nK.  A. SUI~AMANIAW\nThe India Cements Ltd, Madras\nSERI  P. S. RAMACEANDRAN (  Alternate  )\nSUPERINTENUING E N o I N E x R\nPublic\nWorks\nDepartment,\nGovernment\nof \u2018. \u2018amil\n( DESIGNS  )\nNadu\nEXECUTIVE\nE N Q I N E E R\n( SM & R DIVISION ) (  Altrrnafc )\nSHXI  L. SWAROOP\nDalmia Cement ( Bharat ) Ltd, New Delhi\nSHRI A. V. RAMANA (  Alternate )\nSHRI B. T.  UNWALLA\nThe Concrete Association of India, Bombay\nSHRI Y. K. MEHTA (  Alternate )\nSHRI  D. AJITFIA SIMHA,\nDirector General, ISI ( Ex-o&o\nMember )\nDirector ( Civ Engg  )",
          "bbox": [
            44.64,
            289.36,
            366.73,
            386.36
          ],
          "block_id": "b3_8",
          "font_size": 7.8,
          "is_bold": true,
          "is_heading": false
        },
        {
          "type": "text",
          "content": "Secretary",
          "bbox": [
            192.24,
            391.07,
            221.1,
            399.0
          ],
          "block_id": "b3_9",
          "font_size": 7.0,
          "is_bold": true,
          "is_heading": true
        },
        {
          "type": "text",
          "content": "SHRI M. N. NEELAEANDHAN\nAssistant Director ( Civ Engg ), ISI",
          "bbox": [
            143.28,
            401.2,
            272.65,
            417.62
          ],
          "block_id": "b3_10",
          "font_size": 7.0,
          "is_bold": false,
          "is_heading": false
        },
        {
          "type": "text",
          "content": "Instruments\nfor Cement\nand\nConcrete\nTesting\nSubcommittee,\nBDC 2: 10",
          "bbox": [
            71.76,
            431.2,
            329.3,
            449.73
          ],
          "block_id": "b3_11",
          "font_size": 8.6,
          "is_bold": false,
          "is_heading": false
        },
        {
          "type": "text",
          "content": "Convener",
          "bbox": [
            81.6,
            456.11,
            111.18,
            464.04
          ],
          "block_id": "b3_12",
          "font_size": 7.0,
          "is_bold": true,
          "is_heading": true
        },
        {
          "type": "text",
          "content": "DR IQBAL ALI\nEngineering Rrsearch Laboratories, Hyderabad",
          "bbox": [
            45.84,
            466.0,
            347.29,
            474.98
          ],
          "block_id": "b3_13",
          "font_size": 7.0,
          "is_bold": false,
          "is_heading": false
        },
        {
          "type": "text",
          "content": "Members",
          "bbox": [
            81.6,
            480.59,
            110.22,
            488.52
          ],
          "block_id": "b3_14",
          "font_size": 7.0,
          "is_bold": true,
          "is_heading": true
        },
        {
          "type": "text",
          "content": "PROE  B. M.  AHUJA\nSERI T. P. EKAMBARAM\nIndian Institute of Technology,\nNew Delhi\nHighways Research Station, Madras",
          "bbox": [
            46.08,
            490.48,
            335.29,
            507.62
          ],
          "block_id": "b3_15",
          "font_size": 7.0,
          "is_bold": true,
          "is_heading": true
        },
        {
          "type": "text",
          "content": "(  Continued on page 8 )",
          "bbox": [
            293.52,
            509.2,
            370.62,
            517.56
          ],
          "block_id": "b3_16",
          "font_size": 7.0,
          "is_bold": true,
          "is_heading": true
        },
        {
          "type": "text",
          "content": "2",
          "bbox": [
            212.16,
            523.72,
            218.64,
            534.45
          ],
          "block_id": "b3_17",
          "font_size": 8.6,
          "is_bold": false,
          "is_heading": false
        }
      ],
      "images": [],
      "dimensions": {
        "width": 409.6400146484375,
        "height": 568.0960083007812
      },
      "image_id_map": {}
    },
    {
      "page_num": 4,
      "blocks": [
        {
          "type": "text",
          "content": "1S:9459\n-  1980",
          "bbox": [
            291.84,
            33.3,
            358.61,
            43.54
          ],
          "block_id": "b4_0",
          "font_size": 8.6,
          "is_bold": true,
          "is_heading": true
        },
        {
          "type": "text",
          "content": "Indian Standard",
          "bbox": [
            135.6,
            58.61,
            266.34,
            79.18
          ],
          "block_id": "b4_1",
          "font_size": 17.0,
          "is_bold": true,
          "is_heading": true
        },
        {
          "type": "text",
          "content": "SPECIFICATION\nFOR\nAPPARATUS\nFOR  USE IN MEASUREMENT\nOF\nLENGTH CHANGE\nOF HARDENED\nCEMENT\nPASTE, MORTAR\nAN-D CONCRETE",
          "bbox": [
            41.28,
            86.1,
            360.56,
            150.17
          ],
          "block_id": "b4_2",
          "font_size": 11.5,
          "is_bold": true,
          "is_heading": true
        },
        {
          "type": "text",
          "content": "0.\nFOREWORU",
          "bbox": [
            137.04,
            188.89,
            223.68,
            202.02
          ],
          "block_id": "b4_3",
          "font_size": 10.6,
          "is_bold": false,
          "is_heading": false
        },
        {
          "type": "text",
          "content": "0.1 This Indian\nStandard\nwas adopted\nby the Indian\nStandards\nInstitution\non 8 February\n1980, after the draft finalized\nby the Cement\nand Concrete\nSectional\nCommittee\nhad been approved\nby the Civil Engineering\nDivision\nCouncil.",
          "bbox": [
            40.8,
            210.89,
            359.34,
            250.5
          ],
          "block_id": "b4_4",
          "font_size": 7.9,
          "is_bold": false,
          "is_heading": false
        },
        {
          "type": "text",
          "content": "0.2 The\nIndian\nStandards\nInstitution\nhas already\npublished\na series of\nstandards\non\nmethods\nof\ntesting\ncement\nand concrete.\nIt has been\nrecognized\nthat reproducible\nand repeatable\ntest results\ncan be obtained\nonly with standard\ntesting equipment\ncapable\nof giving the desired\nievel\nof accuracy.\nThe Sectional\nCommittee\nhas, therefore,\ndecided\nto bring\nout a series of specifications\ncovering\nthe requirements\nof equipments\nused\nfor testing\ncement\nand\nconcrete,\nto encourage\ntheir\ndevelopment\nand\nmanufacture\nin the country.",
          "bbox": [
            40.8,
            259.37,
            364.62,
            338.58
          ],
          "block_id": "b4_5",
          "font_size": 7.9,
          "is_bold": false,
          "is_heading": false
        },
        {
          "type": "text",
          "content": "0.3 Accordingly,\nthis standard\nhas been prepared\nto cover\nrequirements\nof the apparatus\nfor use in measurement\nof length\nchange\nof hardened\ncement\npaste,\nmortar\nand concrete.\nThis\napparatus\nmay\nbe used\nfor\ndetermining\nthe initial\ndrying\nshrinkage,\ndrying\nshrinkage\nand moisture\nmovement\nof concrete\n( ste IS  :  119%1959*\n), alkali reactivity\nof aggregate\n[ see IS  :  2386\n( Part\nVII\n)-1963t\n] and\ndrying\nshrinkage\nof Portland\npozzolana\ncement\n( see IS  :  4031-1968:\n).",
          "bbox": [
            41.28,
            347.45,
            364.14,
            417.0
          ],
          "block_id": "b4_6",
          "font_size": 8.2,
          "is_bold": false,
          "is_heading": false
        },
        {
          "type": "text",
          "content": "0.4\nIn the formulation\nof this standard,\ndue weightage\nhas been given to\ninternational\nco-ordination\namong\nthe standards\nand practices\nprevailing\nin different\ncountries\nin addition\nto relating\nit to the practices\nin the field\nin this country.",
          "bbox": [
            41.76,
            425.45,
            365.58,
            465.54
          ],
          "block_id": "b4_7",
          "font_size": 7.9,
          "is_bold": false,
          "is_heading": false
        },
        {
          "type": "text",
          "content": "*Methods\nof sampling\nand analysis\nof concrete.\ntMethods\nof test for aggregate\nfor concrete:\nPart\nVII\nAlkali\naggregate\nreactivity.\nfMrthods\nof physical\ntests for hydraulic\ncement.",
          "bbox": [
            56.64,
            479.81,
            349.26,
            504.93
          ],
          "block_id": "b4_8",
          "font_size": 7.0,
          "is_bold": false,
          "is_heading": false
        },
        {
          "type": "text",
          "content": "\u201d\n3",
          "bbox": [
            203.04,
            518.16,
            207.32,
            526.56
          ],
          "block_id": "b4_9",
          "font_size": 5.0,
          "is_bold": false,
          "is_heading": false
        }
      ],
      "images": [],
      "dimensions": {
        "width": 413.6400146484375,
        "height": 572.0960083007812
      },
      "image_id_map": {}
    },
    {
      "page_num": 5,
      "blocks": [
        {
          "type": "text",
          "content": "IS t 9459\n- 1980",
          "bbox": [
            41.76,
            37.54,
            110.45,
            47.61
          ],
          "block_id": "b5_0",
          "font_size": 8.6,
          "is_bold": true,
          "is_heading": true
        },
        {
          "type": "text",
          "content": "0.5\nFor the purpose of deciding\nwhether a particular\nrequirement\nof this\nstandard\nis complied\nwith,\nthe final\nvalue,\nobserved\nor calculated,\nexpressing\nthe result\nof\na test or\nanalysis,\nshall\nbe rounded\noff in\naccordance\nwith IS  :  2-1960*.\nThe number\nof significant\nplaces retained\nin the rounded\noff value should be the same as that of the specified value\nin this standard.",
          "bbox": [
            40.56,
            57.22,
            364.12,
            116.22
          ],
          "block_id": "b5_1",
          "font_size": 8.6,
          "is_bold": true,
          "is_heading": false
        },
        {
          "type": "text",
          "content": "1. SCOPE",
          "bbox": [
            42.96,
            147.62,
            85.48,
            157.02
          ],
          "block_id": "b5_2",
          "font_size": 7.9,
          "is_bold": false,
          "is_heading": false
        },
        {
          "type": "text",
          "content": "1.1 This standard\nlays down the requirements\nof apparatus\n( known\nas\nlength comparator\n) to measure length change in hardened\ncement paste,\nmortar and concrete,\nusing a suitable\nmicrometer.",
          "bbox": [
            41.52,
            163.46,
            365.08,
            192.54
          ],
          "block_id": "b5_3",
          "font_size": 7.9,
          "is_bold": false,
          "is_heading": false
        },
        {
          "type": "text",
          "content": "2. APPARATUS",
          "bbox": [
            41.76,
            202.1,
            108.04,
            211.5
          ],
          "block_id": "b5_4",
          "font_size": 7.9,
          "is_bold": false,
          "is_heading": false
        },
        {
          "type": "text",
          "content": "2.1 The apparatus\nshall consist of an adjustable\nlength comparator\nusing\na  screw or dial micrometer,\ntogether with a suitable reference\nbar.",
          "bbox": [
            42.24,
            217.94,
            365.32,
            237.85
          ],
          "block_id": "b5_5",
          "font_size": 7.9,
          "is_bold": false,
          "is_heading": false
        },
        {
          "type": "text",
          "content": "3. CONSTRUCTION\nAND\nDIMENSIONS",
          "bbox": [
            42.24,
            246.5,
            233.8,
            255.9
          ],
          "block_id": "b5_6",
          "font_size": 7.9,
          "is_bold": false,
          "is_heading": false
        },
        {
          "type": "text",
          "content": "3.1 The construction\nof the length comparator\nshall be as given in Fig. 1\nor Fig. 2.\nThe type of\napparatus\nshown\nin Fig. 2 is recommended\nfor\ntesting\nheavy\nspecimens,\nsince the pressure\ncaused by the weight of the\nspecimen,\nwhich would otherwise fall on the lower reference ball, iscarried\nby the slotted\nshelf.\nThe apparatus\nshall preferably\nbe adjustable\nfor\nspecimens\nof different\nlengths.\nNominal\ndimensions\nof the apparatus\nof\nthe type shown\nin Fig.\n1 are indicated\nin the figure.\nThe end of the\nframe to seat the lower end of the reference bar shall be provided\nwith a\ncylindrical\nor conical\nrecess.\nThe surfaces in contact with the specimen\nreference\npoints shall be heat-treated,\nhardened\nand polished.",
          "bbox": [
            42.0,
            262.34,
            367.72,
            360.78
          ],
          "block_id": "b5_7",
          "font_size": 7.9,
          "is_bold": false,
          "is_heading": false
        },
        {
          "type": "text",
          "content": "3.1.1 The measuring\ninstrument\nin the length comparator\nshall be a\nhigh grade micrometer\nhaving a range of at least 10 mm and graduated\nto read in O-002 mm units, accurate\nwithin 0\u2019002\nmm in any 0.020 mm\nrange or a suitable\ndial gauge.\nThis gauge shall be rigidly mounted in a\nmeasuring\nframe and shall have a conical\nspindle\nwhich\ncan be located\nupon\na 6 mm diameter\nball\nor other reference\npoint cemented\nin the\nspecimen.",
          "bbox": [
            43.44,
            366.98,
            367.48,
            435.9
          ],
          "block_id": "b5_8",
          "font_size": 7.9,
          "is_bold": false,
          "is_heading": false
        },
        {
          "type": "text",
          "content": "3.2 The reference\nbar against which the readings of the gauge are tested,\nshall be of sta-inless steel having a co-efficient\nof thermal\nexpansion\nnot\ngreater\nthan 2 millionth\nper deg C.\nThe reference\nbar may\nhave\nan\noverall diameter of 20 mm and of 300 2 is mm or 150 t Ls mm length which",
          "bbox": [
            43.92,
            442.1,
            367.24,
            481.26
          ],
          "block_id": "b5_9",
          "font_size": 7.9,
          "is_bold": false,
          "is_heading": false
        },
        {
          "type": "text",
          "content": "*Rules for rounding\noff numerical\nvalues\n(  revised ).",
          "bbox": [
            59.76,
            493.85,
            250.14,
            505.72
          ],
          "block_id": "b5_10",
          "font_size": 7.8,
          "is_bold": true,
          "is_heading": true
        }
      ],
      "images": [],
      "dimensions": {
        "width": 413.6400146484375,
        "height": 570.0960083007812
      },
      "image_id_map": {}
    },
    {
      "page_num": 6,
      "blocks": [
        {
          "type": "text",
          "content": "IS : 9459 * 1980",
          "bbox": [
            286.56,
            40.06,
            355.72,
            50.94
          ],
          "block_id": "b6_0",
          "font_size": 7.9,
          "is_bold": false,
          "is_heading": false
        },
        {
          "type": "text",
          "content": "ever is appropriate.\nThe length\nof the reference\nbar shall\nbe standard-\nized ai a particular\ntemperature\nand\nprovided\nwith\ncalibration\ncharts\nfor reading\nlength\nat different\ntemperatures.\nEach end of the bar shall\nbe  machined\nto 6 mm diameter\nspherical\nends or 6 mm dia balls may be\nswaged or otherwise\nfixed to the end.\nThe\nends\nshall\nbe heat-treated,\nhardened\nand\nthen\npolished.\nThe central\nIOO~mm of the length\nof the\nbar shall\nbe covered\nby insulating\nmaterial,\nsuch-as 6 mm thick rubber\ntube,\nto facilitate\nhandling\nand to minimize\nthe effect of temperature\nduring\nhandling.\none end.\nThe bar shall be provided\nwith a positioning\nmark near",
          "bbox": [
            33.84,
            59.16,
            355.44,
            159.48
          ],
          "block_id": "b6_1",
          "font_size": 8.6,
          "is_bold": false,
          "is_heading": false
        },
        {
          "type": "text",
          "content": "rr\n285\n-I",
          "bbox": [
            120.48,
            234.6,
            234.72,
            247.8
          ],
          "block_id": "b6_2",
          "font_size": 8.6,
          "is_bold": false,
          "is_heading": false
        },
        {
          "type": "text",
          "content": ",-OIAL\nGAUGE",
          "bbox": [
            193.92,
            255.82,
            252.13,
            266.7
          ],
          "block_id": "b6_3",
          "font_size": 7.9,
          "is_bold": true,
          "is_heading": true
        },
        {
          "type": "text",
          "content": "All\ndimensions in millimetres.",
          "bbox": [
            144.72,
            489.46,
            251.34,
            499.3
          ],
          "block_id": "b6_4",
          "font_size": 8.6,
          "is_bold": true,
          "is_heading": true
        },
        {
          "type": "text",
          "content": "Fro.\n1\nLENGTH COMPARATOR",
          "bbox": [
            129.6,
            503.16,
            264.86,
            514.9
          ],
          "block_id": "b6_5",
          "font_size": 8.6,
          "is_bold": true,
          "is_heading": true
        },
        {
          "type": "text",
          "content": "5",
          "bbox": [
            197.04,
            522.6,
            203.52,
            534.12
          ],
          "block_id": "b6_6",
          "font_size": 8.6,
          "is_bold": false,
          "is_heading": false
        }
      ],
      "images": [],
      "dimensions": {
        "width": 419.6400146484375,
        "height": 558.0960083007812
      },
      "image_id_map": {}
    },
    {
      "page_num": 7,
      "blocks": [
        {
          "type": "text",
          "content": "I8 : 9459 - 1980",
          "bbox": [
            58.08,
            38.67,
            131.1,
            49.1
          ],
          "block_id": "b7_0",
          "font_size": 8.6,
          "is_bold": true,
          "is_heading": true
        },
        {
          "type": "text",
          "content": "q-SHELF  SUPPORT",
          "bbox": [
            241.92,
            74.43,
            316.33,
            84.86
          ],
          "block_id": "b7_1",
          "font_size": 7.8,
          "is_bold": true,
          "is_heading": true
        },
        {
          "type": "text",
          "content": "SECTION\nXX",
          "bbox": [
            233.76,
            159.1,
            295.97,
            169.17
          ],
          "block_id": "b7_4",
          "font_size": 8.6,
          "is_bold": true,
          "is_heading": true
        },
        {
          "type": "text",
          "content": "I",
          "bbox": [
            102.24,
            311.74,
            107.31,
            324.93
          ],
          "block_id": "b7_2",
          "font_size": 9.6,
          "is_bold": false,
          "is_heading": false
        },
        {
          "type": "text",
          "content": "P",
          "bbox": [
            96.0,
            356.62,
            105.15,
            369.81
          ],
          "block_id": "b7_3",
          "font_size": 9.6,
          "is_bold": false,
          "is_heading": false
        },
        {
          "type": "text",
          "content": "FIG. 2\nTYPICAL\nSET  UP FOR DRYING SHRINKAGE  AND  MCJISTURE\nMOVEMENT TEST ON HEAVY  SPECIMEX",
          "bbox": [
            71.76,
            394.08,
            373.44,
            415.2
          ],
          "block_id": "b7_5",
          "font_size": 8.6,
          "is_bold": true,
          "is_heading": true
        },
        {
          "type": "text",
          "content": "3.3  Except\nwhere\nthe\ntolerances\nare specifically\nindicated\nagainst\nthe\nspecified dimensions,\nall dimensions\nshall be taken as nominal\ndimensions\nwith tolerances\nnormally\napplicable\nin general\nengineering\npractice.",
          "bbox": [
            63.12,
            435.12,
            382.8,
            466.56
          ],
          "block_id": "b7_6",
          "font_size": 8.6,
          "is_bold": true,
          "is_heading": false
        },
        {
          "type": "text",
          "content": "4.  MATERIAL",
          "bbox": [
            62.88,
            476.88,
            121.92,
            488.4
          ],
          "block_id": "b7_7",
          "font_size": 8.6,
          "is_bold": true,
          "is_heading": true
        },
        {
          "type": "text",
          "content": "4.1  Materials\nof\nconstruction\nof\ndifferent\ncomponent\nparts\nof\nthe\napparatus\nshall be as given in Table\n1.",
          "bbox": [
            62.88,
            492.24,
            382.8,
            514.08
          ],
          "block_id": "b7_8",
          "font_size": 8.6,
          "is_bold": true,
          "is_heading": true
        },
        {
          "type": "text",
          "content": "6",
          "bbox": [
            222.96,
            521.76,
            229.44,
            533.28
          ],
          "block_id": "b7_9",
          "font_size": 8.6,
          "is_bold": false,
          "is_heading": false
        }
      ],
      "images": [],
      "dimensions": {
        "width": 433.6400146484375,
        "height": 585.0960083007812
      },
      "image_id_map": {}
    },
    {
      "page_num": 8,
      "blocks": [
        {
          "type": "text",
          "content": "IS  I  9459  -  1980",
          "bbox": [
            287.28,
            16.87,
            362.22,
            28.74
          ],
          "block_id": "b8_0",
          "font_size": 7.2,
          "is_bold": true,
          "is_heading": true
        },
        {
          "type": "text",
          "content": "TABLE 1  MATERIALS\nFOR LENGTH\nCOMPARATOR",
          "bbox": [
            80.4,
            44.19,
            299.92,
            53.75
          ],
          "block_id": "b8_1",
          "font_size": 7.4,
          "is_bold": true,
          "is_heading": true
        },
        {
          "type": "text",
          "content": "( Clause 4.1 )",
          "bbox": [
            174.0,
            56.46,
            219.28,
            64.75
          ],
          "block_id": "b8_2",
          "font_size": 7.0,
          "is_bold": true,
          "is_heading": true
        },
        {
          "type": "text",
          "content": "SL\nPART\nM.~TE~UAL\nSPECIAL REQUIREMENTS, IF ANY\nNo.",
          "bbox": [
            41.76,
            72.78,
            346.96,
            90.19
          ],
          "block_id": "b8_3",
          "font_size": 7.0,
          "is_bold": true,
          "is_heading": true
        },
        {
          "type": "text",
          "content": "i)\nBase\nChannel\nmild steel\n( IS  :  226-1975* )",
          "bbox": [
            46.56,
            94.62,
            203.44,
            111.78
          ],
          "block_id": "b8_4",
          "font_size": 7.5,
          "is_bold": true,
          "is_heading": true
        },
        {
          "type": "text",
          "content": "ii)\nPillars\nMild steel\n( 1s  :  226-1975* )\nThreaded\nfor adjustment",
          "bbox": [
            43.44,
            116.22,
            307.84,
            133.38
          ],
          "block_id": "b8_5",
          "font_size": 7.5,
          "is_bold": true,
          "is_heading": true
        },
        {
          "type": "text",
          "content": "iii)\nBracket\nMild steel\n( IS  :  226-1975* )\n-",
          "bbox": [
            40.08,
            137.1,
            289.36,
            155.46
          ],
          "block_id": "b8_6",
          "font_size": 7.5,
          "is_bold": true,
          "is_heading": true
        },
        {
          "type": "text",
          "content": "iv)\nReference\nbar\nStainless steel\nEnds\nheat-treated,\nhardened\nand\nthen polished",
          "bbox": [
            41.04,
            160.14,
            351.76,
            176.59
          ],
          "block_id": "b8_7",
          "font_size": 7.0,
          "is_bold": true,
          "is_heading": true
        },
        {
          "type": "text",
          "content": "v)\nRubber\ntube\nRubber\n-",
          "bbox": [
            43.92,
            180.78,
            289.84,
            190.51
          ],
          "block_id": "b8_8",
          "font_size": 7.0,
          "is_bold": true,
          "is_heading": true
        },
        {
          "type": "text",
          "content": "NOTE -\nAll non-working\nmild steel parts of the apparatus\nshall be provided\nsuit-\nable anticorrosive\ntreatment\nsuch as painting,\nnitriding\nand phosphating\nconforming\nto relevant\nIndian Standards.",
          "bbox": [
            45.36,
            202.14,
            355.12,
            226.03
          ],
          "block_id": "b8_9",
          "font_size": 7.0,
          "is_bold": true,
          "is_heading": true
        },
        {
          "type": "text",
          "content": "*Specification\nfor structural\nsteel ( standard\nquality\n) (J;fi/z revision ).",
          "bbox": [
            49.2,
            237.66,
            302.32,
            245.95
          ],
          "block_id": "b8_10",
          "font_size": 7.0,
          "is_bold": true,
          "is_heading": true
        },
        {
          "type": "text",
          "content": "5. MARKING",
          "bbox": [
            33.6,
            261.89,
            94.38,
            272.32
          ],
          "block_id": "b8_11",
          "font_size": 8.6,
          "is_bold": true,
          "is_heading": true
        },
        {
          "type": "text",
          "content": "5.1  The apparatus\nshall be marked\nwith the following\ninformation:",
          "bbox": [
            34.32,
            276.98,
            320.4,
            288.51
          ],
          "block_id": "b8_12",
          "font_size": 8.6,
          "is_bold": true,
          "is_heading": true
        },
        {
          "type": "text",
          "content": "a) Name of the manufacturer\nor his trade-mark,\nand\nb) Date of manfacture.",
          "bbox": [
            54.72,
            292.82,
            288.0,
            317.31
          ],
          "block_id": "b8_13",
          "font_size": 8.6,
          "is_bold": false,
          "is_heading": false
        },
        {
          "type": "text",
          "content": "5.1.1\nThe product may also be marked with StandardMark.",
          "bbox": [
            44.4,
            321.86,
            276.24,
            333.39
          ],
          "block_id": "b8_14",
          "font_size": 8.6,
          "is_bold": false,
          "is_heading": false
        },
        {
          "type": "text",
          "content": "5.2\nThe use of the Standard Mark is governed by the provisions\nof  Bureau of\nIn&n\nStandards Act, 1986  and the Rules and Regulations\nmade thereunder.\nThe details of conditions\nunder which the licence for the use of Standard Mark\nmay be granted to manfucaturers\nor producers may be obtained from the Bureau\nof Indian Standards.",
          "bbox": [
            30.72,
            347.78,
            354.0,
            402.27
          ],
          "block_id": "b8_15",
          "font_size": 8.6,
          "is_bold": true,
          "is_heading": false
        },
        {
          "type": "text",
          "content": "7",
          "bbox": [
            194.16,
            498.98,
            200.64,
            510.51
          ],
          "block_id": "b8_16",
          "font_size": 8.6,
          "is_bold": false,
          "is_heading": false
        }
      ],
      "images": [],
      "dimensions": {
        "width": 383.3999938964844,
        "height": 554.3999633789062
      },
      "image_id_map": {}
    },
    {
      "page_num": 9,
      "blocks": [
        {
          "type": "text",
          "content": "IS  I  9459  -  1980",
          "bbox": [
            44.64,
            28.49,
            116.16,
            40.36
          ],
          "block_id": "b9_0",
          "font_size": 7.2,
          "is_bold": true,
          "is_heading": true
        },
        {
          "type": "text",
          "content": "( Continued from page  2 )",
          "bbox": [
            44.4,
            48.77,
            132.97,
            58.34
          ],
          "block_id": "b9_1",
          "font_size": 7.0,
          "is_bold": false,
          "is_heading": false
        },
        {
          "type": "text",
          "content": "Members\nRepresenting",
          "bbox": [
            79.92,
            63.45,
            270.7,
            71.14
          ],
          "block_id": "b9_2",
          "font_size": 6.2,
          "is_bold": true,
          "is_heading": true
        },
        {
          "type": "text",
          "content": "Da R. K. GHOST\nCentral\nRoad\nResearch\nInstitute\n(  CSIR ),\nNew Delhi\nSHRI K. L.  SETHI (  Altematc )\nSHRI  H. K.  GUHA\nAll\nIndia\nInstruments\nManufacturers\nand Dealers\nAssociation,\nBombay\nSRRI V. K.  VASUDEVAN\n( Alfcrnots )\nSHRI P. J. Jnous\nThe Associated Cement Companies Ltd, Bombay\nSHRI I). A.  WADIA (  Altwnatr\n)\nSEBI M. R. Josnr\nRcsrarch\n& Development\nOrganization\n( Ministry\nof Dcfencc ), Pune\nSHRI Y. P. PATHAK (  Alternote )\nSHRI  E. K. RAMACHANDRAN\nNational Test House, Calcutta\nP~OF  C.  K. RAMESH\nIndian Institute of T&hnolol;y,\nBombay\nDR R. S.  AYYAR (  Alternate )\nSHRI  M. V. RANGA RAO\nCement Research Institute of India, New Delhi\nDR K. C. NARANG (  Altcmafe )\nDa S. S. REHSI\nCentral\nBuilding\nResearch\nInstitute\n( CSIR ),\nRoorkcc\nSARI J. P. KAUSHISH (  Aftcrn~tr )\nSass\nM. M. D. SETH\nPublFradys;ks\nDepartment,\nGovernment\nOF Uttar",
          "bbox": [
            44.4,
            70.73,
            371.29,
            231.93
          ],
          "block_id": "b9_3",
          "font_size": 7.8,
          "is_bold": true,
          "is_heading": false
        },
        {
          "type": "text",
          "content": "SHRI J. P.  BHATNAGAR (  Alfcrnafe )\nSERI H. c. VERMA\nAssociated\nInstrument\nManufacturers\n( India )\nPrivate-Ltd, New Delhi\nSERI A. V. S~ASTRI  (  Altsmatr\n)",
          "bbox": [
            48.48,
            239.04,
            372.98,
            272.2
          ],
          "block_id": "b9_4",
          "font_size": 7.5,
          "is_bold": true,
          "is_heading": true
        },
        {
          "type": "text",
          "content": "8",
          "bbox": [
            208.56,
            509.93,
            215.76,
            521.8
          ],
          "block_id": "b9_5",
          "font_size": 8.6,
          "is_bold": false,
          "is_heading": false
        }
      ],
      "images": [],
      "dimensions": {
        "width": 419.6400146484375,
        "height": 540.0960083007812
      },
      "image_id_map": {}
    },
    {
      "page_num": 10,
      "blocks": [
        {
          "type": "text",
          "content": "BUREAU OF INDIAN STANDARDS",
          "bbox": [
            41.52,
            43.28,
            184.12,
            52.56
          ],
          "block_id": "b10_0",
          "font_size": 7.9,
          "is_bold": true,
          "is_heading": true
        },
        {
          "type": "text",
          "content": "Manak  Bhavan, 9 Bahadur Shah Zafar fvtarg, NEW DELHI 11Oti\nTelephones: 323 0131. 323 3375, 323 9402\nFax : 91  113234062,\n91 113239399, 91 113239362\nTelegrams  :  Manaksanstha\n(Common to all Offices)",
          "bbox": [
            41.28,
            70.77,
            367.45,
            118.02
          ],
          "block_id": "b10_1",
          "font_size": 7.5,
          "is_bold": true,
          "is_heading": true
        },
        {
          "type": "text",
          "content": "Central Laboratory:\nTelephone",
          "bbox": [
            42.0,
            121.65,
            369.13,
            131.22
          ],
          "block_id": "b10_2",
          "font_size": 7.0,
          "is_bold": true,
          "is_heading": true
        },
        {
          "type": "text",
          "content": "21ot No. 20/9, Site IV, Sahibabad Industrial Area, SAHIBABAD\n201010\n6-77 00 32",
          "bbox": [
            42.0,
            132.45,
            369.61,
            142.02
          ],
          "block_id": "b10_3",
          "font_size": 7.0,
          "is_bold": false,
          "is_heading": false
        },
        {
          "type": "text",
          "content": "Regional OMces:",
          "bbox": [
            41.76,
            146.42,
            104.42,
            154.57
          ],
          "block_id": "b10_4",
          "font_size": 7.0,
          "is_bold": true,
          "is_heading": true
        },
        {
          "type": "text",
          "content": "Central  : Manak  Bhavan, 9 Bahadur Shah Zafar Marg, NEW DELHI 110002\n323 76 17",
          "bbox": [
            41.52,
            156.81,
            370.33,
            168.68
          ],
          "block_id": "b10_5",
          "font_size": 7.5,
          "is_bold": false,
          "is_heading": false
        },
        {
          "type": "text",
          "content": "\u2018Eastern\n:  l/l4\nCIT Scheme VII M, V.I.P. Road, Maniktola, CALCUTTA700054\n337 66 62",
          "bbox": [
            41.52,
            167.85,
            369.61,
            179.72
          ],
          "block_id": "b10_6",
          "font_size": 7.8,
          "is_bold": false,
          "is_heading": false
        },
        {
          "type": "text",
          "content": "Northern : SC0 335-336, Sector 34-A, CHANOIGARH\n160022\n60 36 43",
          "bbox": [
            41.76,
            180.69,
            369.37,
            190.26
          ],
          "block_id": "b10_7",
          "font_size": 7.0,
          "is_bold": false,
          "is_heading": false
        },
        {
          "type": "text",
          "content": "Southern  1  C;.l.T.  Campus, IV Cross Road, CHENNAI\n600113\n235 23 15",
          "bbox": [
            41.76,
            189.69,
            370.57,
            201.56
          ],
          "block_id": "b10_8",
          "font_size": 7.4,
          "is_bold": true,
          "is_heading": true
        },
        {
          "type": "text",
          "content": "twestern\n:  Manakalaya, E9 Behind Mar01 Telephone Exchange, Andheri (East),\n632 92 95\nMUMBAI\n400093",
          "bbox": [
            42.0,
            200.73,
            369.85,
            221.46
          ],
          "block_id": "b10_9",
          "font_size": 7.8,
          "is_bold": false,
          "is_heading": false
        },
        {
          "type": "text",
          "content": "Branch Otkes:",
          "bbox": [
            42.0,
            229.46,
            94.82,
            237.61
          ],
          "block_id": "b10_10",
          "font_size": 7.0,
          "is_bold": true,
          "is_heading": true
        },
        {
          "type": "text",
          "content": "\u2018Pushpak\u2019,\nNurmohamed\nShaikh Marg, Khanpur, AHMEDABAD\n360001\n550 13 46",
          "bbox": [
            41.76,
            241.65,
            370.09,
            251.22
          ],
          "block_id": "b10_11",
          "font_size": 7.0,
          "is_bold": true,
          "is_heading": true
        },
        {
          "type": "text",
          "content": "SPeenya Industrial Area, 1st Stage, Bangalore - Tumkur Road,\n639 49 55\n~BANGALORE 566056",
          "bbox": [
            42.24,
            253.17,
            370.57,
            272.1
          ],
          "block_id": "b10_12",
          "font_size": 7.0,
          "is_bold": true,
          "is_heading": true
        },
        {
          "type": "text",
          "content": "Gangotri Complex, 5th Floor, Bhadbhada Road, T. T. Nagar, BHOPAL 462003\n55 40 21",
          "bbox": [
            42.0,
            273.57,
            370.09,
            283.14
          ],
          "block_id": "b10_13",
          "font_size": 7.0,
          "is_bold": true,
          "is_heading": true
        },
        {
          "type": "text",
          "content": "Plot No. 62-63, Unit VI. Ganga Nagar, BHUBANESHWAR\n751001\n40 36 27",
          "bbox": [
            42.24,
            285.33,
            370.09,
            294.9
          ],
          "block_id": "b10_14",
          "font_size": 7.0,
          "is_bold": true,
          "is_heading": true
        },
        {
          "type": "text",
          "content": "Kalaikathir Buildings, 670 Avinashi Road, COIMBATORE\n641037\n21 01 41",
          "bbox": [
            42.24,
            296.85,
            370.09,
            306.42
          ],
          "block_id": "b10_15",
          "font_size": 7.0,
          "is_bold": true,
          "is_heading": true
        },
        {
          "type": "text",
          "content": "Plot No. 43, Sector 16 A, Mathura Road, FARIDABAD\n121001\n6-26 66 01",
          "bbox": [
            42.48,
            308.61,
            370.09,
            318.18
          ],
          "block_id": "b10_16",
          "font_size": 7.0,
          "is_bold": true,
          "is_heading": true
        },
        {
          "type": "text",
          "content": "Savitri Complex,\n116 G. T. Road, GHAZIABAD\n201001\n6-71 19 96",
          "bbox": [
            42.72,
            319.89,
            370.33,
            329.46
          ],
          "block_id": "b10_17",
          "font_size": 7.0,
          "is_bold": true,
          "is_heading": true
        },
        {
          "type": "text",
          "content": "5315 Ward No. 29, R. G. Barua Road, 5th By-lane, GUWAHATI 761003\n54 11 37",
          "bbox": [
            42.48,
            331.65,
            370.57,
            341.22
          ],
          "block_id": "b10_18",
          "font_size": 7.0,
          "is_bold": true,
          "is_heading": true
        },
        {
          "type": "text",
          "content": "5-6-56C\nL. N. Gupta Marg, Nampally Station Road, HYDERABAD\n500001\n20 10 63",
          "bbox": [
            42.72,
            343.41,
            370.57,
            352.98
          ],
          "block_id": "b10_19",
          "font_size": 7.0,
          "is_bold": true,
          "is_heading": true
        },
        {
          "type": "text",
          "content": "E-52, Chitaranjan Marg, C-Scheme, JAIPUR 302001\n37 29 25",
          "bbox": [
            42.96,
            354.69,
            370.57,
            364.26
          ],
          "block_id": "b10_20",
          "font_size": 7.0,
          "is_bold": true,
          "is_heading": true
        },
        {
          "type": "text",
          "content": "117/416 8, Sarvodaya\nNagar, KANPUR 206005\n21 66 76",
          "bbox": [
            43.2,
            366.45,
            370.81,
            376.02
          ],
          "block_id": "b10_21",
          "font_size": 7.0,
          "is_bold": true,
          "is_heading": true
        },
        {
          "type": "text",
          "content": "Seth Bhawan, 2nd Floor, Behind Leela Cinema, Naval Kishore Road,\n23 69 23\nLUCKNOW 226001",
          "bbox": [
            42.96,
            378.21,
            371.05,
            397.14
          ],
          "block_id": "b10_22",
          "font_size": 7.0,
          "is_bold": true,
          "is_heading": true
        },
        {
          "type": "text",
          "content": "Patliputra Industrial Estate, PATNA 600013",
          "bbox": [
            43.2,
            399.09,
            194.17,
            408.66
          ],
          "block_id": "b10_23",
          "font_size": 7.0,
          "is_bold": false,
          "is_heading": false
        },
        {
          "type": "text",
          "content": "26 23 05",
          "bbox": [
            338.16,
            400.34,
            371.05,
            408.49
          ],
          "block_id": "b10_27",
          "font_size": 7.0,
          "is_bold": true,
          "is_heading": true
        },
        {
          "type": "text",
          "content": "T. C. No. 1411421, University\nP. 0. Palayam,\nTHIRUVANANTHAPURAM\n695034",
          "bbox": [
            42.96,
            410.85,
            202.81,
            429.78
          ],
          "block_id": "b10_24",
          "font_size": 7.0,
          "is_bold": false,
          "is_heading": false
        },
        {
          "type": "text",
          "content": "621\n17",
          "bbox": [
            342.24,
            411.86,
            372.01,
            420.01
          ],
          "block_id": "b10_28",
          "font_size": 7.0,
          "is_bold": true,
          "is_heading": true
        },
        {
          "type": "text",
          "content": "NIT Building, Second Floor, Gokulpat Market, NAGPUR 440010",
          "bbox": [
            43.44,
            432.21,
            270.01,
            441.78
          ],
          "block_id": "b10_25",
          "font_size": 7.0,
          "is_bold": false,
          "is_heading": false
        },
        {
          "type": "text",
          "content": "52 51 71",
          "bbox": [
            338.16,
            433.22,
            371.05,
            441.37
          ],
          "block_id": "b10_29",
          "font_size": 7.0,
          "is_bold": true,
          "is_heading": true
        },
        {
          "type": "text",
          "content": "Institution of Engineers  (  India  )  Building, 1332 Shiiaji Nagar, PUNE 411005",
          "bbox": [
            43.44,
            441.93,
            315.37,
            453.8
          ],
          "block_id": "b10_26",
          "font_size": 7.6,
          "is_bold": false,
          "is_heading": false
        },
        {
          "type": "text",
          "content": "32 36 35",
          "bbox": [
            338.4,
            444.74,
            371.53,
            452.89
          ],
          "block_id": "b10_30",
          "font_size": 7.0,
          "is_bold": true,
          "is_heading": true
        },
        {
          "type": "text",
          "content": "\u2018Sales Office is at 5 Chowringhes\nApproach, P. 0. Princep Street,\nCALCUTTA 700072",
          "bbox": [
            43.44,
            467.73,
            280.57,
            486.9
          ],
          "block_id": "b10_31",
          "font_size": 7.0,
          "is_bold": false,
          "is_heading": false
        },
        {
          "type": "text",
          "content": ",27 10 65",
          "bbox": [
            336.96,
            477.86,
            371.29,
            486.01
          ],
          "block_id": "b10_34",
          "font_size": 7.0,
          "is_bold": true,
          "is_heading": true
        },
        {
          "type": "text",
          "content": "tSales\nOffice is at  Novelty Chambers, Grant  Road, MUMBAI\n400007",
          "bbox": [
            43.68,
            488.85,
            291.61,
            498.42
          ],
          "block_id": "b10_32",
          "font_size": 7.0,
          "is_bold": true,
          "is_heading": true
        },
        {
          "type": "text",
          "content": "309 65 26",
          "bbox": [
            334.32,
            489.38,
            371.53,
            497.53
          ],
          "block_id": "b10_35",
          "font_size": 7.0,
          "is_bold": true,
          "is_heading": true
        },
        {
          "type": "text",
          "content": "*Sales\nOffice is at \u2018F\u2019 Block, Unity Building, Narashimaraja\nSquare,\nBANGALORE\n560002",
          "bbox": [
            43.68,
            500.61,
            284.42,
            519.54
          ],
          "block_id": "b10_33",
          "font_size": 7.0,
          "is_bold": false,
          "is_heading": false
        },
        {
          "type": "text",
          "content": "222 39 71",
          "bbox": [
            334.56,
            500.9,
            371.53,
            509.05
          ],
          "block_id": "b10_36",
          "font_size": 7.0,
          "is_bold": true,
          "is_heading": true
        },
        {
          "type": "text",
          "content": "Printed  at New India Printing Press, Khurja, India",
          "bbox": [
            215.52,
            532.05,
            373.94,
            541.62
          ],
          "block_id": "b10_37",
          "font_size": 7.0,
          "is_bold": true,
          "is_heading": true
        }
      ],
      "images": [],
      "dimensions": {
        "width": 409.6400146484375,
        "height": 568.0960083007812
      },
      "image_id_map": {}
    },
    {
      "page_num": 11,
      "blocks": [
        {
          "type": "text",
          "content": "AMENDMENT\nNO.  1\nNOVEMBER\n1984",
          "bbox": [
            91.44,
            29.79,
            342.0,
            45.62
          ],
          "block_id": "b11_0",
          "font_size": 11.5,
          "is_bold": true,
          "is_heading": true
        },
        {
          "type": "text",
          "content": "TO",
          "bbox": [
            204.72,
            49.65,
            219.17,
            59.2
          ],
          "block_id": "b11_1",
          "font_size": 7.9,
          "is_bold": true,
          "is_heading": true
        },
        {
          "type": "text",
          "content": "IS I 9459 - 1980 SPECIFICATION FOR APPARATUS\nFOR USE IN MEASUREMENT\nOF  LENGTH\nCHANGE OF HARDENED CEMENT\nPASTE, MORTAR AND CONCRETE",
          "bbox": [
            53.76,
            64.01,
            352.08,
            121.29
          ],
          "block_id": "b11_2",
          "font_size": 11.5,
          "is_bold": true,
          "is_heading": true
        },
        {
          "type": "text",
          "content": "Alterdons",
          "bbox": [
            173.28,
            133.41,
            215.33,
            142.96
          ],
          "block_id": "b11_3",
          "font_size": 7.9,
          "is_bold": true,
          "is_heading": true
        },
        {
          "type": "text",
          "content": "j  Page 4, clause  3.1,  J;fth sentem ) -\nSubstitute the following for the\nexisting matter:",
          "bbox": [
            44.88,
            154.28,
            368.16,
            175.09
          ],
          "block_id": "b11_4",
          "font_size": 8.6,
          "is_bold": true,
          "is_heading": true
        },
        {
          "type": "text",
          "content": "\u2018  The end of the yoke opposite to the micrometer end of the reference bar\nshall be provided with an anvil having a cylindrical\nor conical recess.\u2019",
          "bbox": [
            45.36,
            179.05,
            367.92,
            200.53
          ],
          "block_id": "b11_5",
          "font_size": 8.6,
          "is_bold": false,
          "is_heading": false
        },
        {
          "type": "text",
          "content": "(  Page  4,  clause  3.1.1,  line  5 ) -\nSubstitute  c  yoke  \u2018for  \u2018  frame \u2018.",
          "bbox": [
            70.32,
            205.21,
            340.32,
            217.08
          ],
          "block_id": "b11_6",
          "font_size": 8.6,
          "is_bold": true,
          "is_heading": true
        },
        {
          "type": "text",
          "content": "(  Page  4,  clause  3.2,  line  4 ) -\nSubstitute  \u2018  12 mm  \u2018for  \u2018  20 mm \u2018.",
          "bbox": [
            70.56,
            222.25,
            348.48,
            234.12
          ],
          "block_id": "b11_7",
          "font_size": 8.6,
          "is_bold": true,
          "is_heading": true
        },
        {
          "type": "text",
          "content": "(  Page  5,  Fig.  1 ) -\nSubstitute  \u2018  YOKE\n\u2018for  \u2018  PILLAR\n\u2018.",
          "bbox": [
            70.8,
            238.33,
            321.84,
            250.2
          ],
          "block_id": "b11_8",
          "font_size": 8.6,
          "is_bold": true,
          "is_heading": true
        },
        {
          "type": "text",
          "content": "(  Page 6, Fig.\n2 ) -\nSubstitute the figure given on page 2 for the\nexisting figure.",
          "bbox": [
            45.6,
            255.8,
            368.88,
            276.61
          ],
          "block_id": "b11_9",
          "font_size": 8.6,
          "is_bold": true,
          "is_heading": true
        },
        {
          "type": "text",
          "content": "[  Page 7, Tuble  1, co1 3, Sl Jvo. (i) ] -Substitute\n\u2018 ISLC 150 or ISMC 150\nconforming to IS : 226.1975+\u2019  for the existing matter.",
          "bbox": [
            45.6,
            282.68,
            371.58,
            303.49
          ],
          "block_id": "b11_10",
          "font_size": 8.4,
          "is_bold": true,
          "is_heading": true
        }
      ],
      "images": [],
      "dimensions": {
        "width": 398.44000244140625,
        "height": 566.0960083007812
      },
      "image_id_map": {}
    },
    {
      "page_num": 12,
      "blocks": [
        {
          "type": "text",
          "content": "SPECIMEN\nSECTION\nXX",
          "bbox": [
            125.28,
            131.39,
            274.95,
            144.4
          ],
          "block_id": "b12_1",
          "font_size": 7.0,
          "is_bold": true,
          "is_heading": true
        },
        {
          "type": "text",
          "content": "\\",
          "bbox": [
            118.56,
            146.53,
            123.36,
            158.4
          ],
          "block_id": "b12_0",
          "font_size": 8.6,
          "is_bold": false,
          "is_heading": false
        },
        {
          "type": "text",
          "content": "w-70\n-",
          "bbox": [
            211.92,
            151.89,
            257.91,
            160.0
          ],
          "block_id": "b12_2",
          "font_size": 7.0,
          "is_bold": true,
          "is_heading": true
        },
        {
          "type": "text",
          "content": "LMICROMEIER\nSCREW\nGAUGE",
          "bbox": [
            233.04,
            376.05,
            295.11,
            392.8
          ],
          "block_id": "b12_3",
          "font_size": 7.0,
          "is_bold": true,
          "is_heading": true
        },
        {
          "type": "text",
          "content": "VIEW\nY",
          "bbox": [
            222.24,
            404.85,
            260.55,
            412.96
          ],
          "block_id": "b12_4",
          "font_size": 7.0,
          "is_bold": true,
          "is_heading": true
        },
        {
          "type": "text",
          "content": "All  dimensions in millimetres.",
          "bbox": [
            141.36,
            428.85,
            248.7,
            437.09
          ],
          "block_id": "b12_5",
          "font_size": 7.0,
          "is_bold": true,
          "is_heading": true
        },
        {
          "type": "text",
          "content": "Fra.2\nTYPICAL SET UP  FOR~RYINO\nXIIRINKAGE\nAND MOISTURE\nBAWEMENTTESTONHEAVYSPECIMEN",
          "bbox": [
            53.76,
            441.6,
            331.06,
            461.55
          ],
          "block_id": "b12_6",
          "font_size": 8.6,
          "is_bold": true,
          "is_heading": true
        },
        {
          "type": "text",
          "content": "2",
          "bbox": [
            193.68,
            513.12,
            200.53,
            523.42
          ],
          "block_id": "b12_7",
          "font_size": 8.6,
          "is_bold": true,
          "is_heading": true
        }
      ],
      "images": [],
      "dimensions": {
        "width": 420.6400146484375,
        "height": 575.0960083007812
      },
      "image_id_map": {}
    },
    {
      "page_num": 13,
      "blocks": [
        {
          "type": "text",
          "content": "AMENDMENT\nNO. 2 APRIL\n1993\nTO\nIS 9459 : 1980 SPECIFICATION\nFOR APPARATUS\nFOR\nUSE IN MEASUREMENT\nOF LENGTH CHANGE OF\nHARDENED CEMENT PASTE, MORTAR AND\nCONCRETE",
          "bbox": [
            49.44,
            34.65,
            360.98,
            116.49
          ],
          "block_id": "b13_0",
          "font_size": 10.6,
          "is_bold": false,
          "is_heading": false
        },
        {
          "type": "text",
          "content": "(  Puge 6, clause 33) -Substitute\nthe following for the existing clause:",
          "bbox": [
            57.36,
            122.01,
            340.32,
            134.52
          ],
          "block_id": "b13_1",
          "font_size": 9.6,
          "is_bold": true,
          "is_heading": true
        },
        {
          "type": "text",
          "content": "\u20183.3 Except where the tolerances ate specifically\nindicated against the specified\ndimensions,\nall dimensions\nshall be taken as nominal dimensions\nwith tolerances\nas laid  down  in IS 2102 ( Part 1)  :  1980*.\u2019",
          "bbox": [
            42.24,
            140.04,
            362.88,
            173.32
          ],
          "block_id": "b13_2",
          "font_size": 8.6,
          "is_bold": true,
          "is_heading": false
        },
        {
          "type": "text",
          "content": "(  Page  6,jbor-nofe)\n-\nInsert the following foot-note at the cud:",
          "bbox": [
            58.08,
            177.96,
            310.8,
            189.48
          ],
          "block_id": "b13_3",
          "font_size": 8.6,
          "is_bold": true,
          "is_heading": true
        },
        {
          "type": "text",
          "content": "\u201cGeneral\ntolerances for dimensions and form and position: Part 1 General tolrranc~s for linear and",
          "bbox": [
            43.44,
            198.29,
            367.25,
            205.6
          ],
          "block_id": "b13_4",
          "font_size": 6.2,
          "is_bold": true,
          "is_heading": true
        },
        {
          "type": "text",
          "content": "angular dimensions ( rccrmd revision ).\u201c",
          "bbox": [
            42.96,
            209.33,
            173.09,
            216.64
          ],
          "block_id": "b13_5",
          "font_size": 6.2,
          "is_bold": true,
          "is_heading": true
        },
        {
          "type": "text",
          "content": "(Page\n7,  Table  1)  :",
          "bbox": [
            58.08,
            222.65,
            139.44,
            234.52
          ],
          "block_id": "b13_6",
          "font_size": 8.6,
          "is_bold": true,
          "is_heading": true
        },
        {
          "type": "text",
          "content": "i) Substitute\n\u2018Yoke\u2019/or\n\u2018Pillars\u2019  in co1  2 of Sl No. (ii).",
          "bbox": [
            60.72,
            239.64,
            273.6,
            251.16
          ],
          "block_id": "b13_7",
          "font_size": 8.6,
          "is_bold": true,
          "is_heading": true
        },
        {
          "type": "text",
          "content": "ii) Delete \u2018conforming\nto relevant Indian Standards\u2019 from the NOTE.",
          "bbox": [
            58.32,
            256.68,
            328.8,
            268.2
          ],
          "block_id": "b13_8",
          "font_size": 8.6,
          "is_bold": false,
          "is_heading": false
        },
        {
          "type": "text",
          "content": "(CED2)",
          "bbox": [
            43.2,
            503.4,
            72.72,
            514.92
          ],
          "block_id": "b13_9",
          "font_size": 8.6,
          "is_bold": false,
          "is_heading": false
        },
        {
          "type": "text",
          "content": "Prmted  at  New  India  Prmttng  Press,  Khqa,\nIndia",
          "bbox": [
            216.72,
            516.41,
            355.88,
            528.28
          ],
          "block_id": "b13_10",
          "font_size": 6.2,
          "is_bold": true,
          "is_heading": true
        }
      ],
      "images": [],
      "dimensions": {
        "width": 411.6400146484375,
        "height": 570.0960083007812
      },
      "image_id_map": {}
    }
  ],
  "tables": [],
  "images": []
}