{
  "pages": [
    {
      "page_num": 1,
      "blocks": [
        {
          "type": "text",
          "content": "( Reaffirmed 1996 )",
          "bbox": [
            274.47,
            49.86,
            354.99,
            62.25
          ],
          "block_id": "b1_9",
          "font_size": 9.0,
          "is_bold": true,
          "is_heading": true
        },
        {
          "type": "text",
          "content": "Indian Standard",
          "bbox": [
            122.16,
            57.64,
            242.04,
            75.16
          ],
          "block_id": "b1_1",
          "font_size": 15.8,
          "is_bold": true,
          "is_heading": true
        },
        {
          "type": "text",
          "content": "CODE OF PRACTICE FOR\nLAYING BITUMEN MASTIC FLOORING",
          "bbox": [
            52.8,
            86.22,
            314.58,
            120.39
          ],
          "block_id": "b1_2",
          "font_size": 13.2,
          "is_bold": false,
          "is_heading": true
        },
        {
          "type": "text",
          "content": "( Second Revision )",
          "bbox": [
            115.2,
            130.36,
            253.8,
            147.88
          ],
          "block_id": "b1_3",
          "font_size": 15.8,
          "is_bold": true,
          "is_heading": true
        },
        {
          "type": "text",
          "content": "Third  Reprint DECEMBER 1998",
          "bbox": [
            119.52,
            158.92,
            253.44,
            169.72
          ],
          "block_id": "b1_4",
          "font_size": 9.1,
          "is_bold": true,
          "is_heading": true
        },
        {
          "type": "text",
          "content": "UDC 69.025.331.2\n: 69.001.3",
          "bbox": [
            114.24,
            242.92,
            249.12,
            253.0
          ],
          "block_id": "b1_5",
          "font_size": 8.6,
          "is_bold": false,
          "is_heading": false
        },
        {
          "type": "text",
          "content": "Q Copyright 1978",
          "bbox": [
            148.08,
            455.32,
            225.36,
            465.4
          ],
          "block_id": "b1_6",
          "font_size": 8.6,
          "is_bold": false,
          "is_heading": false
        },
        {
          "type": "text",
          "content": "BUREAU\nOF\nINDIAN\nSTANDARDS\nMANAK\nBHAVAN,\n9\nBAHADUR\nSHAH\nZAFAR\nMARG\nNEW DELHI\n110002",
          "bbox": [
            65.28,
            471.64,
            301.21,
            501.51
          ],
          "block_id": "b1_7",
          "font_size": 9.6,
          "is_bold": true,
          "is_heading": true
        },
        {
          "type": "text",
          "content": "Gr3",
          "bbox": [
            27.36,
            519.23,
            44.16,
            531.1
          ],
          "block_id": "b1_0",
          "font_size": 8.6,
          "is_bold": false,
          "is_heading": false
        },
        {
          "type": "text",
          "content": "my 1978",
          "bbox": [
            303.36,
            519.88,
            345.12,
            529.96
          ],
          "block_id": "b1_8",
          "font_size": 8.6,
          "is_bold": false,
          "is_heading": false
        }
      ],
      "images": [],
      "dimensions": {
        "width": 426.2079772949219,
        "height": 569.0559692382812
      },
      "image_id_map": {}
    },
    {
      "page_num": 2,
      "blocks": [
        {
          "type": "text",
          "content": "Is :  1196  -  197%",
          "bbox": [
            282.96,
            21.92,
            353.28,
            35.11
          ],
          "block_id": "b2_0",
          "font_size": 9.1,
          "is_bold": false,
          "is_heading": false
        },
        {
          "type": "text",
          "content": "Indian Standard",
          "bbox": [
            126.48,
            44.97,
            254.76,
            66.33
          ],
          "block_id": "b2_1",
          "font_size": 18.7,
          "is_bold": false,
          "is_heading": true
        },
        {
          "type": "text",
          "content": "CODE OF PRACTICE FOR",
          "bbox": [
            104.4,
            77.05,
            272.0,
            90.48
          ],
          "block_id": "b2_2",
          "font_size": 11.5,
          "is_bold": false,
          "is_heading": false
        },
        {
          "type": "text",
          "content": "LAYING BITUMEN MASTIC FLOORING",
          "bbox": [
            55.68,
            94.33,
            310.64,
            107.76
          ],
          "block_id": "b2_3",
          "font_size": 11.5,
          "is_bold": false,
          "is_heading": false
        },
        {
          "type": "text",
          "content": "( Second Revision )",
          "bbox": [
            113.52,
            117.45,
            264.84,
            138.81
          ],
          "block_id": "b2_4",
          "font_size": 18.7,
          "is_bold": false,
          "is_heading": true
        },
        {
          "type": "text",
          "content": "Flooring\nand Plastering\nSectional\nCommittee,\nBDC 5",
          "bbox": [
            70.08,
            153.68,
            303.9,
            163.28
          ],
          "block_id": "b2_5",
          "font_size": 7.9,
          "is_bold": true,
          "is_heading": true
        },
        {
          "type": "text",
          "content": "Chairman\nRepresenting",
          "bbox": [
            60.48,
            174.8,
            264.06,
            184.16
          ],
          "block_id": "b2_6",
          "font_size": 7.0,
          "is_bold": true,
          "is_heading": true
        },
        {
          "type": "text",
          "content": "SHRI 0. P. MITTAL\nCentral Public Works Department,\nNew Delhi",
          "bbox": [
            25.2,
            184.79,
            331.22,
            193.87
          ],
          "block_id": "b2_7",
          "font_size": 7.0,
          "is_bold": false,
          "is_heading": false
        },
        {
          "type": "text",
          "content": "Members",
          "bbox": [
            60.48,
            196.64,
            90.3,
            205.04
          ],
          "block_id": "b2_8",
          "font_size": 7.0,
          "is_bold": true,
          "is_heading": true
        },
        {
          "type": "text",
          "content": "SHRI  E. T. ANTIA\nConcrete Association of India, Bombay\nSARI M. G. DANDAVATE ( Alternate)\nBRIG P. M.  BHATI.4\nInstitution of Engineers ( India ), Calcutta\nSIIRI A. K. BX~TTUXARYYA\nNational Test House, Calcutta\nS~rrtl 13. C.  DAM\n(  Alternate )\nSHRT. DINFSH A. CliOmmI\nArcoy Industries, Ahmadabad\nSHRI  Rasrx~~r, A. CHOESHI (  Altemafe )\nL>BPUTY DIlt~:l\u20191.011\nSTANDARDS\nRailway Board ( Ministry of Railways\n)\n(  I: & S ), KLJSO, LUCKNOW\nD~:~x:TY D~~CTOR ( ARCH 1,\nRDSO,\nLi-criaow\n(  Alternate )\nDIRP.cT<r!L\nMah;z;ttra\nEngineering\nResearch\nInstitute,",
          "bbox": [
            24.72,
            205.67,
            346.33,
            301.52
          ],
          "block_id": "b2_9",
          "font_size": 7.8,
          "is_bold": true,
          "is_heading": false
        },
        {
          "type": "text",
          "content": "K 1.: s 1: A 1: (\u2019 1,\nOFFICEH,\nMavl:nr.~~, \u2018I\u2019XSTING DIVISION (  Alternate )\nSHJLI R. G. Goxii.~~,e\nBureau\nof\nPublic\nEnterprises\n( Ministry\nof",
          "bbox": [
            24.72,
            308.87,
            348.73,
            333.44
          ],
          "block_id": "b2_10",
          "font_size": 7.0,
          "is_bold": false,
          "is_heading": false
        },
        {
          "type": "text",
          "content": "Srlltl S. S.  &IMAL\n(Alternate  j\nFinance )",
          "bbox": [
            40.32,
            333.11,
            213.85,
            349.28
          ],
          "block_id": "b2_11",
          "font_size": 7.0,
          "is_bold": true,
          "is_heading": true
        },
        {
          "type": "text",
          "content": "SHI~I Ii.  V.  GI~RIJSWAXY\nIndian Oil Corporation\nLtd, New Delhi\nSnar G. V. PAWGARKAR (  Alternate )\nSH~I  N.  HAIIILAL\nSHRI H.J. VAKEEL (Alternate)\nOxychloride\nFlooring Products Ltd, Bombay",
          "bbox": [
            24.0,
            348.71,
            325.69,
            380.83
          ],
          "block_id": "b2_12",
          "font_size": 7.0,
          "is_bold": true,
          "is_heading": true
        },
        {
          "type": "text",
          "content": "SHRI s.c.&J?OOR\nSHRI A. C. KAPOOB (  Altmzufe )\nModern Tiles 8s Marble, New Delhi",
          "bbox": [
            23.76,
            380.87,
            294.98,
            397.28
          ],
          "block_id": "b2_13",
          "font_size": 7.0,
          "is_bold": true,
          "is_heading": true
        },
        {
          "type": "text",
          "content": "DR I. V.  KRISHNAWJRTY\nSHRI K. E. S. MANI\nNational\nRubber Manufacturers\u2019\nLtd, Calcutta\nBhor Industries\nLtd, Bombay\nSHHI RA~ESH D.  PATEL (  Al&mate )\nSIIRI  G.  R. MIRCIIANDANI\nEngineer-in-Chief\u2019s\nBranch, Army Headquarters,\nNew Delhi\nMAJ  V. S. RAO  (  Altem~&)\n( Continued on page 2)",
          "bbox": [
            23.28,
            396.71,
            346.14,
            452.96
          ],
          "block_id": "b2_14",
          "font_size": 7.3,
          "is_bold": true,
          "is_heading": false
        },
        {
          "type": "text",
          "content": "@\nCiq+glu\n1978",
          "bbox": [
            154.32,
            462.08,
            223.41,
            470.72
          ],
          "block_id": "b2_15",
          "font_size": 7.0,
          "is_bold": true,
          "is_heading": true
        },
        {
          "type": "text",
          "content": "BUREAU\nOF  INDIAN\nSTANDARDS\nThis  publication\nis protected\nunder\nthe  Zadiaa Ck@v&ht Act ( XIV\nof 1957 ) and\nreproduction\nin whole or in part by any means except with written\npermission\nof the\npublkher\nshall be  deemed to be an infringement of copyright under the said Act.",
          "bbox": [
            29.28,
            474.32,
            344.37,
            514.16
          ],
          "block_id": "b2_16",
          "font_size": 7.4,
          "is_bold": true,
          "is_heading": false
        }
      ],
      "images": [],
      "dimensions": {
        "width": 421.8479919433594,
        "height": 576.0559692382812
      },
      "image_id_map": {}
    },
    {
      "page_num": 3,
      "blocks": [
        {
          "type": "text",
          "content": "B t  ii96 -  1978",
          "bbox": [
            46.32,
            15.78,
            115.2,
            31.71
          ],
          "block_id": "b3_0",
          "font_size": 11.1,
          "is_bold": true,
          "is_heading": true
        },
        {
          "type": "text",
          "content": "(  Conliaaedfrom @ags 1 )",
          "bbox": [
            45.6,
            40.41,
            127.45,
            51.29
          ],
          "block_id": "b3_1",
          "font_size": 7.4,
          "is_bold": false,
          "is_heading": false
        },
        {
          "type": "text",
          "content": "Representing",
          "bbox": [
            245.52,
            55.64,
            284.46,
            63.58
          ],
          "block_id": "b3_9",
          "font_size": 7.0,
          "is_bold": false,
          "is_heading": false
        },
        {
          "type": "text",
          "content": "Mnnbcrs\nDa  MOHAN  RAI",
          "bbox": [
            45.84,
            56.6,
            109.97,
            75.79
          ],
          "block_id": "b3_2",
          "font_size": 7.6,
          "is_bold": true,
          "is_heading": true
        },
        {
          "type": "text",
          "content": "Central\nBuilding\nResearch\nInstitute\n( CSIR ),\nRoorkee",
          "bbox": [
            185.28,
            66.35,
            372.97,
            82.62
          ],
          "block_id": "b3_10",
          "font_size": 7.0,
          "is_bold": false,
          "is_heading": false
        },
        {
          "type": "text",
          "content": "SHRI R. K. JAIN (  Alternate)\nSHRI M. V. MURUCUPPAN\nSHRI R. SRINIVASAN (  Alternate)\nSHRI H. M. NANDKEOLYaR\nSHRI K. P. Sxaa\n(  Alternate  j\nSHEI 0. P. RATRA\nSHRI G. C. SIL~RYA",
          "bbox": [
            45.6,
            82.91,
            176.94,
            138.54
          ],
          "block_id": "b3_3",
          "font_size": 7.5,
          "is_bold": false,
          "is_heading": false
        },
        {
          "type": "text",
          "content": "Coromandel\nProdorite Pvt Ltd, Madras",
          "bbox": [
            185.04,
            90.11,
            331.7,
            98.22
          ],
          "block_id": "b3_4",
          "font_size": 7.0,
          "is_bold": false,
          "is_heading": false
        },
        {
          "type": "text",
          "content": "India Linoleums Ltd, 24 Parganas ( West Bengal )",
          "bbox": [
            184.8,
            105.95,
            373.21,
            114.06
          ],
          "block_id": "b3_5",
          "font_size": 7.0,
          "is_bold": false,
          "is_heading": false
        },
        {
          "type": "text",
          "content": "National Buildings Organization,\nNew Delhi\nIndian Institute of Architects,\nBombay\nSHRI D. B. Sxrr (  Alternate  I )\nSERI S. B. SEIFLOXANY (  AlterMte  II )\nS u P E a I N T E N D I N Q ENGINEER Public Works Department,\nGovernment\nof Tamil\n( PLANNINO AND DESIGN  CIRCLJJ )\nNadu\nEXEOUTIVE\nENOINEER\n( BUILDING CENTRE DIVISION ) (  Alternak )\nSUPERINTENDINO SURVEYOR\nOB Central Public Works Department,\nNew Delhi\nWORKS ( ND2 )\nSURVEYOR OF WORKS I (  Alternate )\nSanr D. AJITRI Sma.4,\nDirector General, IS1 (  Ex-ofiio\nMember )\nDirector\n( Civ Engg )",
          "bbox": [
            46.08,
            122.03,
            370.57,
            225.66
          ],
          "block_id": "b3_6",
          "font_size": 7.3,
          "is_bold": true,
          "is_heading": false
        },
        {
          "type": "text",
          "content": "Secretary",
          "bbox": [
            196.8,
            228.35,
            229.94,
            236.46
          ],
          "block_id": "b3_7",
          "font_size": 7.0,
          "is_bold": false,
          "is_heading": false
        },
        {
          "type": "text",
          "content": "SHRI SU~ESH MALKANI\nAssistant Director\n( Civ Engg ), IS1",
          "bbox": [
            144.72,
            239.39,
            277.93,
            255.42
          ],
          "block_id": "b3_8",
          "font_size": 7.0,
          "is_bold": false,
          "is_heading": false
        },
        {
          "type": "text",
          "content": "Bituminous\nFlooring\nSubcommittee,\nBDC 5:5",
          "bbox": [
            111.84,
            267.82,
            309.6,
            279.35
          ],
          "block_id": "b3_11",
          "font_size": 8.6,
          "is_bold": false,
          "is_heading": false
        },
        {
          "type": "text",
          "content": "Convener",
          "bbox": [
            85.2,
            291.54,
            115.5,
            299.37
          ],
          "block_id": "b3_12",
          "font_size": 7.0,
          "is_bold": true,
          "is_heading": true
        },
        {
          "type": "text",
          "content": "P~OF C. G. SWAMINATHAN\nCentral\nRoad\nResearch\nInstitute (CSIR\n), New\nDelhi",
          "bbox": [
            48.24,
            302.03,
            373.93,
            318.06
          ],
          "block_id": "b3_13",
          "font_size": 7.0,
          "is_bold": false,
          "is_heading": false
        },
        {
          "type": "text",
          "content": "M.?mbcrS",
          "bbox": [
            85.2,
            321.56,
            115.74,
            329.5
          ],
          "block_id": "b3_14",
          "font_size": 7.0,
          "is_bold": false,
          "is_heading": false
        },
        {
          "type": "text",
          "content": "ADDITIONAL DIREOTOR\nRailway Board ( Ministry of Railways )\nSHRI G. T. BHIDE\nDB R. S. RAT~A (  Alternate )\nNational Buildings Organization,\nNew Delhi",
          "bbox": [
            48.96,
            331.79,
            352.58,
            356.14
          ],
          "block_id": "b3_15",
          "font_size": 7.0,
          "is_bold": false,
          "is_heading": false
        },
        {
          "type": "text",
          "content": "SHRI G. C. DAS\nNational\nTest House, Calcutta\nDa D. K. DAS (Alternate  )\nSHRI A. Y. GUPTE\nHindustan Petroleum Corporation\nLtd, Bombay\nSHRI  C. V. RAIUASWAMY (  Alternate )\nDR G. W.  KAPSE\nCent~~or~~lding\nResearch\nInstitute\n( CSIR ),",
          "bbox": [
            48.72,
            355.79,
            374.41,
            395.82
          ],
          "block_id": "b3_16",
          "font_size": 7.0,
          "is_bold": true,
          "is_heading": false
        },
        {
          "type": "text",
          "content": "SHRI M. ASLAM (  Alternate )\nSH~I D. R. KOHLI\nSHRI K. C. CHOPRA (  Alternate )\nBharat Refineries Ltd, Bombay",
          "bbox": [
            49.2,
            403.31,
            303.85,
            427.42
          ],
          "block_id": "b3_17",
          "font_size": 7.0,
          "is_bold": false,
          "is_heading": false
        },
        {
          "type": "text",
          "content": "SHRI G. R. MIRCHANDANI\nMic\ntry\nof\nDefence\n( Engineer-in-Chief\n\u2018S",
          "bbox": [
            48.72,
            427.07,
            376.81,
            435.18
          ],
          "block_id": "b3_18",
          "font_size": 7.0,
          "is_bold": false,
          "is_heading": false
        },
        {
          "type": "text",
          "content": "\u2019\nMAJ  V. S. RAO (Alternate  )\nBranch )",
          "bbox": [
            49.44,
            435.23,
            237.85,
            452.06
          ],
          "block_id": "b3_19",
          "font_size": 8.6,
          "is_bold": true,
          "is_heading": true
        },
        {
          "type": "text",
          "content": "SHRI T. K. ROY\nShal~imT:utar\nProducts\n( 1935)\nPvt\nLtd,",
          "bbox": [
            49.68,
            451.07,
            373.45,
            459.42
          ],
          "block_id": "b3_20",
          "font_size": 7.0,
          "is_bold": false,
          "is_heading": false
        },
        {
          "type": "text",
          "content": "SHRI B. K. BHATTACHA~YA (  Alternate )\nSIJRVEYOR\nOF WORKS ( NDZ )\nCentral Public Works Department,\nNew Delhi",
          "bbox": [
            50.64,
            466.91,
            360.26,
            482.94
          ],
          "block_id": "b3_21",
          "font_size": 7.0,
          "is_bold": true,
          "is_heading": true
        },
        {
          "type": "text",
          "content": "2",
          "bbox": [
            211.44,
            499.9,
            217.92,
            511.43
          ],
          "block_id": "b3_22",
          "font_size": 8.6,
          "is_bold": false,
          "is_heading": false
        }
      ],
      "images": [],
      "dimensions": {
        "width": 415.1679992675781,
        "height": 567.0559692382812
      },
      "image_id_map": {}
    },
    {
      "page_num": 4,
      "blocks": [
        {
          "type": "text",
          "content": "Indian Standard",
          "bbox": [
            125.28,
            57.42,
            253.62,
            77.98
          ],
          "block_id": "b4_0",
          "font_size": 17.0,
          "is_bold": true,
          "is_heading": true
        },
        {
          "type": "text",
          "content": "CODE OF PRACTICE FOR\nLAYING BITUMEN MASTIC FLOORING",
          "bbox": [
            57.6,
            87.42,
            316.19,
            118.77
          ],
          "block_id": "b4_1",
          "font_size": 12.5,
          "is_bold": false,
          "is_heading": true
        },
        {
          "type": "text",
          "content": "( Second Revision )",
          "bbox": [
            115.2,
            129.66,
            262.02,
            150.22
          ],
          "block_id": "b4_2",
          "font_size": 17.0,
          "is_bold": true,
          "is_heading": true
        },
        {
          "type": "text",
          "content": "0.\nFOREWORD",
          "bbox": [
            127.44,
            171.15,
            222.0,
            184.11
          ],
          "block_id": "b4_3",
          "font_size": 11.5,
          "is_bold": true,
          "is_heading": true
        },
        {
          "type": "text",
          "content": "0.1 This Indian Standard ( Second Revision ) was adopted by the Indian\nStandards Institution on 31 January\n1978, after the draft finalized by the\nFlooring and Plastering Sectional Committee had been approved by the\nCivil Engineering Division Council.",
          "bbox": [
            25.92,
            194.98,
            348.72,
            235.21
          ],
          "block_id": "b4_4",
          "font_size": 8.6,
          "is_bold": true,
          "is_heading": false
        },
        {
          "type": "text",
          "content": "0.2 This standard was first published in 1958 and subsequently revised in\n1968.\nThe second revision has been based  on  further experience gained\nduring course of these years in the use of bitumen mastic.\nThe salient\nfeatures of this revision include information to the users regarding resis-\ntance of bitumen mastic floor finishes to chemical attack so that the use of\nbitumen mastic is fully appreciated\nin practice.\nProvisions for surface\narmouring to increase abrasion resistance for industrial purposes have also\nbeen incorporated.\nInformation\nregarding\nprovision\nof an\nisolating\nmembrane has been suitably elaborated.",
          "bbox": [
            26.16,
            245.62,
            350.16,
            335.29
          ],
          "block_id": "b4_5",
          "font_size": 8.6,
          "is_bold": true,
          "is_heading": false
        },
        {
          "type": "text",
          "content": "0.3 In the formulation of this standard due weightage has been given to\ninternational co-ordination among the standards and practices prevailing\nin different countries in addition to relating it to the practices in the field\nin this country.\nThis has been met by referring to BS CP 204  :  1965\n\u2019 In situ  floor finishes  \u2019  issued by the British Standards Institution.",
          "bbox": [
            25.44,
            345.46,
            349.92,
            396.26
          ],
          "block_id": "b4_6",
          "font_size": 8.9,
          "is_bold": true,
          "is_heading": false
        },
        {
          "type": "text",
          "content": "0.3.1 This code of practice represents a standard of good practice and,\ntherefore, takes the form of recommendation.",
          "bbox": [
            25.92,
            404.02,
            347.76,
            424.57
          ],
          "block_id": "b4_7",
          "font_size": 8.6,
          "is_bold": true,
          "is_heading": true
        },
        {
          "type": "text",
          "content": "0.4 For the purpose of deciding whether a particular\nrequirement of this\nstandard is complied with, the final value, observed or calculated, express-\ning the result of a test or analysis, shall be rounded off in accordance with\nIS  :  2-1960*.\nThe number of significant places retained in the rounded off\nvalue should be the same as that of the specified value in this standard.",
          "bbox": [
            25.92,
            433.06,
            350.88,
            483.37
          ],
          "block_id": "b4_8",
          "font_size": 8.6,
          "is_bold": true,
          "is_heading": false
        },
        {
          "type": "text",
          "content": "*Rules for rounding off numerical values  (w&d).",
          "bbox": [
            37.44,
            499.59,
            217.69,
            508.5
          ],
          "block_id": "b4_9",
          "font_size": 7.4,
          "is_bold": true,
          "is_heading": true
        },
        {
          "type": "text",
          "content": "3",
          "bbox": [
            184.32,
            521.14,
            190.8,
            531.61
          ],
          "block_id": "b4_10",
          "font_size": 8.6,
          "is_bold": true,
          "is_heading": true
        }
      ],
      "images": [],
      "dimensions": {
        "width": 425.447998046875,
        "height": 571.0159912109375
      },
      "image_id_map": {}
    },
    {
      "page_num": 5,
      "blocks": [
        {
          "type": "text",
          "content": "X8:1196-1978",
          "bbox": [
            52.08,
            38.01,
            126.96,
            50.0
          ],
          "block_id": "b5_0",
          "font_size": 9.6,
          "is_bold": false,
          "is_heading": false
        },
        {
          "type": "text",
          "content": "1. SCOPE\n*\n1.1  This standard lays down the procedure for laying \u2018bitumen mastic\nflooring and its maintenance.\n1.2 It does not include provisions of  acid  resistant bitumen mastic.",
          "bbox": [
            52.8,
            59.51,
            374.64,
            106.17
          ],
          "block_id": "b5_1",
          "font_size": 9.1,
          "is_bold": true,
          "is_heading": true
        },
        {
          "type": "text",
          "content": "I.3 Details of floor finishes, fixings and adhesives when bitumen mastic is\nused as a damp-proofing base are not included in this specification.",
          "bbox": [
            53.76,
            108.66,
            378.24,
            128.97
          ],
          "block_id": "b5_2",
          "font_size": 8.6,
          "is_bold": true,
          "is_heading": true
        },
        {
          "type": "text",
          "content": "2. TERMINOLOGY",
          "bbox": [
            53.52,
            132.42,
            137.76,
            142.89
          ],
          "block_id": "b5_3",
          "font_size": 8.6,
          "is_bold": true,
          "is_heading": true
        },
        {
          "type": "text",
          "content": "2.1 For the purpose of this standard, the definitions given in IS : 334-1965*\nshall apply.",
          "bbox": [
            53.28,
            145.38,
            371.27,
            166.17
          ],
          "block_id": "b5_4",
          "font_size": 8.6,
          "is_bold": true,
          "is_heading": true
        },
        {
          "type": "text",
          "content": "3. GENERAL",
          "bbox": [
            53.28,
            168.9,
            111.6,
            179.37
          ],
          "block_id": "b5_5",
          "font_size": 8.6,
          "is_bold": true,
          "is_heading": true
        },
        {
          "type": "text",
          "content": "3.1 Necessary\nInformation\n-\nFor efficient planning and execution of\nflooring work, detailed data and information as given below shall be\ntaken into account:\n4\nb)\n4",
          "bbox": [
            53.76,
            184.26,
            378.0,
            257.28
          ],
          "block_id": "b5_6",
          "font_size": 11.5,
          "is_bold": true,
          "is_heading": true
        },
        {
          "type": "text",
          "content": "The function which the bitumen mastic flooring has to fulfil;",
          "bbox": [
            92.88,
            217.14,
            358.56,
            227.61
          ],
          "block_id": "b5_10",
          "font_size": 8.6,
          "is_bold": true,
          "is_heading": true
        },
        {
          "type": "text",
          "content": "Type of traffic -\nlight, medium or heavy;\nWheeled conveyors, loads and rates of travel, types and widths\nof wheel or tyre;\nWeight of standing loads, nature of load and bearing area;\nMaximum\nand,, minimum temperatures\nto which the bitumen\nmastic is to be subjected;\nType of surface finish;",
          "bbox": [
            92.16,
            230.1,
            376.56,
            311.61
          ],
          "block_id": "b5_11",
          "font_size": 8.6,
          "is_bold": true,
          "is_heading": false
        },
        {
          "type": "text",
          "content": "4\n4",
          "bbox": [
            78.72,
            264.26,
            89.12,
            293.04
          ],
          "block_id": "b5_7",
          "font_size": 11.5,
          "is_bold": false,
          "is_heading": false
        },
        {
          "type": "text",
          "content": "f)\ng)",
          "bbox": [
            78.48,
            299.78,
            92.48,
            329.04
          ],
          "block_id": "b5_8",
          "font_size": 11.5,
          "is_bold": false,
          "is_heading": false
        },
        {
          "type": "text",
          "content": "Age, nature and present condition of the base over which the\nbitumen mastic is to be laid;\nType and thickness of concrete screed to be laid on the base;\nj) Type of underlay, or separating layer, if any;\nk) Space available\nfor plant and means of storing and hoisting\nmaterials; and\nm) Any other special requirements.",
          "bbox": [
            74.88,
            314.34,
            377.52,
            396.09
          ],
          "block_id": "b5_12",
          "font_size": 8.6,
          "is_bold": true,
          "is_heading": false
        },
        {
          "type": "text",
          "content": "h)",
          "bbox": [
            78.96,
            335.78,
            92.48,
            351.6
          ],
          "block_id": "b5_9",
          "font_size": 11.5,
          "is_bold": false,
          "is_heading": false
        },
        {
          "type": "text",
          "content": "4. DESIGN CONSIDERATIONS\n4.1 Bitumen mastic is dustless, odourless, jointless and impervious to the\ntransmission of moisture, either in liquid or vapour form.\nThe surface is\neasily cleaned, noiseless under traffic and resilient. Bitumen mastic is also\ndurable.\nWhile it may carry heavy loads, application\nof concentrated\npoint load may cause indentation.\nIn designing the bitumen mastic floor-\ning consideration shall be given to the anticipated\nservice conditions.\nBitumen mastic is, therefore, suitable for a variety of uses under a wide\nrange of climatic and service conditions.",
          "bbox": [
            54.0,
            400.98,
            379.2,
            493.29
          ],
          "block_id": "b5_13",
          "font_size": 8.6,
          "is_bold": true,
          "is_heading": false
        },
        {
          "type": "text",
          "content": "*Glossary  of terms  relating  to bitumen\nand tar (first revision ).",
          "bbox": [
            66.24,
            501.06,
            291.18,
            511.53
          ],
          "block_id": "b5_14",
          "font_size": 7.8,
          "is_bold": true,
          "is_heading": true
        },
        {
          "type": "text",
          "content": "4",
          "bbox": [
            215.52,
            522.95,
            222.72,
            534.82
          ],
          "block_id": "b5_15",
          "font_size": 8.6,
          "is_bold": false,
          "is_heading": false
        }
      ],
      "images": [],
      "dimensions": {
        "width": 425.2079772949219,
        "height": 572.0559692382812
      },
      "image_id_map": {}
    },
    {
      "page_num": 6,
      "blocks": [
        {
          "type": "text",
          "content": "4.1.1 Limihhbu of Use -The\nsurface\nof bitumen\nmastic is liable to\nbecome gradually\nsoftended\nby prolonged\ncontact with greases, fats and\noils.\nContamination\nwith such materials shall be avoided.",
          "bbox": [
            31.68,
            65.06,
            359.65,
            96.12
          ],
          "block_id": "b6_0",
          "font_size": 9.6,
          "is_bold": true,
          "is_heading": true
        },
        {
          "type": "text",
          "content": "4.1.2 Susceptibility of bitumen mastic floor finishes to chemical\nattack\nisgiveninTable\n1.",
          "bbox": [
            31.2,
            102.32,
            357.73,
            122.04
          ],
          "block_id": "b6_1",
          "font_size": 8.6,
          "is_bold": true,
          "is_heading": true
        },
        {
          "type": "text",
          "content": "4.2 TLIckrau\n-\nThe total thickness to which bitumen mastic should be\nlaid depends\nupon\nthe  traffic  conditions\nto which\nthe flooring will be\nsubjected.\nUsually\nthe bitumen\nmastic should be laid in one coat, but\ntwo-coat\nwork may be used, depending\non the thickness of floor finish.\nAs a general guide the thicknesses as given in Table 2 are recommended.",
          "bbox": [
            31.44,
            128.48,
            359.41,
            178.44
          ],
          "block_id": "b6_2",
          "font_size": 8.6,
          "is_bold": true,
          "is_heading": false
        },
        {
          "type": "text",
          "content": "5.1 Bitumen\nmastic\nshall\nconform\nto\nthe\nrequirements\ngiven\nin\nIS  :  1195-1988*.",
          "bbox": [
            32.4,
            202.4,
            359.17,
            223.1
          ],
          "block_id": "b6_3",
          "font_size": 8.6,
          "is_bold": true,
          "is_heading": true
        },
        {
          "type": "text",
          "content": "5.2 The bitumen mastic may be delivered to the site either in the form of\nblocks weighing about 25 kg or in molten condition\nin a mobile mixer or\nprepared at the site.",
          "bbox": [
            32.64,
            228.56,
            359.17,
            258.6
          ],
          "block_id": "b6_4",
          "font_size": 8.6,
          "is_bold": true,
          "is_heading": true
        },
        {
          "type": "text",
          "content": "5.3 sarfaee\nArmouring\n-Special\ntypes of metal armouring\nmay\nbe\nincorporated\nin bitumen mastic flooring for industrial purposes to increase\nresistance of abrasion.",
          "bbox": [
            32.64,
            264.56,
            359.17,
            294.84
          ],
          "block_id": "b6_5",
          "font_size": 8.6,
          "is_bold": true,
          "is_heading": true
        },
        {
          "type": "text",
          "content": "6.  EQUIPMENT",
          "bbox": [
            32.64,
            300.14,
            110.3,
            311.39
          ],
          "block_id": "b6_6",
          "font_size": 9.1,
          "is_bold": true,
          "is_heading": true
        },
        {
          "type": "text",
          "content": "6.1 The\nequipment\nshall\nconsist\nof a bitumen\nboiler, a mechanically\nagitated mixer called mastic cooker and other accessories. The equipment\nshall be set up as near the site of work as possible so as to avoid cooling of\nthe molten material.",
          "bbox": [
            32.88,
            316.88,
            360.37,
            357.24
          ],
          "block_id": "b6_7",
          "font_size": 8.6,
          "is_bold": true,
          "is_heading": false
        },
        {
          "type": "text",
          "content": "7.  CONSTRUCTION",
          "bbox": [
            33.6,
            364.46,
            130.46,
            375.71
          ],
          "block_id": "b6_8",
          "font_size": 9.1,
          "is_bold": true,
          "is_heading": true
        },
        {
          "type": "text",
          "content": "7.1  The base on which the bitumen\nmastic flooring is to be laid shall be\nadequately\nstrong\nto receive\nthe mastic and to carry the anticipated\ntraffic over it.",
          "bbox": [
            33.6,
            380.3,
            359.89,
            411.96
          ],
          "block_id": "b6_9",
          "font_size": 9.1,
          "is_bold": true,
          "is_heading": true
        },
        {
          "type": "text",
          "content": "7.2  Preparation\nof the Base - The base shall have a true, even and\ndry surface which has been slightly coarsened by means 0f.a\u2019 stiff broom\nor wire brush\nand should\nbe free from ridges and hollows.\nA steel\ntrowelled\nfinish is not desirable.\nThe levels of the base should be such\nthat the specified thickness of bitumen mastic may be applied uniformly.\nIf the finished tloor is likely to have water or industrial liquors upon it, a\nstraight fall of not less than 1 in 75 should be provided.\nChannels should\nbe provided as necessary to ensure adequate drainage.",
          "bbox": [
            34.08,
            417.02,
            360.37,
            498.6
          ],
          "block_id": "b6_10",
          "font_size": 9.1,
          "is_bold": true,
          "is_heading": false
        },
        {
          "type": "text",
          "content": "*Specification for bitumen mastic for flooring (fist rmision ).",
          "bbox": [
            45.6,
            506.48,
            269.65,
            516.6
          ],
          "block_id": "b6_11",
          "font_size": 8.6,
          "is_bold": true,
          "is_heading": true
        },
        {
          "type": "text",
          "content": "5",
          "bbox": [
            195.84,
            526.83,
            203.04,
            538.7
          ],
          "block_id": "b6_12",
          "font_size": 8.6,
          "is_bold": false,
          "is_heading": false
        }
      ],
      "images": [],
      "dimensions": {
        "width": 426.2079772949219,
        "height": 573.0559692382812
      },
      "image_id_map": {}
    },
    {
      "page_num": 7,
      "blocks": [
        {
          "type": "text",
          "content": "IS : 1199 - 1979",
          "bbox": [
            39.36,
            29.97,
            114.38,
            41.55
          ],
          "block_id": "b7_0",
          "font_size": 9.6,
          "is_bold": true,
          "is_heading": true
        },
        {
          "type": "text",
          "content": "TABLE I S-OF\nBITUMEN MASTIC FLOOR FINISHES  TO\nOHEMIOAL\nAND TEMPERATURE\nATTACK",
          "bbox": [
            49.44,
            57.07,
            353.44,
            74.75
          ],
          "block_id": "b7_1",
          "font_size": 7.9,
          "is_bold": true,
          "is_heading": true
        },
        {
          "type": "text",
          "content": "( Claurr 4.1.2 )",
          "bbox": [
            174.72,
            78.84,
            227.68,
            87.0
          ],
          "block_id": "b7_24",
          "font_size": 7.0,
          "is_bold": true,
          "is_heading": true
        },
        {
          "type": "text",
          "content": "I%.",
          "bbox": [
            38.88,
            88.84,
            68.34,
            112.25
          ],
          "block_id": "b7_2",
          "font_size": 17.0,
          "is_bold": false,
          "is_heading": true
        },
        {
          "type": "text",
          "content": "SV~CEPTI~ILITY TO ATTACIL",
          "bbox": [
            219.36,
            92.52,
            325.12,
            100.68
          ],
          "block_id": "b7_25",
          "font_size": 7.0,
          "is_bold": true,
          "is_heading": true
        },
        {
          "type": "text",
          "content": "AQxm7Y",
          "bbox": [
            96.96,
            92.76,
            127.36,
            100.92
          ],
          "block_id": "b7_12",
          "font_size": 7.0,
          "is_bold": true,
          "is_heading": true
        },
        {
          "type": "text",
          "content": "(1)\n3",
          "bbox": [
            41.76,
            112.44,
            56.19,
            139.55
          ],
          "block_id": "b7_3",
          "font_size": 9.6,
          "is_bold": false,
          "is_heading": false
        },
        {
          "type": "text",
          "content": "(3)",
          "bbox": [
            266.4,
            116.28,
            277.12,
            124.44
          ],
          "block_id": "b7_26",
          "font_size": 7.0,
          "is_bold": true,
          "is_heading": true
        },
        {
          "type": "text",
          "content": "(2)",
          "bbox": [
            108.0,
            116.52,
            118.72,
            124.68
          ],
          "block_id": "b7_13",
          "font_size": 7.0,
          "is_bold": true,
          "is_heading": true
        },
        {
          "type": "text",
          "content": "Acids and vegetable\nextracts\nother than oils",
          "bbox": [
            61.92,
            128.52,
            162.4,
            144.6
          ],
          "block_id": "b7_14",
          "font_size": 7.0,
          "is_bold": true,
          "is_heading": true
        },
        {
          "type": "text",
          "content": "Normal\ngrades\nof bitumen\nmastic\nare subject\nto attack\nby\nacids,\nbut\nspecial\ngrades\nare\navailable\nto withstand\nattack\nby dilute\nsolu-\ntions",
          "bbox": [
            181.68,
            128.52,
            362.56,
            160.44
          ],
          "block_id": "b7_27",
          "font_size": 7.0,
          "is_bold": true,
          "is_heading": true
        },
        {
          "type": "text",
          "content": "ii)",
          "bbox": [
            45.36,
            165.24,
            53.68,
            173.4
          ],
          "block_id": "b7_4",
          "font_size": 7.0,
          "is_bold": true,
          "is_heading": true
        },
        {
          "type": "text",
          "content": "Alcoholic\nliquors",
          "bbox": [
            62.4,
            165.24,
            122.08,
            173.4
          ],
          "block_id": "b7_15",
          "font_size": 7.0,
          "is_bold": true,
          "is_heading": true
        },
        {
          "type": "text",
          "content": "Normal\ngrades\nof bitumen\nmastic are\nsubject\nto attack\nby\ncertain\nalcoholic\nliquors\nand\nthe use of special\ngrades\nmay be necessary\nin\nsome situations,\nfor example,\nbreweries\nand\ndistilleries",
          "bbox": [
            180.24,
            165.24,
            362.8,
            205.08
          ],
          "block_id": "b7_28",
          "font_size": 7.0,
          "is_bold": true,
          "is_heading": true
        },
        {
          "type": "text",
          "content": "iii)",
          "bbox": [
            43.44,
            210.84,
            53.68,
            219.0
          ],
          "block_id": "b7_5",
          "font_size": 7.0,
          "is_bold": true,
          "is_heading": true
        },
        {
          "type": "text",
          "content": "Alkalis",
          "bbox": [
            61.92,
            210.84,
            84.88,
            219.0
          ],
          "block_id": "b7_16",
          "font_size": 7.0,
          "is_bold": true,
          "is_heading": true
        },
        {
          "type": "text",
          "content": "Alkali solutions\nof low concentration,\nat normal\ntemperatures,\nhave\nlittle\nor\nno\neffect\non\nbitumen\nmastic.\nAlkali\nsolutions\nabove 38\u2019C,\nparticularly\nof high concentration,\nwill\naffect\nbitumen\nmastic",
          "bbox": [
            181.44,
            210.84,
            363.04,
            250.68
          ],
          "block_id": "b7_29",
          "font_size": 7.0,
          "is_bold": true,
          "is_heading": true
        },
        {
          "type": "text",
          "content": "iv)",
          "bbox": [
            45.36,
            256.44,
            54.88,
            264.6
          ],
          "block_id": "b7_6",
          "font_size": 7.0,
          "is_bold": true,
          "is_heading": true
        },
        {
          "type": "text",
          "content": "Under\nnormal\nconditions,\nbitumen\nmastic\nis\nunaffected\nby these agencies",
          "bbox": [
            182.64,
            256.44,
            363.52,
            272.76
          ],
          "block_id": "b7_30",
          "font_size": 7.0,
          "is_bold": true,
          "is_heading": true
        },
        {
          "type": "text",
          "content": "Brine (sodium\nand calcium\nchforide )\nand\nsulphate\nsalts",
          "bbox": [
            63.84,
            256.68,
            161.92,
            280.44
          ],
          "block_id": "b7_17",
          "font_size": 7.0,
          "is_bold": true,
          "is_heading": true
        },
        {
          "type": "text",
          "content": "Complex\nindustrial\nliquors\nand radio-active\nmaterials",
          "bbox": [
            64.08,
            286.44,
            165.04,
            302.52
          ],
          "block_id": "b7_18",
          "font_size": 7.0,
          "is_bold": true,
          "is_heading": true
        },
        {
          "type": "text",
          "content": "Laboratory\ntests are essential\nto ensure\nthat a\nsuitable\ngrade of bitumen\nmastic is used",
          "bbox": [
            184.32,
            286.44,
            363.28,
            302.52
          ],
          "block_id": "b7_31",
          "font_size": 7.0,
          "is_bold": true,
          "is_heading": true
        },
        {
          "type": "text",
          "content": "v)",
          "bbox": [
            48.48,
            288.36,
            56.08,
            296.52
          ],
          "block_id": "b7_7",
          "font_size": 7.0,
          "is_bold": true,
          "is_heading": true
        },
        {
          "type": "text",
          "content": "Vi)",
          "bbox": [
            45.12,
            308.28,
            56.56,
            316.44
          ],
          "block_id": "b7_8",
          "font_size": 7.0,
          "is_bold": true,
          "is_heading": true
        },
        {
          "type": "text",
          "content": "Radio-active\nmaterials",
          "bbox": [
            64.08,
            308.28,
            142.96,
            316.44
          ],
          "block_id": "b7_19",
          "font_size": 7.0,
          "is_bold": true,
          "is_heading": true
        },
        {
          "type": "text",
          "content": "Special grades of bitumen\nmastic are required",
          "bbox": [
            182.16,
            308.28,
            349.84,
            316.44
          ],
          "block_id": "b7_32",
          "font_size": 7.0,
          "is_bold": true,
          "is_heading": true
        },
        {
          "type": "text",
          "content": "Dairy p\u2019roducts and milk",
          "bbox": [
            62.88,
            321.96,
            153.76,
            330.12
          ],
          "block_id": "b7_20",
          "font_size": 7.0,
          "is_bold": true,
          "is_heading": true
        },
        {
          "type": "text",
          "content": "Where hygienic\nconditions\nare\nmaintained\nby\nadequate\ncleansing,.\na\nnormal\ngrade\nis\nsuitable.\nWhere\nchurns\nor\nmilk\ncans\nare\nhandled,\nit is advisable\nto incorporate\nmetal\narmourmg\nin the floor surface,\notherwise\nthe\nfloor will become\nindented\nand in these areas\nfats may accumulate\nand attack the mastic",
          "bbox": [
            181.92,
            321.96,
            364.0,
            377.88
          ],
          "block_id": "b7_33",
          "font_size": 7.0,
          "is_bold": true,
          "is_heading": false
        },
        {
          "type": "text",
          "content": "xii)",
          "bbox": [
            42.0,
            322.2,
            54.16,
            330.36
          ],
          "block_id": "b7_9",
          "font_size": 7.0,
          "is_bold": true,
          "is_heading": true
        },
        {
          "type": "text",
          "content": "viii)",
          "bbox": [
            41.76,
            383.4,
            55.12,
            391.56
          ],
          "block_id": "b7_10",
          "font_size": 7.0,
          "is_bold": true,
          "is_heading": true
        },
        {
          "type": "text",
          "content": "Mineral,\nanimal\nand vege-\ntable oils, fats and greases",
          "bbox": [
            65.52,
            383.64,
            166.72,
            399.72
          ],
          "block_id": "b7_21",
          "font_size": 7.0,
          "is_bold": true,
          "is_heading": true
        },
        {
          "type": "text",
          "content": "Bitumen\nmastic floor finish is subject to attack by\nthese oils, fats and greases",
          "bbox": [
            183.12,
            383.88,
            363.28,
            399.96
          ],
          "block_id": "b7_34",
          "font_size": 7.0,
          "is_bold": true,
          "is_heading": true
        },
        {
          "type": "text",
          "content": "Sugar,\nsyrup,\nsugar\nsolu-\ntions, etc",
          "bbox": [
            61.68,
            405.72,
            166.72,
            421.32
          ],
          "block_id": "b7_22",
          "font_size": 7.0,
          "is_bold": true,
          "is_heading": true
        },
        {
          "type": "text",
          "content": "Bitumen\nmastic\nis unaffected\nby dry sugar\nor\nsolutions\nof\nlow\nconcentration\nat\nnormal\ntemperatures.\nSyrups,\nmolasses\nand\nother\nconcentrated\nsolutions\nwill\naffect\nbitumen\nmastic at all temperatures",
          "bbox": [
            184.08,
            405.72,
            364.0,
            445.56
          ],
          "block_id": "b7_35",
          "font_size": 7.0,
          "is_bold": true,
          "is_heading": true
        },
        {
          "type": "text",
          "content": "IX):",
          "bbox": [
            43.92,
            407.09,
            54.75,
            413.17
          ],
          "block_id": "b7_11",
          "font_size": 5.0,
          "is_bold": true,
          "is_heading": true
        },
        {
          "type": "text",
          "content": "Water",
          "bbox": [
            64.32,
            451.32,
            85.6,
            459.48
          ],
          "block_id": "b7_23",
          "font_size": 7.0,
          "is_bold": true,
          "is_heading": true
        },
        {
          "type": "text",
          "content": "Bitumen\nmastic\nis unaffected\nunless\nfrequently\nin contact with hot water; under such circums-\ntances, a high-temperature\ngrade mastic should\nbe\nused.\nHot\nand\ncold\nwater\nfrequently\ndischarged\non to the floor may cause cracking",
          "bbox": [
            182.88,
            451.56,
            360.88,
            491.64
          ],
          "block_id": "b7_36",
          "font_size": 7.0,
          "is_bold": true,
          "is_heading": false
        },
        {
          "type": "text",
          "content": "6",
          "bbox": [
            199.92,
            509.97,
            209.42,
            521.55
          ],
          "block_id": "b7_37",
          "font_size": 9.6,
          "is_bold": true,
          "is_heading": true
        }
      ],
      "images": [],
      "dimensions": {
        "width": 414.2079772949219,
        "height": 565.0559692382812
      },
      "image_id_map": {}
    },
    {
      "page_num": 8,
      "blocks": [
        {
          "type": "text",
          "content": "IS:  1198 -  1978",
          "bbox": [
            302.4,
            42.55,
            368.4,
            54.42
          ],
          "block_id": "b8_0",
          "font_size": 8.6,
          "is_bold": true,
          "is_heading": true
        },
        {
          "type": "text",
          "content": "TABLE\n2\nTHICKNESS\nOF BITUMBN\nMASTIC\nFOR DIFFERENT\nSERVICE\nCONDITIONS",
          "bbox": [
            72.96,
            73.2,
            330.16,
            89.28
          ],
          "block_id": "b8_1",
          "font_size": 7.0,
          "is_bold": true,
          "is_heading": true
        },
        {
          "type": "text",
          "content": "( ClauW 4.2 )",
          "bbox": [
            182.64,
            94.8,
            228.4,
            102.96
          ],
          "block_id": "b8_2",
          "font_size": 7.0,
          "is_bold": true,
          "is_heading": true
        },
        {
          "type": "text",
          "content": "RECOMMENDED\nTHICKNESS\nmm",
          "bbox": [
            311.28,
            109.2,
            372.4,
            133.44
          ],
          "block_id": "b8_11",
          "font_size": 7.0,
          "is_bold": true,
          "is_heading": true
        },
        {
          "type": "text",
          "content": "SL\nEXAMPLES\nOF  SERVICE\nNo.\nCONDITIONS\nTYPE OF\nFLOORING",
          "bbox": [
            43.44,
            109.44,
            271.36,
            126.0
          ],
          "block_id": "b8_3",
          "font_size": 7.0,
          "is_bold": true,
          "is_heading": true
        },
        {
          "type": "text",
          "content": "(3)",
          "bbox": [
            243.36,
            138.48,
            254.08,
            146.64
          ],
          "block_id": "b8_7",
          "font_size": 7.0,
          "is_bold": true,
          "is_heading": true
        },
        {
          "type": "text",
          "content": "(4)\n15 to 20",
          "bbox": [
            325.68,
            138.48,
            354.16,
            156.96
          ],
          "block_id": "b8_12",
          "font_size": 7.0,
          "is_bold": true,
          "is_heading": true
        },
        {
          "type": "text",
          "content": "(1)\n(2)\ni)\nMedium\nwear due to foot traffic\nExam@\nSmall scale industries,\nsuch\nas those manufacturing\nelectronic\nand\nelectrical\nequipment",
          "bbox": [
            45.12,
            138.96,
            185.68,
            188.88
          ],
          "block_id": "b8_4",
          "font_size": 7.0,
          "is_bold": true,
          "is_heading": true
        },
        {
          "type": "text",
          "content": "Light duty",
          "bbox": [
            227.76,
            149.04,
            265.6,
            157.2
          ],
          "block_id": "b8_8",
          "font_size": 7.0,
          "is_bold": true,
          "is_heading": true
        },
        {
          "type": "text",
          "content": "20  to  25",
          "bbox": [
            324.72,
            192.02,
            354.16,
            203.55
          ],
          "block_id": "b8_13",
          "font_size": 7.5,
          "is_bold": true,
          "is_heading": true
        },
        {
          "type": "text",
          "content": "ii)\nSevere\nabrasion\ndue\nto\ncontinuous\nroot\ntraffic\nExam#la: Passenger\nplatforms,\nfootpaths,\nworkshops,\netc",
          "bbox": [
            48.96,
            194.4,
            185.33,
            226.8
          ],
          "block_id": "b8_5",
          "font_size": 7.0,
          "is_bold": true,
          "is_heading": true
        },
        {
          "type": "text",
          "content": "Medium\nduty",
          "bbox": [
            222.24,
            194.64,
            271.36,
            202.8
          ],
          "block_id": "b8_9",
          "font_size": 7.0,
          "is_bold": true,
          "is_heading": true
        },
        {
          "type": "text",
          "content": "25 to 30\nand more",
          "bbox": [
            322.56,
            231.84,
            356.56,
            248.16
          ],
          "block_id": "b8_14",
          "font_size": 7.0,
          "is_bold": true,
          "is_heading": true
        },
        {
          "type": "text",
          "content": "iii)\nSevere abrasion\ncombined\nwith\nimpact\nExampls:\nHeavy\nengineering\nworkshops,\ndespatch\nyards,\nloading\ndocks,\ngoods\nplat-\nforms,\nloading\nplatfcrms\nfor\ntrucks\ncarrying\nmilk\nbottles\nin dairy,\netc",
          "bbox": [
            47.28,
            232.08,
            184.48,
            295.44
          ],
          "block_id": "b8_6",
          "font_size": 7.0,
          "is_bold": true,
          "is_heading": true
        },
        {
          "type": "text",
          "content": "Heavy\nduty",
          "bbox": [
            225.6,
            232.08,
            268.0,
            240.24
          ],
          "block_id": "b8_10",
          "font_size": 7.0,
          "is_bold": true,
          "is_heading": true
        },
        {
          "type": "text",
          "content": "7.3 Treatment\nof the Base -The\ntreatment\nof the base shall be decided\nby the \u2018designer\nin consultation\nwith those responsible\nfor the\nflooring.\nOne of the following\nmay be used:\na>",
          "bbox": [
            42.0,
            310.1,
            360.0,
            362.34
          ],
          "block_id": "b8_15",
          "font_size": 15.8,
          "is_bold": true,
          "is_heading": true
        },
        {
          "type": "text",
          "content": "A screeded\nbed of cement\nconcrete\nor lime concrete\nnot less than\n25 mm thick; or",
          "bbox": [
            80.16,
            346.34,
            361.44,
            367.47
          ],
          "block_id": "b8_17",
          "font_size": 8.6,
          "is_bold": false,
          "is_heading": false
        },
        {
          "type": "text",
          "content": "b)\n4",
          "bbox": [
            66.48,
            370.9,
            80.0,
            402.56
          ],
          "block_id": "b8_16",
          "font_size": 11.5,
          "is_bold": false,
          "is_heading": false
        },
        {
          "type": "text",
          "content": "An isolating\nmembrane\nor underlay\n(see 7.4 ); or",
          "bbox": [
            80.4,
            372.02,
            293.52,
            383.55
          ],
          "block_id": "b8_18",
          "font_size": 8.6,
          "is_bold": false,
          "is_heading": false
        },
        {
          "type": "text",
          "content": "On metal\nfloors, a thin\npriming\ncoat of bitumen\npaint\napplied\nover a clean and dry surface.\nThe paint should\nbe dry before\nthe\nmastic\nis laid.",
          "bbox": [
            80.4,
            387.62,
            363.36,
            419.31
          ],
          "block_id": "b8_19",
          "font_size": 8.6,
          "is_bold": true,
          "is_heading": true
        },
        {
          "type": "text",
          "content": "7.4 Isolating\nMembrane\n-An\nisolating\nmembrane\nconforming\nto Type 1\nof IS: 1322-1970* is normally\nused where bitumen\nmastic\nup to 20 mm in\nthickness\nis laid.\nWhere\nthe base  is in direct\ncontact\nwith the ground,\nglass\nfibre\nfelt\n(see IS : 7193-1974t\n) may\nbe\nused\nas an alternative.",
          "bbox": [
            42.0,
            428.9,
            366.48,
            470.19
          ],
          "block_id": "b8_20",
          "font_size": 8.6,
          "is_bold": true,
          "is_heading": false
        },
        {
          "type": "text",
          "content": "*Specification for bitumen felts for waterproofing and damp-proofing (.~onrl\nrevision  ) .\n~SpcvScation for glass fibre  base coal tar pitch and bitumen\nfelts.",
          "bbox": [
            41.28,
            482.4,
            366.78,
            507.6
          ],
          "block_id": "b8_21",
          "font_size": 7.9,
          "is_bold": true,
          "is_heading": true
        },
        {
          "type": "text",
          "content": "7",
          "bbox": [
            200.64,
            523.22,
            207.12,
            534.75
          ],
          "block_id": "b8_22",
          "font_size": 8.6,
          "is_bold": false,
          "is_heading": false
        }
      ],
      "images": [],
      "dimensions": {
        "width": 423.447998046875,
        "height": 569.0159912109375
      },
      "image_id_map": {}
    },
    {
      "page_num": 9,
      "blocks": [
        {
          "type": "text",
          "content": "IS t  1196  -  1978",
          "bbox": [
            35.28,
            39.72,
            107.1,
            52.91
          ],
          "block_id": "b9_0",
          "font_size": 9.1,
          "is_bold": true,
          "is_heading": true
        },
        {
          "type": "text",
          "content": "Thickness of bitumen mastic exceeding 20 mm on new concrete are usually\nlaid without an isolating membrane\nexcept in circumstances\ndescribed\nin\n( b ) below.\nIsolating membranes\nshould be laid loose.",
          "bbox": [
            35.76,
            64.08,
            358.93,
            93.88
          ],
          "block_id": "b9_1",
          "font_size": 8.6,
          "is_bold": true,
          "is_heading": true
        },
        {
          "type": "text",
          "content": "a) An isolating membrane\nis essential:",
          "bbox": [
            60.24,
            99.6,
            223.81,
            109.72
          ],
          "block_id": "b9_2",
          "font_size": 8.6,
          "is_bold": true,
          "is_heading": true
        },
        {
          "type": "text",
          "content": "1) on a timber base;",
          "bbox": [
            74.64,
            113.52,
            162.61,
            123.64
          ],
          "block_id": "b9_3",
          "font_size": 8.6,
          "is_bold": true,
          "is_heading": true
        },
        {
          "type": "text",
          "content": "2)  on a base of porous or open texture, such as no-fines or light-\nweight concrete;",
          "bbox": [
            73.68,
            126.14,
            358.8,
            146.21
          ],
          "block_id": "b9_4",
          "font_size": 8.6,
          "is_bold": true,
          "is_heading": true
        },
        {
          "type": "text",
          "content": "3) where the concrete surfaces contains line cracks;",
          "bbox": [
            74.16,
            148.7,
            296.64,
            159.17
          ],
          "block_id": "b9_5",
          "font_size": 8.6,
          "is_bold": true,
          "is_heading": true
        },
        {
          "type": "text",
          "content": "4) on a concrete\nbase which has received a surface treatment,\nsuch as sodium silicate solution;\n5) when concrete has been contaminated by foreign matter from\nindustrial processes, such as oils, greases, sugar solutions or\nchemicals; and\n6) when the mastic is to be laid over a thermal insulating\nmedium, for example, in cold stores.",
          "bbox": [
            73.68,
            161.66,
            360.0,
            237.17
          ],
          "block_id": "b9_6",
          "font_size": 8.6,
          "is_bold": true,
          "is_heading": false
        },
        {
          "type": "text",
          "content": "b) An isolating membrane may also be found necessary in circums-\ntances arising immediately before or at the time of laying, such\nas the following:",
          "bbox": [
            60.72,
            240.38,
            360.24,
            270.77
          ],
          "block_id": "b9_7",
          "font_size": 8.6,
          "is_bold": true,
          "is_heading": true
        },
        {
          "type": "text",
          "content": "1) When the bitumen mastic cools too rapidly to allow it to be\nmanipulated and properly finished.\nPremature cooling may\nbe caused by the dissipation of heat through the base or by\nweather conditions, or both.\nIt may also occur when it is\nnecessary to transport the material far from the cauldron  or\nmixer.\nUnder these conditions, an isolating membrane may\nact as a thermal insulating medium to assist the retention of\nheat for a longer time after laying.",
          "bbox": [
            76.8,
            273.98,
            361.44,
            353.57
          ],
          "block_id": "b9_8",
          "font_size": 8.6,
          "is_bold": true,
          "is_heading": false
        },
        {
          "type": "text",
          "content": "2) When  (blowing\n\u2019  of the mastic asphalt occurs and cannot be\navoided by dusting the base with a suitable powder.\nThe\nreasons for  c  blowing  \u2019  are obscure,\nbut it may be due to\nextreme dampness or dryness or by the nature of the surface\ntexture of the concrete.\nWhere it is known in advance that\nthese\nconditions may arise, those\nentrusted\nwith\nlaying\nbitumen mastic should be notified.",
          "bbox": [
            76.8,
            355.63,
            360.72,
            426.29
          ],
          "block_id": "b9_9",
          "font_size": 8.6,
          "is_bold": true,
          "is_heading": false
        },
        {
          "type": "text",
          "content": "7.5  Placing the Underlay -  The underlay, when required should be laid\nloose with lapped joints.",
          "bbox": [
            36.24,
            433.82,
            359.41,
            454.36
          ],
          "block_id": "b9_10",
          "font_size": 8.6,
          "is_bold": true,
          "is_heading": true
        },
        {
          "type": "text",
          "content": "7.6 Setting  Out -  The setting out of the floor area into bays is normally\ndecided according to workable requirements. The arrangement of the bays\ndepends upon the design of the floor and the number of spreaders engaged,\nso  that the laying and finishing processes may both be easily controlled by\nthe operatives.",
          "bbox": [
            36.48,
            459.26,
            360.72,
            509.8
          ],
          "block_id": "b9_11",
          "font_size": 8.6,
          "is_bold": true,
          "is_heading": false
        },
        {
          "type": "text",
          "content": "8",
          "bbox": [
            196.08,
            520.99,
            203.28,
            532.86
          ],
          "block_id": "b9_12",
          "font_size": 8.6,
          "is_bold": false,
          "is_heading": false
        }
      ],
      "images": [],
      "dimensions": {
        "width": 418.1679992675781,
        "height": 571.0559692382812
      },
      "image_id_map": {}
    },
    {
      "page_num": 10,
      "blocks": [
        {
          "type": "text",
          "content": "IS :  1196 - 1978",
          "bbox": [
            287.28,
            29.34,
            361.74,
            40.08
          ],
          "block_id": "b10_0",
          "font_size": 8.6,
          "is_bold": true,
          "is_heading": true
        },
        {
          "type": "text",
          "content": "7.7 Re-melting  at Site -\nRe-melting is the term applied to the melting\nat the site or in a mobile mixer of the pieces of broken bitumen mastic\nblocks.\nThe blocks shall be broken\nto convenient\nsize not exceeding\n60 mm cubes and loaded into the mechanically\nagitated mixer or mastic\ncooker at the site of work.\nThe material shall then be carefully remelted.\nAt this stage any coarse aggregate preferably\npreheated\nshall be fed\nin successive portions until the complete charge is thoroughly incorporated.\nAfter all the coarse aggregate\nhas been incorporated,\nthe material\nshall\nbe mixed continuously for a period of not less than one hour before laying\nis begun, and mixing shall be continued until laying operation\nis com-\npleted, so as to maintain the coarse aggregate\nin suspension.\nAt no stage\nduring the re-melting\nand mixing process, shall the temperature\nexceed\n205\u00b0C.",
          "bbox": [
            32.4,
            51.18,
            356.4,
            180.96
          ],
          "block_id": "b10_1",
          "font_size": 8.6,
          "is_bold": true,
          "is_heading": false
        },
        {
          "type": "text",
          "content": "7.8  Laying",
          "bbox": [
            32.88,
            191.82,
            82.86,
            202.56
          ],
          "block_id": "b10_2",
          "font_size": 8.6,
          "is_bold": true,
          "is_heading": true
        },
        {
          "type": "text",
          "content": "7.8.1  Transgort of Molten Material-When\nthe material\nis sufficiently\nmolten to be workable, it should be carried in flat mortar pans, to the\npoint of laying.\nTo prevent the molten material from sticking to the pans\nthey may be sprinkled inside with a minimum quantity of inorganic dust,\nsudh as limestone dust, cement, ash or oil shall not be used.",
          "bbox": [
            32.64,
            213.66,
            354.48,
            264.0
          ],
          "block_id": "b10_3",
          "font_size": 8.6,
          "is_bold": true,
          "is_heading": false
        },
        {
          "type": "text",
          "content": "7.8.2  @reading-Bitumen\nmastic should generally be laid in bays in\none coat.\nIt should be spread to the specified thickness by means of\nsuitable hand tools, gauges, straight edges and hand levels being used to\nensure accuracy.\nThe\nbitumen\nmastic\nshould then\nbe\nfloated\nto a\nuniformly level surface by a heavy wooden float and should be free from\nroughness and\u2019 imperfections.",
          "bbox": [
            32.16,
            270.78,
            355.44,
            331.2
          ],
          "block_id": "b10_4",
          "font_size": 8.6,
          "is_bold": true,
          "is_heading": false
        },
        {
          "type": "text",
          "content": "7.8.2.1\nIf  \u2018blowing\n\u2019  occurs, the bubbles should be punctured and\nthe area affected carefully made good while the mastic is still hot.",
          "bbox": [
            31.92,
            337.55,
            354.48,
            359.28
          ],
          "block_id": "b10_5",
          "font_size": 8.6,
          "is_bold": false,
          "is_heading": false
        },
        {
          "type": "text",
          "content": "7.8.2.2\nTwo-coat work should be treated in a manner similar to that\nfor single-coat\nwork, but care should be taken to arrange that the joints\nin successive layers are staggered.",
          "bbox": [
            31.92,
            366.3,
            354.24,
            396.72
          ],
          "block_id": "b10_6",
          "font_size": 8.6,
          "is_bold": false,
          "is_heading": false
        },
        {
          "type": "text",
          "content": "7.8.3  Surface Finish  -The\ntype of surface finish required\nshould be\nspecified by the designer.\nThe following.are\nthe two types:\na>",
          "bbox": [
            32.16,
            403.26,
            354.48,
            444.46
          ],
          "block_id": "b10_7",
          "font_size": 15.8,
          "is_bold": true,
          "is_heading": true
        },
        {
          "type": "text",
          "content": "Muttfinish -\nThe surface should be rubbed in with sand during\nthe final floating operation.\nThe sand should be clean and free\nfrom foreign matter. All surplus material should be removed after\nrubbing is completed, and\nPolishedjnish\n-\nThe surface should be finished with a float in a\nmanner similar to that used for a matt finish but without the use\nof an abrasive,",
          "bbox": [
            70.32,
            429.42,
            354.72,
            502.32
          ],
          "block_id": "b10_9",
          "font_size": 8.6,
          "is_bold": true,
          "is_heading": false
        },
        {
          "type": "text",
          "content": "b)",
          "bbox": [
            56.4,
            468.54,
            70.67,
            485.69
          ],
          "block_id": "b10_8",
          "font_size": 12.5,
          "is_bold": false,
          "is_heading": true
        },
        {
          "type": "text",
          "content": "9",
          "bbox": [
            189.84,
            515.82,
            196.32,
            526.56
          ],
          "block_id": "b10_10",
          "font_size": 8.6,
          "is_bold": false,
          "is_heading": false
        }
      ],
      "images": [],
      "dimensions": {
        "width": 421.2079772949219,
        "height": 569.0559692382812
      },
      "image_id_map": {}
    },
    {
      "page_num": 11,
      "blocks": [
        {
          "type": "text",
          "content": "IS I 1198 - 1978",
          "bbox": [
            36.0,
            28.03,
            104.03,
            37.32
          ],
          "block_id": "b11_0",
          "font_size": 7.9,
          "is_bold": true,
          "is_heading": true
        },
        {
          "type": "text",
          "content": "7.8.3.1\nImmediately\nafter completion of the laying, the bitumen\nmastic should be protected from damage till the material cools to the\nsurrounding temperature.",
          "bbox": [
            35.76,
            49.38,
            361.44,
            79.53
          ],
          "block_id": "b11_1",
          "font_size": 8.6,
          "is_bold": true,
          "is_heading": true
        },
        {
          "type": "text",
          "content": "7&A  Slijperiness -  Bitumen mastic has reasonable slip-resistance, but\nfrequent polishing tends to make it slippery.\nWhere mastic is used as\npaving\nto stairs a suitable-non-slip\nsafety nosing or\ninset should be\nincorporated in the tread.",
          "bbox": [
            36.0,
            84.9,
            362.64,
            125.37
          ],
          "block_id": "b11_2",
          "font_size": 8.6,
          "is_bold": true,
          "is_heading": false
        },
        {
          "type": "text",
          "content": "7.9  Juncdons\n-\nS  pecial care should be taken in effecting proper junctions\nbetween new and previously laid sections of work.\nThe contact edges of\nthe previously laid mastic should be cleaned and warmed by additional\napplications\nof hot mastic.\nThis procedure should also be adopted at\njunctions between the floor finish and skirtings, coves or fillets.",
          "bbox": [
            35.04,
            131.46,
            362.88,
            182.25
          ],
          "block_id": "b11_3",
          "font_size": 8.6,
          "is_bold": true,
          "is_heading": false
        },
        {
          "type": "text",
          "content": "7.10 skirtisgs\n-\nSkirtings should be executed in not less than two coats,\nparticular care being taken to ensure proper adhesion of the first coat to\nthe base.\nSpecial care should be taken at external angles to ensure the\nfull thickness of the material.",
          "bbox": [
            36.0,
            187.38,
            362.64,
            227.85
          ],
          "block_id": "b11_4",
          "font_size": 8.6,
          "is_bold": true,
          "is_heading": false
        },
        {
          "type": "text",
          "content": "7.11  Protection\nof the\nSurface -The\nnewly laid surface should be\nprotected from damage due to careless handling of construction\nequip-\nment, spillage of oils, paints, chemicals, plying of vehicles, etc.\nConcrete\nor mortar shall not be mixed directly on the bitumen mastic surface.",
          "bbox": [
            36.24,
            233.22,
            362.88,
            273.93
          ],
          "block_id": "b11_5",
          "font_size": 8.6,
          "is_bold": true,
          "is_heading": false
        },
        {
          "type": "text",
          "content": "7.12  Bringing\ninto Service -\nThe mastic flooring should not be subjected\nto traffic until the material has cooled throughout to the temperature of\nthe surrounding atmosphere.",
          "bbox": [
            36.0,
            279.3,
            364.08,
            309.93
          ],
          "block_id": "b11_6",
          "font_size": 8.6,
          "is_bold": true,
          "is_heading": true
        },
        {
          "type": "text",
          "content": "8.  INSPECTION",
          "bbox": [
            36.24,
            318.66,
            107.87,
            329.13
          ],
          "block_id": "b11_7",
          "font_size": 8.3,
          "is_bold": true,
          "is_heading": true
        },
        {
          "type": "text",
          "content": "8.1  The work shall be inspected while in progress and after completion,\nspecial attention shall be paid to the following points:\n-4\nb)",
          "bbox": [
            36.24,
            334.26,
            360.23,
            385.73
          ],
          "block_id": "b11_8",
          "font_size": 12.5,
          "is_bold": true,
          "is_heading": true
        },
        {
          "type": "text",
          "content": "General condition of the base;",
          "bbox": [
            75.84,
            358.02,
            208.32,
            368.49
          ],
          "block_id": "b11_9",
          "font_size": 8.6,
          "is_bold": true,
          "is_heading": true
        },
        {
          "type": "text",
          "content": "Irregular surface of the base, and correct laying of the underlay,\nwhen used;\n4\n4\ne)",
          "bbox": [
            61.44,
            371.22,
            360.24,
            434.88
          ],
          "block_id": "b11_10",
          "font_size": 12.5,
          "is_bold": true,
          "is_heading": true
        },
        {
          "type": "text",
          "content": "Cleanliness of plant for re-melting;",
          "bbox": [
            74.88,
            394.26,
            223.67,
            404.73
          ],
          "block_id": "b11_11",
          "font_size": 8.6,
          "is_bold": true,
          "is_heading": true
        },
        {
          "type": "text",
          "content": "Correct temperature of the mixture prior to laying;\nUse of the correct kind of dust to assist removal of mixture from\nthe buckets;\nf)  Making good all  (  blows \u2018;\ng)  Correct thickness throughout;\nh)  Removal of all asphalt tailings;\n3  Correctness of finished level and specified finish; and\nW  Correct pattern of decorative designs, if any.",
          "bbox": [
            61.44,
            407.46,
            362.88,
            509.28
          ],
          "block_id": "b11_12",
          "font_size": 10.6,
          "is_bold": true,
          "is_heading": false
        },
        {
          "type": "text",
          "content": "10",
          "bbox": [
            195.12,
            518.58,
            205.92,
            529.05
          ],
          "block_id": "b11_13",
          "font_size": 8.6,
          "is_bold": true,
          "is_heading": true
        }
      ],
      "images": [],
      "dimensions": {
        "width": 417.2079772949219,
        "height": 566.0559692382812
      },
      "image_id_map": {}
    },
    {
      "page_num": 12,
      "blocks": [
        {
          "type": "text",
          "content": "9. MAINTENANCE",
          "bbox": [
            31.68,
            44.66,
            123.02,
            55.91
          ],
          "block_id": "b12_0",
          "font_size": 9.6,
          "is_bold": true,
          "is_heading": true
        },
        {
          "type": "text",
          "content": "9.1 The bitumen mastic surface requires relatively\nlittle maintenance,\nthough attention is necessary to obtain maximum service,\nSuperficial dirt\nmay normally\nbe removed\nby washing with warm water and suitable\ndetergents.\nWhere there is much dirt on the floor, the additions\nof a\nsmall quantity of washing soda to the warm water may be desirable. After\nthe dirt has been removed the floor should be mopped with clean water.\nIt is essential that all oils, fats and greases spilled on the floor should be\nremoved immediately.",
          "bbox": [
            31.92,
            60.82,
            358.56,
            140.89
          ],
          "block_id": "b12_1",
          "font_size": 8.6,
          "is_bold": true,
          "is_heading": false
        },
        {
          "type": "text",
          "content": "9.2  Repairs",
          "bbox": [
            33.36,
            146.26,
            89.58,
            156.73
          ],
          "block_id": "b12_2",
          "font_size": 8.6,
          "is_bold": true,
          "is_heading": true
        },
        {
          "type": "text",
          "content": "9.2.1  When a damaged section has to be removed, it should be done\ncarefully.\nConsiderable damage may result from an attempt to cut away\nan affected area with the hammer and chisel or to soften it with a blow\nlamp.\nThe correct method is to place hot mastic around and over the\narea concerned, and after this has had a sufficient softening effect, the area\nshall be carefully cut away and made good, with fresh bitumen mastic.",
          "bbox": [
            33.12,
            161.86,
            359.04,
            222.01
          ],
          "block_id": "b12_3",
          "font_size": 8.6,
          "is_bold": true,
          "is_heading": false
        },
        {
          "type": "text",
          "content": "9.2.2\nWhen two-coat work is being restored or made good, the edge\nalong the perimeter of the area shall be cut back not less than 75 mm to\nhalf the total thickness of the mastic, to form a lapped joint.",
          "bbox": [
            35.04,
            227.14,
            360.24,
            257.29
          ],
          "block_id": "b12_4",
          "font_size": 8.6,
          "is_bold": true,
          "is_heading": false
        },
        {
          "type": "text",
          "content": "11",
          "bbox": [
            199.2,
            512.74,
            210.0,
            523.21
          ],
          "block_id": "b12_5",
          "font_size": 8.6,
          "is_bold": true,
          "is_heading": true
        }
      ],
      "images": [],
      "dimensions": {
        "width": 425.447998046875,
        "height": 576.0559692382812
      },
      "image_id_map": {}
    },
    {
      "page_num": 13,
      "blocks": [
        {
          "type": "text",
          "content": "BUREAU\nOF INDIAN STANDARDS\n.",
          "bbox": [
            39.12,
            22.49,
            223.72,
            35.95
          ],
          "block_id": "b13_0",
          "font_size": 7.9,
          "is_bold": true,
          "is_heading": true
        },
        {
          "type": "text",
          "content": "-:\nMmdt Sham,\u20189\nBahedr  Shah ZaMr Marg, NPW DELHI 110092\nTdrphorwib: 323 0131, 323 3375, 323 9492\nFax:91113234062,91113239399.91113239382\nTekgrcmS  : l4wdsmstha\n(Common to dl Ottices)",
          "bbox": [
            39.36,
            40.97,
            367.22,
            96.45
          ],
          "block_id": "b13_1",
          "font_size": 7.9,
          "is_bold": true,
          "is_heading": true
        },
        {
          "type": "text",
          "content": "curwL&om&ry:\nTW\nPlot No. 20/9, Site IV, Sahibabad Industrial Area, SAHIBABAD\n201010\n0-770032",
          "bbox": [
            39.36,
            101.86,
            359.29,
            120.69
          ],
          "block_id": "b13_2",
          "font_size": 7.0,
          "is_bold": true,
          "is_heading": true
        },
        {
          "type": "text",
          "content": "Reg&wwo#ces:",
          "bbox": [
            39.6,
            125.86,
            92.89,
            133.89
          ],
          "block_id": "b13_3",
          "font_size": 7.0,
          "is_bold": true,
          "is_heading": true
        },
        {
          "type": "text",
          "content": "Centrai : Manak Bhavw\n9 Bahadur Shah Zafar Marg, NEW DELHI 119092\n32376\n17",
          "bbox": [
            39.36,
            138.34,
            368.17,
            146.85
          ],
          "block_id": "b13_4",
          "font_size": 7.0,
          "is_bold": true,
          "is_heading": true
        },
        {
          "type": "text",
          "content": "\u2018Eastern  :  l/14 CIT Scheme VII M. V.I.P. Road, Maniktota, CALCUTTA799954\n337 86 62",
          "bbox": [
            39.12,
            146.75,
            367.21,
            158.62
          ],
          "block_id": "b13_5",
          "font_size": 7.5,
          "is_bold": true,
          "is_heading": true
        },
        {
          "type": "text",
          "content": "Northern : SC0 335336,\nSector 34-A, CHANDIGARH\n160022\n603843",
          "bbox": [
            39.36,
            160.18,
            359.53,
            168.69
          ],
          "block_id": "b13_6",
          "font_size": 7.0,
          "is_bold": true,
          "is_heading": true
        },
        {
          "type": "text",
          "content": "Southern  :  C.I.T. Campus, IV Cross Road, CHENNAI 690113\n23523\n15",
          "bbox": [
            39.12,
            168.59,
            368.17,
            180.46
          ],
          "block_id": "b13_7",
          "font_size": 7.5,
          "is_bold": true,
          "is_heading": true
        },
        {
          "type": "text",
          "content": "TWestern  :  Manakalaya, E9 Behind Marol Telephone Exchange, Andheri (East),\n632 92 95\nMUMBAI\n499093",
          "bbox": [
            39.36,
            179.63,
            367.45,
            200.13
          ],
          "block_id": "b13_8",
          "font_size": 7.5,
          "is_bold": true,
          "is_heading": true
        },
        {
          "type": "text",
          "content": "\u2018PushpaIr\u2019. Nurmchamed Shaikh Marg, Khanpur, AHMEDABAD\n369991\n5591340",
          "bbox": [
            39.36,
            221.14,
            359.77,
            229.65
          ],
          "block_id": "b13_9",
          "font_size": 7.0,
          "is_bold": true,
          "is_heading": true
        },
        {
          "type": "text",
          "content": "SPeenya lndustrii Area, 1st Stage, Bangatom-Tumkur Road,\n0394955\nBANGALORE\n569058",
          "bbox": [
            39.6,
            232.42,
            359.53,
            250.53
          ],
          "block_id": "b13_10",
          "font_size": 7.0,
          "is_bold": true,
          "is_heading": true
        },
        {
          "type": "text",
          "content": "Gangotri Compiex, 5th Floor, Bhadbhada Road, T. T. Nagar, BHOPAL 462993\n55 40 21",
          "bbox": [
            39.6,
            252.82,
            367.21,
            261.57
          ],
          "block_id": "b13_11",
          "font_size": 7.0,
          "is_bold": true,
          "is_heading": true
        },
        {
          "type": "text",
          "content": "Plot No. 62-63. Unit VI, Ganga Nagar, BHUBANESHWAR\n751901\n40 36 27",
          "bbox": [
            39.84,
            264.34,
            367.21,
            273.09
          ],
          "block_id": "b13_12",
          "font_size": 7.0,
          "is_bold": true,
          "is_heading": true
        },
        {
          "type": "text",
          "content": "Kalaikathir Buildings, 670 Avinashi Road, COIMBATORE 641037\n21 01 41",
          "bbox": [
            39.6,
            275.86,
            367.21,
            284.61
          ],
          "block_id": "b13_13",
          "font_size": 7.0,
          "is_bold": true,
          "is_heading": true
        },
        {
          "type": "text",
          "content": "Plot No. 43. Sector 16 A, Mathura Road, FARIDABAD\n121001\n8-28 88 01",
          "bbox": [
            39.6,
            287.62,
            367.45,
            296.37
          ],
          "block_id": "b13_14",
          "font_size": 7.0,
          "is_bold": true,
          "is_heading": true
        },
        {
          "type": "text",
          "content": "Savitri Complex, 116 G. T. Road, GHAZIABAD\n201001\na-71 19 96",
          "bbox": [
            39.6,
            299.14,
            367.45,
            307.89
          ],
          "block_id": "b13_15",
          "font_size": 7.0,
          "is_bold": true,
          "is_heading": true
        },
        {
          "type": "text",
          "content": "5315 Ward No. 29, R. 0. Barua Road, 5th By-lane, GUWAHATI 781003\n5411\n37",
          "bbox": [
            39.36,
            310.66,
            367.69,
            319.65
          ],
          "block_id": "b13_16",
          "font_size": 7.0,
          "is_bold": true,
          "is_heading": true
        },
        {
          "type": "text",
          "content": "C&58C,\nL. N. Gupta Marg. Nsmpally Statii\nRoad, HYDERABAD\n5oooOl\n20 10 83",
          "bbox": [
            39.6,
            322.18,
            367.45,
            331.17
          ],
          "block_id": "b13_17",
          "font_size": 7.0,
          "is_bold": true,
          "is_heading": true
        },
        {
          "type": "text",
          "content": "E-52, Chiianjan\nMarg, C-Scheme, JAIPUR 392091\n37 29 25",
          "bbox": [
            39.84,
            333.94,
            367.45,
            342.69
          ],
          "block_id": "b13_18",
          "font_size": 7.0,
          "is_bold": true,
          "is_heading": true
        },
        {
          "type": "text",
          "content": "1171418 0, Sarvodaya Nagar. KANPUR 298995\n21 68 76",
          "bbox": [
            40.32,
            345.7,
            367.69,
            354.45
          ],
          "block_id": "b13_19",
          "font_size": 7.0,
          "is_bold": true,
          "is_heading": true
        },
        {
          "type": "text",
          "content": "Seth Bhawan, 2nd Floor, Behind Leela Cii.\nNavai Kishore Road,\n23 89 23\nLUCKNOW\n226001",
          "bbox": [
            39.84,
            357.22,
            367.45,
            375.57
          ],
          "block_id": "b13_20",
          "font_size": 7.0,
          "is_bold": true,
          "is_heading": true
        },
        {
          "type": "text",
          "content": "252305",
          "bbox": [
            335.04,
            376.25,
            363.16,
            387.13
          ],
          "block_id": "b13_23",
          "font_size": 7.9,
          "is_bold": false,
          "is_heading": false
        },
        {
          "type": "text",
          "content": "Pattiputra Jndustrial Estate, PATNA 809913",
          "bbox": [
            40.32,
            379.06,
            192.01,
            387.09
          ],
          "block_id": "b13_21",
          "font_size": 7.0,
          "is_bold": true,
          "is_heading": true
        },
        {
          "type": "text",
          "content": "6 21 17\nTHIRUVANANTHAPURAM\n695034",
          "bbox": [
            52.8,
            389.86,
            368.65,
            408.21
          ],
          "block_id": "b13_24",
          "font_size": 7.0,
          "is_bold": true,
          "is_heading": true
        },
        {
          "type": "text",
          "content": "T. C. No. 14/1421. University P. 0. Palayam,",
          "bbox": [
            39.84,
            390.82,
            201.61,
            398.85
          ],
          "block_id": "b13_22",
          "font_size": 7.0,
          "is_bold": true,
          "is_heading": true
        },
        {
          "type": "text",
          "content": "52 51 71",
          "bbox": [
            335.28,
            411.46,
            367.93,
            419.49
          ],
          "block_id": "b13_27",
          "font_size": 7.0,
          "is_bold": true,
          "is_heading": true
        },
        {
          "type": "text",
          "content": "NIT Building, Second Floor, Gokulpat M&t.\nNAGPUR 440910",
          "bbox": [
            40.32,
            412.18,
            267.61,
            420.21
          ],
          "block_id": "b13_25",
          "font_size": 7.0,
          "is_bold": true,
          "is_heading": true
        },
        {
          "type": "text",
          "content": "lnstitutton of Engineers  (  India ) Building, 1332 Shivaji Nags, PUNE 411005",
          "bbox": [
            40.32,
            420.83,
            312.49,
            432.7
          ],
          "block_id": "b13_26",
          "font_size": 7.5,
          "is_bold": true,
          "is_heading": true
        },
        {
          "type": "text",
          "content": "323e35",
          "bbox": [
            335.04,
            422.98,
            360.01,
            431.01
          ],
          "block_id": "b13_28",
          "font_size": 7.0,
          "is_bold": true,
          "is_heading": true
        },
        {
          "type": "text",
          "content": "*Sales  Offlce is at 5 Chowrin$ws\nApproach, P 0. Prtncep Street,\nCALCUTTA\n790972\n27 10 85",
          "bbox": [
            40.32,
            446.27,
            367.69,
            465.09
          ],
          "block_id": "b13_29",
          "font_size": 7.4,
          "is_bold": true,
          "is_heading": true
        },
        {
          "type": "text",
          "content": "TSates Ottice is at Novelty Chambers, Grant Road, MUMBAI 409997\n399 65 23",
          "bbox": [
            40.56,
            467.86,
            368.17,
            476.37
          ],
          "block_id": "b13_30",
          "font_size": 7.0,
          "is_bold": true,
          "is_heading": true
        },
        {
          "type": "text",
          "content": "*Sates Otfice is at \u2018F\u2019 Block. Unity Building, Narashimwsja Square,\n222 39 71\nBANGALORE\n569902",
          "bbox": [
            40.8,
            479.38,
            368.17,
            497.49
          ],
          "block_id": "b13_31",
          "font_size": 7.0,
          "is_bold": true,
          "is_heading": true
        },
        {
          "type": "text",
          "content": "Prtntsd at New lndls Prhtln9 Press, Khurjs. trv9a",
          "bbox": [
            212.64,
            511.3,
            371.05,
            519.33
          ],
          "block_id": "b13_32",
          "font_size": 7.0,
          "is_bold": true,
          "is_heading": true
        }
      ],
      "images": [],
      "dimensions": {
        "width": 414.447998046875,
        "height": 569.0559692382812
      },
      "image_id_map": {}
    }
  ],
  "tables": [],
  "images": []
}