{
  "pages": [
    {
      "page_num": 1,
      "blocks": [
        {
          "type": "text",
          "content": "Is 15173:2002",
          "bbox": [
            400.8,
            27.84,
            470.93,
            42.37
          ],
          "block_id": "b1_0",
          "font_size": 10.6,
          "is_bold": true,
          "is_heading": true
        },
        {
          "type": "text",
          "content": "3?kfa@tizmT@wT",
          "bbox": [
            161.52,
            85.84,
            352.97,
            116.53
          ],
          "block_id": "b1_2",
          "font_size": 22.3,
          "is_bold": true,
          "is_heading": true
        },
        {
          "type": "text",
          "content": "rllf\nm",
          "bbox": [
            121.92,
            95.75,
            148.79,
            147.53
          ],
          "block_id": "b1_1",
          "font_size": 30.2,
          "is_bold": true,
          "is_heading": true
        },
        {
          "type": "text",
          "content": "ti-wm\nda@-mmw$\n%1-=mawmw-hw",
          "bbox": [
            153.36,
            114.64,
            380.43,
            173.12
          ],
          "block_id": "b1_3",
          "font_size": 22.3,
          "is_bold": true,
          "is_heading": true
        },
        {
          "type": "text",
          "content": "Indian Standard",
          "bbox": [
            204.48,
            194.22,
            314.17,
            213.56
          ],
          "block_id": "b1_4",
          "font_size": 15.8,
          "is_bold": false,
          "is_heading": true
        },
        {
          "type": "text",
          "content": "METHODS OF TEST FOR TARS AND BITUMINOUS\nMATERIALS \u2014DETERMINATION\nOF BREAKING\nPOINT FOR CATIONIC BITUMEN EMULSION",
          "bbox": [
            64.32,
            220.21,
            452.13,
            283.34
          ],
          "block_id": "b1_5",
          "font_size": 15.8,
          "is_bold": false,
          "is_heading": true
        },
        {
          "type": "text",
          "content": "Ics 75.140",
          "bbox": [
            240.48,
            331.18,
            284.63,
            343.98
          ],
          "block_id": "b1_6",
          "font_size": 9.6,
          "is_bold": false,
          "is_heading": false
        },
        {
          "type": "text",
          "content": "(3 BIS 2002",
          "bbox": [
            236.64,
            643.67,
            285.83,
            656.47
          ],
          "block_id": "b1_7",
          "font_size": 9.6,
          "is_bold": false,
          "is_heading": false
        },
        {
          "type": "text",
          "content": "BUREAU\nOF\nINDIAN\nSTANDARDS\nMANAK\nBHAVAN,\n9 BAHADUR\nSHAH\nZAFAR\nMARG\nNEW DELHI 110002\n.",
          "bbox": [
            116.4,
            660.99,
            403.14,
            708.3
          ],
          "block_id": "b1_8",
          "font_size": 10.6,
          "is_bold": true,
          "is_heading": true
        },
        {
          "type": "text",
          "content": "August 2002\nPrice Group\n3",
          "bbox": [
            39.6,
            722.41,
            483.12,
            736.62
          ],
          "block_id": "b1_9",
          "font_size": 9.6,
          "is_bold": true,
          "is_heading": true
        }
      ],
      "images": [],
      "dimensions": {
        "width": 509.511962890625,
        "height": 761.864013671875
      },
      "image_id_map": {}
    },
    {
      "page_num": 2,
      "blocks": [
        {
          "type": "text",
          "content": "Bitumen, Tar and Their Products Sectional Committee, PCD 6",
          "bbox": [
            37.99,
            16.28,
            294.56,
            29.08
          ],
          "block_id": "b2_0",
          "font_size": 9.6,
          "is_bold": false,
          "is_heading": false
        },
        {
          "type": "text",
          "content": "FOREWORD",
          "bbox": [
            38.47,
            102.44,
            92.44,
            115.24
          ],
          "block_id": "b2_1",
          "font_size": 9.6,
          "is_bold": false,
          "is_heading": false
        },
        {
          "type": "text",
          "content": "This Indian Standard was adopted by the Bureau of Indian Standards, after the drafi finalized by the Bitumen, Tar\nand Their Products Sectional Committee had been approved by the Petroleum, Coal and Related Products\nDivision Council.",
          "bbox": [
            38.47,
            120.44,
            487.08,
            157.0
          ],
          "block_id": "b2_2",
          "font_size": 9.6,
          "is_bold": false,
          "is_heading": false
        },
        {
          "type": "text",
          "content": "Bitumen emulsions are heterogeneous two-phase systems consisting of two immiscible liquids, that is, bitumen\nand water. The bitumen is dispersed throughout the continuous water phase in the form of discrete globu Ies\ntypically 0.1 \u2013 5.0 mm in diameter which again are held in suspension by electrostatic charges stabilized by an\nemulsifier.",
          "bbox": [
            38.95,
            161.96,
            488.93,
            210.52
          ],
          "block_id": "b2_3",
          "font_size": 9.6,
          "is_bold": false,
          "is_heading": false
        },
        {
          "type": "text",
          "content": "Neutralization\nof these electrostatic charg~s is known as breaking of the bitumen emulsion. The individual\nbitumen pa~icles coalesce and join together to form a deposition or coating once the charge is neutralized by\ncontact with the aggregates.",
          "bbox": [
            38.95,
            215.49,
            488.48,
            252.05
          ],
          "block_id": "b2_4",
          "font_size": 9.6,
          "is_bold": false,
          "is_heading": false
        },
        {
          "type": "text",
          "content": "In surface dressing construction, the spreading of stone aggregates is resorted to only when the emulsion fiIm\nturns from brown to black. At this point, it is assumed that the bitumen emulsion has broken. The breaking\npoint of bitumen emulsion can, however, be established more precisely by the addition of silica powder under\ncontrolled conditions. The amount of silica powder needed to induce the breaking of bitumen emulsion is then\ncorrelated with the breaking time.",
          "bbox": [
            39.43,
            257.01,
            489.49,
            317.33
          ],
          "block_id": "b2_5",
          "font_size": 9.6,
          "is_bold": false,
          "is_heading": false
        },
        {
          "type": "text",
          "content": "The breaking point not only helps in case of construction but also distinguishes the rate of breaking of different\ntypes of emulsion.",
          "bbox": [
            40.39,
            322.29,
            487.05,
            346.85
          ],
          "block_id": "b2_6",
          "font_size": 9.6,
          "is_bold": false,
          "is_heading": false
        },
        {
          "type": "text",
          "content": "The composition of the Committee responsible for the formulation of this standard is given in Annex A.",
          "bbox": [
            40.63,
            351.81,
            466.38,
            364.61
          ],
          "block_id": "b2_7",
          "font_size": 9.6,
          "is_bold": false,
          "is_heading": false
        },
        {
          "type": "text",
          "content": "In reporting the results of a test or analysis in accordance with this standard, if the final value, observed or\ncalculated, is to be rounded off, it shall be done in accordance with IS 2:1960 \u2018Rules for rounding off numerical\nvalues (revised)\u2019.",
          "bbox": [
            40.87,
            369.81,
            489.24,
            406.37
          ],
          "block_id": "b2_8",
          "font_size": 9.6,
          "is_bold": false,
          "is_heading": false
        }
      ],
      "images": [],
      "dimensions": {
        "width": 523.823974609375,
        "height": 759.5360107421875
      },
      "image_id_map": {}
    },
    {
      "page_num": 3,
      "blocks": [
        {
          "type": "text",
          "content": "Is 15173:2002",
          "bbox": [
            417.67,
            22.18,
            475.98,
            34.98
          ],
          "block_id": "b3_0",
          "font_size": 9.6,
          "is_bold": false,
          "is_heading": false
        },
        {
          "type": "text",
          "content": "Indian Standard",
          "bbox": [
            201.67,
            46.74,
            311.12,
            66.08
          ],
          "block_id": "b3_1",
          "font_size": 15.8,
          "is_bold": false,
          "is_heading": true
        },
        {
          "type": "text",
          "content": "METHODS OF TEST FOR TARS AND BITUMINOUS\nMATERIALS \u2014 DETERMINATION\nOF BREAKING\nPOINT FOR CATIONIC BITUMEN EMULSION",
          "bbox": [
            63.19,
            72.73,
            449.8,
            136.1
          ],
          "block_id": "b3_2",
          "font_size": 15.8,
          "is_bold": false,
          "is_heading": true
        },
        {
          "type": "text",
          "content": "1 SCOPE",
          "bbox": [
            42.07,
            144.82,
            79.76,
            157.62
          ],
          "block_id": "b3_3",
          "font_size": 9.6,
          "is_bold": false,
          "is_heading": false
        },
        {
          "type": "text",
          "content": "Before starting the test, the silica fines shall be dried\nin an oven at 120\u00b0C and kept in a sealed container.",
          "bbox": [
            270.55,
            144.82,
            482.0,
            169.38
          ],
          "block_id": "b3_20",
          "font_size": 9.6,
          "is_bold": false,
          "is_heading": false
        },
        {
          "type": "text",
          "content": "This standard covers method for determination\nof\nbreaking point of a cationic bitumen emulsion with\nrespect to mineral fines. It applies to emulsion of pure\nbitumen and to emulsion made of cut-back or fluxed\nbitumens.",
          "bbox": [
            41.83,
            162.58,
            252.59,
            222.43
          ],
          "block_id": "b3_4",
          "font_size": 9.6,
          "is_bold": false,
          "is_heading": false
        },
        {
          "type": "text",
          "content": "5 APPARATUS",
          "bbox": [
            270.55,
            177.47,
            332.94,
            190.27
          ],
          "block_id": "b3_21",
          "font_size": 9.6,
          "is_bold": false,
          "is_heading": false
        },
        {
          "type": "text",
          "content": "5.1 Conical shaped pan with a non-stick surface,\nhaving an opening of 2.5 mm diameter such that the\nflow of fines is between 0.3 to 0.5 g/s or sand pouring\ncylinder device with which it is possible to obtain the\nsame rate of flow. An example of the apparatus to be\nused is shown in Fig. 1 to 4.",
          "bbox": [
            270.55,
            194.99,
            482.46,
            267.07
          ],
          "block_id": "b3_22",
          "font_size": 9.6,
          "is_bold": false,
          "is_heading": false
        },
        {
          "type": "text",
          "content": "2 NORMATIVE\nREFERENCE",
          "bbox": [
            42.07,
            230.51,
            170.0,
            243.31
          ],
          "block_id": "b3_5",
          "font_size": 9.6,
          "is_bold": false,
          "is_heading": false
        },
        {
          "type": "text",
          "content": "The following Indian Standard contains provision\nwhich, through reference\nin this text, constitutes\nprovision of this standard. At the time of publication,\nthe edition indicated was valid, All standards are\nsubject to revision and parties to agreements based on\nthis standard\nare encouraged\nto investigate\nthe\npossibility of applying the most recent edition of the\nstandard indicated below:",
          "bbox": [
            41.59,
            248.27,
            253.03,
            343.39
          ],
          "block_id": "b3_6",
          "font_size": 9.6,
          "is_bold": false,
          "is_heading": false
        },
        {
          "type": "text",
          "content": "5.2 Enamel dish measuring 20 cm inside diameter and\n10 cm high.",
          "bbox": [
            270.55,
            272.03,
            482.21,
            296.35
          ],
          "block_id": "b3_23",
          "font_size": 9.6,
          "is_bold": false,
          "is_heading": false
        },
        {
          "type": "text",
          "content": "5.3 Nickel spatula, 20 cm long.",
          "bbox": [
            270.55,
            301.31,
            396.31,
            314.11
          ],
          "block_id": "b3_24",
          "font_size": 9.6,
          "is_bold": false,
          "is_heading": false
        },
        {
          "type": "text",
          "content": "5.4 Thermostat regulated tank.",
          "bbox": [
            270.79,
            319.07,
            394.38,
            331.87
          ],
          "block_id": "b3_25",
          "font_size": 9.6,
          "is_bold": false,
          "is_heading": false
        },
        {
          "type": "text",
          "content": "5.5 Balance capable of weighing\nto an accuracy\nof 0.1 g.",
          "bbox": [
            270.55,
            336.83,
            479.56,
            361.39
          ],
          "block_id": "b3_26",
          "font_size": 9.6,
          "is_bold": false,
          "is_heading": false
        },
        {
          "type": "text",
          "content": "IS No.\nTitle\n334:2002\nGlossmy of terms relating to bitumen\nand tar  (third revision)",
          "bbox": [
            41.11,
            348.35,
            253.27,
            385.01
          ],
          "block_id": "b3_7",
          "font_size": 9.6,
          "is_bold": true,
          "is_heading": true
        },
        {
          "type": "text",
          "content": "6 PREPARATION\nOF THE SAMPLE",
          "bbox": [
            270.55,
            369.23,
            431.85,
            382.03
          ],
          "block_id": "b3_27",
          "font_size": 9.6,
          "is_bold": false,
          "is_heading": false
        },
        {
          "type": "text",
          "content": "3  TERMINOLOGY",
          "bbox": [
            40.87,
            386.74,
            120.05,
            399.65
          ],
          "block_id": "b3_8",
          "font_size": 9.1,
          "is_bold": true,
          "is_heading": true
        },
        {
          "type": "text",
          "content": "6.1 A sample of bitumen emulsion is filtered through\na mesh of the size of 600 pm and made thoroughly\nhomogenized by stirring.",
          "bbox": [
            270.55,
            386.99,
            481.28,
            423.55
          ],
          "block_id": "b3_28",
          "font_size": 9.6,
          "is_bold": false,
          "is_heading": false
        },
        {
          "type": "text",
          "content": "For the purpose of this standar~ the definitions given\nin IS 334 and the following shall apply.",
          "bbox": [
            41.11,
            404.5,
            252.54,
            429.06
          ],
          "block_id": "b3_9",
          "font_size": 9.6,
          "is_bold": false,
          "is_heading": false
        },
        {
          "type": "text",
          "content": "6.2 The amount of reference fines necessary for the\ntest is taken from a stock that has previously been\nhomogenized.",
          "bbox": [
            270.31,
            428.27,
            482.22,
            465.07
          ],
          "block_id": "b3_29",
          "font_size": 9.6,
          "is_bold": false,
          "is_heading": false
        },
        {
          "type": "text",
          "content": "3.1 Breaking Point",
          "bbox": [
            40.63,
            436.91,
            119.61,
            449.71
          ],
          "block_id": "b3_10",
          "font_size": 9.6,
          "is_bold": false,
          "is_heading": false
        },
        {
          "type": "text",
          "content": "The amount of reference fines required to induce the\nbreaking point of 100 g of emulsion is to be added\nsteadily to the emulsion according to a conventional\nprocedure. The breaking point is then calculated.",
          "bbox": [
            40.63,
            454.67,
            252.78,
            502.99
          ],
          "block_id": "b3_11",
          "font_size": 9.6,
          "is_bold": false,
          "is_heading": false
        },
        {
          "type": "text",
          "content": "7 PROCEDURE",
          "bbox": [
            270.31,
            473.15,
            335.57,
            485.95
          ],
          "block_id": "b3_30",
          "font_size": 9.6,
          "is_bold": false,
          "is_heading": false
        },
        {
          "type": "text",
          "content": "7.1 Keep the emulsion to be tested and 1kg of reference\nfines in sealed containers in a thermostat controlled\ntank, regulated to a temperature of 25 * 1\u2018C for one\nhour before carrying out the test.",
          "bbox": [
            270.31,
            490.91,
            482.22,
            539.47
          ],
          "block_id": "b3_31",
          "font_size": 9.6,
          "is_bold": false,
          "is_heading": false
        },
        {
          "type": "text",
          "content": "4 REAGENTS",
          "bbox": [
            40.63,
            511.31,
            98.72,
            524.11
          ],
          "block_id": "b3_12",
          "font_size": 9.6,
          "is_bold": false,
          "is_heading": false
        },
        {
          "type": "text",
          "content": "4.1 Silica Fines",
          "bbox": [
            40.63,
            531.47,
            104.45,
            544.27
          ],
          "block_id": "b3_13",
          "font_size": 9.6,
          "is_bold": false,
          "is_heading": false
        },
        {
          "type": "text",
          "content": "7.2 Weigh to an accuracy of 0.1 g mass (ml) of the\nenamel dish containing the nickel spatula.",
          "bbox": [
            270.31,
            544.43,
            481.74,
            568.99
          ],
          "block_id": "b3_32",
          "font_size": 9.6,
          "is_bold": false,
          "is_heading": false
        },
        {
          "type": "text",
          "content": "Natural\nsilica fines having\nsilicon\noxide (SiOJ\npercentage of more than 98 pet$ent and density of\n2.65 g/ml with neutral pH value. The range of particle\nsize shall be as given in Table 1.",
          "bbox": [
            40.87,
            547.79,
            252.59,
            596.11
          ],
          "block_id": "b3_14",
          "font_size": 9.6,
          "is_bold": false,
          "is_heading": false
        },
        {
          "type": "text",
          "content": "7.3 Weigh approximately 100 g to within 0.1 g of the\nemulsion sample into the dish. The mass of the dish,\nspatula and emulsion together, determine to within\n0.1 g (m*).",
          "bbox": [
            269.83,
            573.72,
            481.74,
            622.52
          ],
          "block_id": "b3_33",
          "font_size": 9.6,
          "is_bold": false,
          "is_heading": false
        },
        {
          "type": "text",
          "content": "Table 1 Range of Particle Size",
          "bbox": [
            83.11,
            603.95,
            210.54,
            616.75
          ],
          "block_id": "b3_15",
          "font_size": 9.6,
          "is_bold": false,
          "is_heading": false
        },
        {
          "type": "text",
          "content": "Residue on Sieve, ~m\n(1)",
          "bbox": [
            61.03,
            623.95,
            132.02,
            643.87
          ],
          "block_id": "b3_16",
          "font_size": 7.9,
          "is_bold": false,
          "is_heading": false
        },
        {
          "type": "text",
          "content": "Percentage\n(2)",
          "bbox": [
            186.56,
            623.95,
            221.78,
            644.11
          ],
          "block_id": "b3_18",
          "font_size": 7.9,
          "is_bold": false,
          "is_heading": false
        },
        {
          "type": "text",
          "content": "7.4 The mass of added emulsion(E) is equal to",
          "bbox": [
            270.31,
            627.24,
            456.57,
            640.04
          ],
          "block_id": "b3_34",
          "font_size": 9.6,
          "is_bold": false,
          "is_heading": false
        },
        {
          "type": "text",
          "content": "100\n80\n63\n50\n40\nPassing 40",
          "bbox": [
            61.75,
            645.55,
            95.71,
            704.59
          ],
          "block_id": "b3_17",
          "font_size": 7.9,
          "is_bold": false,
          "is_heading": false
        },
        {
          "type": "text",
          "content": "lto5\n5to  10\n15t025\nloto20\n25 to 35\n17t030",
          "bbox": [
            188.71,
            645.55,
            215.82,
            704.83
          ],
          "block_id": "b3_19",
          "font_size": 7.9,
          "is_bold": false,
          "is_heading": false
        },
        {
          "type": "text",
          "content": "E=m2\u2013m,",
          "bbox": [
            351.19,
            646.45,
            386.21,
            657.65
          ],
          "block_id": "b3_35",
          "font_size": 8.6,
          "is_bold": true,
          "is_heading": true
        },
        {
          "type": "text",
          "content": "7.5  Place the enamel dish in the thermostatwontrolled\ntank in which the water is maintained at a temperature\nof25 * lot.",
          "bbox": [
            269.59,
            662.5,
            479.82,
            699.06
          ],
          "block_id": "b3_36",
          "font_size": 9.6,
          "is_bold": true,
          "is_heading": true
        }
      ],
      "images": [],
      "dimensions": {
        "width": 526.2319946289062,
        "height": 752.3360595703125
      },
      "image_id_map": {}
    },
    {
      "page_num": 4,
      "blocks": [
        {
          "type": "text",
          "content": "Is 15173:2002",
          "bbox": [
            46.78,
            17.67,
            104.84,
            30.47
          ],
          "block_id": "b4_0",
          "font_size": 9.6,
          "is_bold": false,
          "is_heading": false
        },
        {
          "type": "text",
          "content": "I",
          "bbox": [
            261.34,
            42.71,
            263.98,
            53.27
          ],
          "block_id": "b4_2",
          "font_size": 7.9,
          "is_bold": false,
          "is_heading": false
        },
        {
          "type": "text",
          "content": "\\",
          "bbox": [
            371.75,
            214.31,
            373.95,
            224.88
          ],
          "block_id": "b4_3",
          "font_size": 7.9,
          "is_bold": false,
          "is_heading": false
        },
        {
          "type": "text",
          "content": "(\nI",
          "bbox": [
            209.5,
            221.03,
            427.97,
            235.75
          ],
          "block_id": "b4_4",
          "font_size": 9.6,
          "is_bold": true,
          "is_heading": true
        },
        {
          "type": "text",
          "content": "I\nI\ni\nt\u2019\nL\nSCREW\nF/90 N3 X 15,\nSTAINLESS\nSTEEL",
          "bbox": [
            205.18,
            231.45,
            318.94,
            304.27
          ],
          "block_id": "b4_5",
          "font_size": 41.0,
          "is_bold": true,
          "is_heading": true
        },
        {
          "type": "text",
          "content": "Plateareofnon-PlasticizedPVC",
          "bbox": [
            136.78,
            326.31,
            244.99,
            339.11
          ],
          "block_id": "b4_6",
          "font_size": 9.6,
          "is_bold": false,
          "is_heading": false
        },
        {
          "type": "text",
          "content": "NOTE \u2014 Pan, Tray and",
          "bbox": [
            57.34,
            327.6,
            135.23,
            338.16
          ],
          "block_id": "b4_1",
          "font_size": 7.9,
          "is_bold": false,
          "is_heading": false
        },
        {
          "type": "text",
          "content": "FIG.  1  GENERAL VIEW OF THE CONICAL PAN",
          "bbox": [
            184.06,
            343.59,
            354.94,
            356.39
          ],
          "block_id": "b4_7",
          "font_size": 8.5,
          "is_bold": false,
          "is_heading": false
        },
        {
          "type": "text",
          "content": "r",
          "bbox": [
            209.5,
            614.04,
            220.6,
            653.34
          ],
          "block_id": "b4_8",
          "font_size": 28.5,
          "is_bold": true,
          "is_heading": true
        },
        {
          "type": "text",
          "content": "All dimensionsin millimetres",
          "bbox": [
            225.82,
            680.64,
            318.68,
            691.2
          ],
          "block_id": "b4_9",
          "font_size": 7.9,
          "is_bold": false,
          "is_heading": false
        },
        {
          "type": "text",
          "content": "FIG. 2 THE PAN",
          "bbox": [
            236.38,
            697.92,
            297.82,
            708.48
          ],
          "block_id": "b4_10",
          "font_size": 7.9,
          "is_bold": false,
          "is_heading": false
        },
        {
          "type": "text",
          "content": "2",
          "bbox": [
            265.18,
            720.0,
            269.14,
            730.56
          ],
          "block_id": "b4_11",
          "font_size": 7.9,
          "is_bold": false,
          "is_heading": false
        }
      ],
      "images": [],
      "dimensions": {
        "width": 511.9119873046875,
        "height": 764.2640380859375
      },
      "image_id_map": {}
    },
    {
      "page_num": 5,
      "blocks": [
        {
          "type": "text",
          "content": "Is 15173:2002",
          "bbox": [
            415.99,
            15.7,
            474.3,
            28.5
          ],
          "block_id": "b5_0",
          "font_size": 9.6,
          "is_bold": false,
          "is_heading": false
        },
        {
          "type": "text",
          "content": "2X27",
          "bbox": [
            134.71,
            42.43,
            161.8,
            54.99
          ],
          "block_id": "b5_1",
          "font_size": 12.5,
          "is_bold": false,
          "is_heading": true
        },
        {
          "type": "text",
          "content": "I\n4-1\ntl\nt\nU,\n//\na\n1!  I",
          "bbox": [
            90.31,
            54.31,
            479.91,
            102.4
          ],
          "block_id": "b5_2",
          "font_size": 18.7,
          "is_bold": true,
          "is_heading": true
        },
        {
          "type": "text",
          "content": "WA\nI\n1\n1",
          "bbox": [
            204.79,
            78.1,
            314.11,
            90.9
          ],
          "block_id": "b5_3",
          "font_size": 9.6,
          "is_bold": false,
          "is_heading": false
        },
        {
          "type": "text",
          "content": "A\n14w\nT\n4  CHANNEL 5 X 5",
          "bbox": [
            173.83,
            88.98,
            431.32,
            127.43
          ],
          "block_id": "b5_4",
          "font_size": 18.7,
          "is_bold": true,
          "is_heading": true
        },
        {
          "type": "text",
          "content": "\u2014\n\u2014.\u2014\n.\u2014-\u2014\n.\u2014\nm \u2014-\u2014\n.-\n%",
          "bbox": [
            77.35,
            151.73,
            470.27,
            180.3
          ],
          "block_id": "b5_5",
          "font_size": 11.5,
          "is_bold": true,
          "is_heading": true
        },
        {
          "type": "text",
          "content": "\u2014",
          "bbox": [
            476.47,
            155.72,
            485.11,
            167.59
          ],
          "block_id": "b5_19",
          "font_size": 8.6,
          "is_bold": false,
          "is_heading": false
        },
        {
          "type": "text",
          "content": "73\n-  -zJ",
          "bbox": [
            166.39,
            193.61,
            336.7,
            275.06
          ],
          "block_id": "b5_7",
          "font_size": 35.4,
          "is_bold": true,
          "is_heading": true
        },
        {
          "type": "text",
          "content": "45",
          "bbox": [
            134.95,
            216.19,
            147.42,
            228.75
          ],
          "block_id": "b5_6",
          "font_size": 12.5,
          "is_bold": false,
          "is_heading": true
        },
        {
          "type": "text",
          "content": "Alldimensionsinmillimetres.",
          "bbox": [
            220.39,
            301.06,
            322.86,
            313.86
          ],
          "block_id": "b5_8",
          "font_size": 9.6,
          "is_bold": false,
          "is_heading": false
        },
        {
          "type": "text",
          "content": "FIG.  3  THE TRAY",
          "bbox": [
            228.31,
            318.1,
            295.02,
            330.9
          ],
          "block_id": "b5_9",
          "font_size": 8.5,
          "is_bold": false,
          "is_heading": false
        },
        {
          "type": "text",
          "content": "I\nI\nI\nI\nI",
          "bbox": [
            167.83,
            354.67,
            348.55,
            367.39
          ],
          "block_id": "b5_10",
          "font_size": 7.9,
          "is_bold": false,
          "is_heading": false
        },
        {
          "type": "text",
          "content": "L\n(",
          "bbox": [
            118.87,
            363.79,
            383.59,
            377.24
          ],
          "block_id": "b5_11",
          "font_size": 7.9,
          "is_bold": false,
          "is_heading": false
        },
        {
          "type": "text",
          "content": "\\\nI\nI\nII",
          "bbox": [
            173.11,
            376.99,
            339.19,
            388.52
          ],
          "block_id": "b5_12",
          "font_size": 7.9,
          "is_bold": false,
          "is_heading": false
        },
        {
          "type": "text",
          "content": "4dn",
          "bbox": [
            244.39,
            397.22,
            253.03,
            401.54
          ],
          "block_id": "b5_13",
          "font_size": 4.3,
          "is_bold": false,
          "is_heading": false
        },
        {
          "type": "text",
          "content": "1-",
          "bbox": [
            221.83,
            426.91,
            228.49,
            437.47
          ],
          "block_id": "b5_14",
          "font_size": 7.9,
          "is_bold": false,
          "is_heading": false
        },
        {
          "type": "text",
          "content": "35\n7\u2019",
          "bbox": [
            227.59,
            477.61,
            297.43,
            546.94
          ],
          "block_id": "b5_15",
          "font_size": 38.6,
          "is_bold": true,
          "is_heading": true
        },
        {
          "type": "text",
          "content": "k",
          "bbox": [
            119.35,
            597.07,
            123.31,
            607.63
          ],
          "block_id": "b5_16",
          "font_size": 7.9,
          "is_bold": false,
          "is_heading": false
        },
        {
          "type": "text",
          "content": "z\u2019 4 Tr 03.2\nTO\nBE PIERCED",
          "bbox": [
            103.03,
            616.6,
            301.94,
            652.23
          ],
          "block_id": "b5_17",
          "font_size": 17.3,
          "is_bold": true,
          "is_heading": true
        },
        {
          "type": "text",
          "content": "COUNTERSUNK\nON MOUNTING  -/",
          "bbox": [
            117.43,
            640.98,
            309.0,
            660.91
          ],
          "block_id": "b5_18",
          "font_size": 9.6,
          "is_bold": true,
          "is_heading": true
        },
        {
          "type": "text",
          "content": "90\u201d prf 1.5",
          "bbox": [
            117.67,
            658.98,
            169.56,
            672.19
          ],
          "block_id": "b5_20",
          "font_size": 9.6,
          "is_bold": true,
          "is_heading": true
        },
        {
          "type": "text",
          "content": "All dimensionsin millimetres",
          "bbox": [
            212.47,
            677.47,
            305.33,
            688.03
          ],
          "block_id": "b5_21",
          "font_size": 7.9,
          "is_bold": false,
          "is_heading": false
        },
        {
          "type": "text",
          "content": "FIG.  4  THE PLATE",
          "bbox": [
            219.67,
            692.98,
            289.06,
            705.78
          ],
          "block_id": "b5_22",
          "font_size": 8.5,
          "is_bold": false,
          "is_heading": false
        },
        {
          "type": "text",
          "content": "3",
          "bbox": [
            251.35,
            714.91,
            255.31,
            725.47
          ],
          "block_id": "b5_23",
          "font_size": 7.9,
          "is_bold": false,
          "is_heading": false
        }
      ],
      "images": [],
      "dimensions": {
        "width": 524.2319946289062,
        "height": 752.3360595703125
      },
      "image_id_map": {}
    },
    {
      "page_num": 6,
      "blocks": [
        {
          "type": "text",
          "content": "IS 15173:2002",
          "bbox": [
            22.06,
            16.91,
            80.6,
            29.71
          ],
          "block_id": "b6_0",
          "font_size": 9.6,
          "is_bold": false,
          "is_heading": false
        },
        {
          "type": "text",
          "content": "7.6 Fill the pan with the reference fines that have been\nkept at 25\u00b0C.",
          "bbox": [
            22.06,
            40.43,
            235.62,
            64.99
          ],
          "block_id": "b6_1",
          "font_size": 9.6,
          "is_bold": false,
          "is_heading": false
        },
        {
          "type": "text",
          "content": "8.LI  Interpretation\nof Results",
          "bbox": [
            253.9,
            40.66,
            372.45,
            53.57
          ],
          "block_id": "b6_15",
          "font_size": 9.1,
          "is_bold": true,
          "is_heading": true
        },
        {
          "type": "text",
          "content": "The  grades of emulsion sitall be identified based on\nthe breaking point (Ic)values obtained at 8.1 as given\nbelow:",
          "bbox": [
            253.66,
            58.43,
            466.3,
            94.99
          ],
          "block_id": "b6_16",
          "font_size": 9.6,
          "is_bold": true,
          "is_heading": true
        },
        {
          "type": "text",
          "content": "7.7 Put the pan containing approximately 500 g of\nreference fines on its support.",
          "bbox": [
            22.3,
            69.95,
            235.94,
            94.75
          ],
          "block_id": "b6_2",
          "font_size": 9.6,
          "is_bold": false,
          "is_heading": false
        },
        {
          "type": "text",
          "content": "7.8 open the pan trap, The fines then drop through\nsteadily into the dish. At the same time, thoroughly\nmix  1 turn\nper second,\nusing the spatula.",
          "bbox": [
            22.3,
            99.47,
            234.94,
            136.03
          ],
          "block_id": "b6_3",
          "font_size": 9.6,
          "is_bold": false,
          "is_heading": false
        },
        {
          "type": "text",
          "content": "If 1=is less than 20, it shall be identified as\nrapid setting (RS) grade;\nIf 1=is 20-40,\nit shall be identified\nas\nmedium setting (A@ grade; and\nIf lc is above 40, it shaIl be identified as slow\nsetting (SS) grade.",
          "bbox": [
            289.18,
            99.71,
            466.7,
            174.91
          ],
          "block_id": "b6_20",
          "font_size": 9.6,
          "is_bold": false,
          "is_heading": false
        },
        {
          "type": "text",
          "content": "a)",
          "bbox": [
            271.66,
            99.95,
            279.1,
            112.75
          ],
          "block_id": "b6_17",
          "font_size": 9.6,
          "is_bold": false,
          "is_heading": false
        },
        {
          "type": "text",
          "content": "b)",
          "bbox": [
            271.42,
            125.39,
            279.37,
            138.19
          ],
          "block_id": "b6_18",
          "font_size": 9.6,
          "is_bold": false,
          "is_heading": false
        },
        {
          "type": "text",
          "content": "7.9 Close the trap when the mixture becomes pasty\nand an isolated clot forms not adhering to the sides of\nthe dish. This clot formation\nis characteristic\nof\nbreaking of emulsion.",
          "bbox": [
            22.53,
            140.75,
            236.17,
            189.07
          ],
          "block_id": "b6_4",
          "font_size": 9.6,
          "is_bold": false,
          "is_heading": false
        },
        {
          "type": "text",
          "content": "c)",
          "bbox": [
            271.66,
            150.59,
            279.1,
            163.39
          ],
          "block_id": "b6_19",
          "font_size": 9.6,
          "is_bold": false,
          "is_heading": false
        },
        {
          "type": "text",
          "content": "9 TEST REPORT",
          "bbox": [
            254.14,
            178.92,
            327.1,
            191.72
          ],
          "block_id": "b6_21",
          "font_size": 9.6,
          "is_bold": false,
          "is_heading": false
        },
        {
          "type": "text",
          "content": "NOTE \u2014 With certain emulsions the formation of a clot is not\nclear and does not allow a proper result to be recorded. If this is\nthe case, it shall be mentioned in the test  report.",
          "bbox": [
            34.78,
            193.88,
            236.86,
            224.11
          ],
          "block_id": "b6_5",
          "font_size": 8.8,
          "is_bold": false,
          "is_heading": false
        },
        {
          "type": "text",
          "content": "The test report shall include the following information:",
          "bbox": [
            254.14,
            196.44,
            465.34,
            209.24
          ],
          "block_id": "b6_22",
          "font_size": 9.6,
          "is_bold": false,
          "is_heading": false
        },
        {
          "type": "text",
          "content": "The type of emulsions tests;\nThe results obtained, notably if the forma-\ntion of clot is ditlicult and does not provide a\nclear test resttlc\nGrade of emulsion; and\nAny details not dealt with in the standard and\nany incidents likely to have htfluenced the\nresults.",
          "bbox": [
            289.42,
            213.96,
            466.96,
            315.08
          ],
          "block_id": "b6_25",
          "font_size": 9.6,
          "is_bold": false,
          "is_heading": false
        },
        {
          "type": "text",
          "content": "a)\nb)",
          "bbox": [
            271.66,
            214.2,
            279.61,
            240.92
          ],
          "block_id": "b6_23",
          "font_size": 9.6,
          "is_bold": false,
          "is_heading": false
        },
        {
          "type": "text",
          "content": "7.10\nRe-weigh\nthe\ndkh\nwith\nthe nickel spatula to\nwithin 0.1 g after having wiped the spatula. This is\nreferred to as  m3.",
          "bbox": [
            22.77,
            228.11,
            237.06,
            264.43
          ],
          "block_id": "b6_6",
          "font_size": 9.6,
          "is_bold": false,
          "is_heading": false
        },
        {
          "type": "text",
          "content": "c)\nd)",
          "bbox": [
            271.9,
            265.32,
            279.85,
            291.8
          ],
          "block_id": "b6_24",
          "font_size": 9.6,
          "is_bold": false,
          "is_heading": false
        },
        {
          "type": "text",
          "content": "7,11 The added mass of fines (m) is equal to",
          "bbox": [
            23.02,
            269.39,
            202.07,
            282.19
          ],
          "block_id": "b6_7",
          "font_size": 9.6,
          "is_bold": false,
          "is_heading": false
        },
        {
          "type": "text",
          "content": "m=m,\n\u2013mz",
          "bbox": [
            105.58,
            288.62,
            151.17,
            299.81
          ],
          "block_id": "b6_8",
          "font_size": 8.6,
          "is_bold": true,
          "is_heading": true
        },
        {
          "type": "text",
          "content": "8  CALCULATION",
          "bbox": [
            23.01,
            308.03,
            99.08,
            320.94
          ],
          "block_id": "b6_9",
          "font_size": 9.1,
          "is_bold": true,
          "is_heading": true
        },
        {
          "type": "text",
          "content": "10  PRECISION",
          "bbox": [
            254.86,
            319.32,
            317.02,
            332.69
          ],
          "block_id": "b6_26",
          "font_size": 9.6,
          "is_bold": true,
          "is_heading": true
        },
        {
          "type": "text",
          "content": "8.1 The breaking point (IJ of emulsion is calculated\nas follows:",
          "bbox": [
            22.78,
            325.31,
            235.87,
            350.11
          ],
          "block_id": "b6_10",
          "font_size": 9.6,
          "is_bold": false,
          "is_heading": false
        },
        {
          "type": "text",
          "content": "10.1 Repeatability",
          "bbox": [
            255.1,
            340.29,
            330.45,
            353.58
          ],
          "block_id": "b6_27",
          "font_size": 9.6,
          "is_bold": true,
          "is_heading": true
        },
        {
          "type": "text",
          "content": "The  results obtained by the same operator shall not\ndiffer by more than 0.03 IC.",
          "bbox": [
            254.38,
            357.72,
            466.55,
            382.76
          ],
          "block_id": "b6_28",
          "font_size": 9.6,
          "is_bold": true,
          "is_heading": true
        },
        {
          "type": "text",
          "content": "Ic  =:XIOO",
          "bbox": [
            106.54,
            366.83,
            148.99,
            380.21
          ],
          "block_id": "b6_11",
          "font_size": 9.6,
          "is_bold": true,
          "is_heading": true
        },
        {
          "type": "text",
          "content": "10.2 Reproducibility",
          "bbox": [
            255.1,
            390.12,
            335.48,
            402.92
          ],
          "block_id": "b6_29",
          "font_size": 9.6,
          "is_bold": false,
          "is_heading": false
        },
        {
          "type": "text",
          "content": "where",
          "bbox": [
            22.78,
            393.23,
            46.27,
            406.03
          ],
          "block_id": "b6_12",
          "font_size": 9.6,
          "is_bold": false,
          "is_heading": false
        },
        {
          "type": "text",
          "content": "Preliminary laboratory test results have led to this\nrepeatability value. Other tests are to be carried out to\nconfirm\nthis value and also to add a value\nfor\nreproducibility.",
          "bbox": [
            254.38,
            407.88,
            466.79,
            455.96
          ],
          "block_id": "b6_30",
          "font_size": 9.6,
          "is_bold": false,
          "is_heading": false
        },
        {
          "type": "text",
          "content": "E\n=  mass of emulsion; and",
          "bbox": [
            41.02,
            410.51,
            162.19,
            423.41
          ],
          "block_id": "b6_13",
          "font_size": 9.1,
          "is_bold": true,
          "is_heading": true
        },
        {
          "type": "text",
          "content": "m\n=  mass of reference fines added.\nWhen presenting the results, give the breaking point\nin relation to silica fines. The breaking point is the\nmean of the results of three tests.",
          "bbox": [
            23.01,
            424.43,
            236.61,
            474.67
          ],
          "block_id": "b6_14",
          "font_size": 9.6,
          "is_bold": true,
          "is_heading": true
        },
        {
          "type": "text",
          "content": "4",
          "bbox": [
            243.82,
            712.21,
            248.61,
            725.01
          ],
          "block_id": "b6_31",
          "font_size": 9.6,
          "is_bold": false,
          "is_heading": false
        }
      ],
      "images": [],
      "dimensions": {
        "width": 485.31195068359375,
        "height": 769.2640380859375
      },
      "image_id_map": {}
    },
    {
      "page_num": 7,
      "blocks": [
        {
          "type": "text",
          "content": "IS  15173:2002",
          "bbox": [
            409.27,
            27.02,
            468.06,
            40.4
          ],
          "block_id": "b7_0",
          "font_size": 9.6,
          "is_bold": true,
          "is_heading": true
        },
        {
          "type": "text",
          "content": "ANNEX A",
          "bbox": [
            224.47,
            52.75,
            277.21,
            67.37
          ],
          "block_id": "b7_1",
          "font_size": 10.6,
          "is_bold": true,
          "is_heading": true
        },
        {
          "type": "text",
          "content": "(Foreword)",
          "bbox": [
            224.71,
            73.22,
            278.44,
            87.28
          ],
          "block_id": "b7_2",
          "font_size": 11.5,
          "is_bold": false,
          "is_heading": false
        },
        {
          "type": "text",
          "content": "COMMITTEE\nCOMPOSITION",
          "bbox": [
            181.51,
            93.03,
            314.46,
            105.82
          ],
          "block_id": "b7_3",
          "font_size": 9.6,
          "is_bold": false,
          "is_heading": false
        },
        {
          "type": "text",
          "content": "Bitumen, Tar and Their Products Sectional Committee, PCD 6",
          "bbox": [
            125.11,
            110.79,
            379.27,
            123.59
          ],
          "block_id": "b7_4",
          "font_size": 9.6,
          "is_bold": false,
          "is_heading": false
        },
        {
          "type": "text",
          "content": "Representative(s)",
          "bbox": [
            320.23,
            132.13,
            369.87,
            141.14
          ],
          "block_id": "b7_31",
          "font_size": 7.0,
          "is_bold": true,
          "is_heading": true
        },
        {
          "type": "text",
          "content": "Organization",
          "bbox": [
            88.87,
            134.05,
            126.99,
            143.06
          ],
          "block_id": "b7_5",
          "font_size": 7.0,
          "is_bold": true,
          "is_heading": true
        },
        {
          "type": "text",
          "content": "PROFP. K. Won\n(Chsw\u201dnnan)\nSmuSum BOSE(AlternateI)\nDRP. K. Jm (Alternate II)",
          "bbox": [
            282.07,
            143.75,
            386.95,
            173.99
          ],
          "block_id": "b7_32",
          "font_size": 7.9,
          "is_bold": false,
          "is_heading": false
        },
        {
          "type": "text",
          "content": "Central RoadResearchInstitute,New Delhi",
          "bbox": [
            29.11,
            145.19,
            165.64,
            155.75
          ],
          "block_id": "b7_6",
          "font_size": 7.9,
          "is_bold": false,
          "is_heading": false
        },
        {
          "type": "text",
          "content": "SmuJ. A. Jmut\n~ Nozm ~ORGE(~/ternate)",
          "bbox": [
            282.31,
            176.39,
            388.12,
            196.31
          ],
          "block_id": "b7_33",
          "font_size": 7.9,
          "is_bold": false,
          "is_heading": false
        },
        {
          "type": "text",
          "content": "Bharat PetroleumCorporationLimited,Murnbai",
          "bbox": [
            29.83,
            177.83,
            180.99,
            188.39
          ],
          "block_id": "b7_7",
          "font_size": 7.9,
          "is_bold": false,
          "is_heading": false
        },
        {
          "type": "text",
          "content": "SsmtR K.Cl!tLY\nSmuB.Am  Kw(Ahernafe)",
          "bbox": [
            282.55,
            199.19,
            377.56,
            219.62
          ],
          "block_id": "b7_34",
          "font_size": 7.9,
          "is_bold": true,
          "is_heading": true
        },
        {
          "type": "text",
          "content": "BuildingMaterialsandTechnologypromotionCormcil,NewDelhi",
          "bbox": [
            30.07,
            200.39,
            237.16,
            210.96
          ],
          "block_id": "b7_8",
          "font_size": 7.9,
          "is_bold": false,
          "is_heading": false
        },
        {
          "type": "text",
          "content": "D@remmr)\nA.BHAmAaYA\nSmr U.BHAnACIiARYA\n(Alternate)",
          "bbox": [
            282.55,
            221.51,
            403.24,
            241.91
          ],
          "block_id": "b7_35",
          "font_size": 7.9,
          "is_bold": true,
          "is_heading": true
        },
        {
          "type": "text",
          "content": "Central Fuel ResearchInstitute, Dhanbad",
          "bbox": [
            29.83,
            223.19,
            159.09,
            233.76
          ],
          "block_id": "b7_9",
          "font_size": 7.9,
          "is_bold": false,
          "is_heading": false
        },
        {
          "type": "text",
          "content": "SummmmsmEtwuwm\nExzctmw Exarma  (Alternate)\nSmuv. PArLY\nSrmrR.  Vmtroom-(Altsrrrate)",
          "bbox": [
            282.79,
            244.31,
            391.96,
            287.3
          ],
          "block_id": "b7_36",
          "font_size": 9.7,
          "is_bold": true,
          "is_heading": true
        },
        {
          "type": "text",
          "content": "Central Public Works DcpartmengNewDelhi",
          "bbox": [
            29.83,
            245.51,
            172.6,
            256.08
          ],
          "block_id": "b7_10",
          "font_size": 7.9,
          "is_bold": false,
          "is_heading": false
        },
        {
          "type": "text",
          "content": "Cochin RefineriesLimited,Co&in",
          "bbox": [
            29.83,
            268.07,
            137.78,
            278.64
          ],
          "block_id": "b7_11",
          "font_size": 7.9,
          "is_bold": false,
          "is_heading": false
        },
        {
          "type": "text",
          "content": "fhF.CTOR\nSmus.s. PGRWAL\nSstruA. K. GrmA  (Alternate)",
          "bbox": [
            283.03,
            289.43,
            383.8,
            322.82
          ],
          "block_id": "b7_37",
          "font_size": 9.7,
          "is_bold": true,
          "is_heading": true
        },
        {
          "type": "text",
          "content": "Directorate General of SuppliesandDkposals,New Delhi",
          "bbox": [
            30.31,
            290.63,
            210.04,
            301.2
          ],
          "block_id": "b7_12",
          "font_size": 7.9,
          "is_bold": false,
          "is_heading": false
        },
        {
          "type": "text",
          "content": "Dkectorate of GeneralBorderRoads,New Delhi",
          "bbox": [
            30.55,
            303.35,
            181.96,
            313.92
          ],
          "block_id": "b7_13",
          "font_size": 7.9,
          "is_bold": false,
          "is_heading": false
        },
        {
          "type": "text",
          "content": "Smr R S. S~",
          "bbox": [
            283.51,
            325.43,
            322.9,
            335.99
          ],
          "block_id": "b7_38",
          "font_size": 7.9,
          "is_bold": false,
          "is_heading": false
        },
        {
          "type": "text",
          "content": "Dr Uppal\u2019sTestingandAnalyticalLaboratory,Ghaziabad",
          "bbox": [
            31.27,
            326.15,
            210.0,
            336.72
          ],
          "block_id": "b7_14",
          "font_size": 7.9,
          "is_bold": false,
          "is_heading": false
        },
        {
          "type": "text",
          "content": "EmH. $. S~",
          "bbox": [
            283.51,
            338.15,
            319.78,
            348.71
          ],
          "block_id": "b7_39",
          "font_size": 7.9,
          "is_bold": false,
          "is_heading": false
        },
        {
          "type": "text",
          "content": "DurgapurProjectsLimited, Durgaptsr",
          "bbox": [
            31.27,
            339.11,
            150.26,
            349.68
          ],
          "block_id": "b7_15",
          "font_size": 7.9,
          "is_bold": false,
          "is_heading": false
        },
        {
          "type": "text",
          "content": "COLV.K.P.S-\nLTCOLR.S. Bwuwvw  (Alternate)",
          "bbox": [
            283.51,
            350.87,
            404.68,
            371.54
          ],
          "block_id": "b7_40",
          "font_size": 7.9,
          "is_bold": true,
          "is_heading": true
        },
        {
          "type": "text",
          "content": "Engineer-in-chiefs Branch,ArmyHeadQuarters,New Delhi",
          "bbox": [
            31.51,
            351.59,
            221.8,
            362.16
          ],
          "block_id": "b7_16",
          "font_size": 7.9,
          "is_bold": false,
          "is_heading": false
        },
        {
          "type": "text",
          "content": "HighwayResezuchStation,Chennai",
          "bbox": [
            31.75,
            374.88,
            143.76,
            385.44
          ],
          "block_id": "b7_17",
          "font_size": 7.9,
          "is_bold": false,
          "is_heading": false
        },
        {
          "type": "text",
          "content": "DrREcroR\nDmrrv  Dtro3xrR (Alternate)\nSHSU\nP.RAtENDRAN\nSmrrH.P.mratwam\n(Abnate)",
          "bbox": [
            283.75,
            375.25,
            393.62,
            416.9
          ],
          "block_id": "b7_41",
          "font_size": 11.5,
          "is_bold": true,
          "is_heading": true
        },
        {
          "type": "text",
          "content": "HindustanColasLimited,Mumbai",
          "bbox": [
            31.99,
            397.44,
            140.18,
            408.0
          ],
          "block_id": "b7_18",
          "font_size": 7.9,
          "is_bold": false,
          "is_heading": false
        },
        {
          "type": "text",
          "content": "Sm S.  K.BHATNAGAR\n.%rrrtA. S. Prwwuwr\n(Alternate)",
          "bbox": [
            283.99,
            419.03,
            398.44,
            439.94
          ],
          "block_id": "b7_42",
          "font_size": 7.9,
          "is_bold": true,
          "is_heading": true
        },
        {
          "type": "text",
          "content": "HirrdustarrPetroleumCorporationLimited,Mumbai",
          "bbox": [
            32.23,
            419.76,
            192.75,
            430.32
          ],
          "block_id": "b7_19",
          "font_size": 7.9,
          "is_bold": false,
          "is_heading": false
        },
        {
          "type": "text",
          "content": "klt\nU.c.  GUFTA\nSmu MosmAtwm(Ak-rrate)",
          "bbox": [
            284.23,
            441.83,
            377.05,
            462.26
          ],
          "block_id": "b7_43",
          "font_size": 7.4,
          "is_bold": true,
          "is_heading": true
        },
        {
          "type": "text",
          "content": "Indian Instituteof Petroleum,DebraDun",
          "bbox": [
            32.23,
            442.08,
            158.62,
            452.64
          ],
          "block_id": "b7_20",
          "font_size": 7.9,
          "is_bold": false,
          "is_heading": false
        },
        {
          "type": "text",
          "content": "Star  R. S. StSODIA\nSrrrulkmKw\n(Alternate)",
          "bbox": [
            284.23,
            464.87,
            386.2,
            485.3
          ],
          "block_id": "b7_44",
          "font_size": 7.9,
          "is_bold": true,
          "is_heading": true
        },
        {
          "type": "text",
          "content": "Indian011CorporationLimited(MarketingDWision),Mumbai",
          "bbox": [
            32.47,
            465.12,
            226.83,
            475.68
          ],
          "block_id": "b7_21",
          "font_size": 7.9,
          "is_bold": false,
          "is_heading": false
        },
        {
          "type": "text",
          "content": "Smu  B.R.TYAGI\nSmt M.P. lb~\n(Afterrrde)",
          "bbox": [
            284.47,
            487.43,
            385.24,
            507.83
          ],
          "block_id": "b7_45",
          "font_size": 7.9,
          "is_bold": true,
          "is_heading": true
        },
        {
          "type": "text",
          "content": "Indian0]1CorporationLimited[(R&D)Centrc],Faridabrrd",
          "bbox": [
            32.47,
            487.44,
            217.47,
            498.0
          ],
          "block_id": "b7_22",
          "font_size": 7.9,
          "is_bold": false,
          "is_heading": false
        },
        {
          "type": "text",
          "content": "SrmrU.K. BMW\nSrmtS. K. Prwmo (Alternate)",
          "bbox": [
            284.47,
            510.23,
            390.76,
            530.39
          ],
          "block_id": "b7_46",
          "font_size": 7.9,
          "is_bold": false,
          "is_heading": false
        },
        {
          "type": "text",
          "content": "IndianOil Corporation(R&P),New Delhi",
          "bbox": [
            32.47,
            510.24,
            163.0,
            520.8
          ],
          "block_id": "b7_23",
          "font_size": 7.9,
          "is_bold": false,
          "is_heading": false
        },
        {
          "type": "text",
          "content": "SsrtuK.B. R.uom\nSssarA. V. Smm  (Afternate)",
          "bbox": [
            284.71,
            532.79,
            383.07,
            553.22
          ],
          "block_id": "b7_47",
          "font_size": 7.9,
          "is_bold": true,
          "is_heading": true
        },
        {
          "type": "text",
          "content": "IndianRoadCongress,New Delhi",
          "bbox": [
            32.47,
            532.8,
            138.76,
            543.37
          ],
          "block_id": "b7_24",
          "font_size": 7.9,
          "is_bold": false,
          "is_heading": false
        },
        {
          "type": "text",
          "content": "Srsro MGMTKHANNA",
          "bbox": [
            284.95,
            555.35,
            358.38,
            565.94
          ],
          "block_id": "b7_48",
          "font_size": 7.4,
          "is_bold": true,
          "is_heading": true
        },
        {
          "type": "text",
          "content": "Lloyd Insulations(India)Limited,New Delhi",
          "bbox": [
            32.71,
            555.6,
            173.08,
            566.17
          ],
          "block_id": "b7_25",
          "font_size": 7.9,
          "is_bold": false,
          "is_heading": false
        },
        {
          "type": "text",
          "content": "SW K. K. -\n(Alternate)",
          "bbox": [
            298.87,
            563.99,
            385.48,
            577.28
          ],
          "block_id": "b7_49",
          "font_size": 8.8,
          "is_bold": true,
          "is_heading": true
        },
        {
          "type": "text",
          "content": "Smrr M.S.SwYm Srrrmmt\nSW B. S~\n(Alternate)",
          "bbox": [
            284.95,
            578.15,
            378.76,
            598.58
          ],
          "block_id": "b7_50",
          "font_size": 7.9,
          "is_bold": true,
          "is_heading": true
        },
        {
          "type": "text",
          "content": "MadrasRefineryLimited,Chennai",
          "bbox": [
            32.95,
            578.16,
            140.88,
            588.73
          ],
          "block_id": "b7_26",
          "font_size": 7.9,
          "is_bold": false,
          "is_heading": false
        },
        {
          "type": "text",
          "content": "Smu  K. H.G.mom\nSmuA. K. SW\n(Alternate)",
          "bbox": [
            285.19,
            600.95,
            383.8,
            621.62
          ],
          "block_id": "b7_51",
          "font_size": 7.9,
          "is_bold": true,
          "is_heading": true
        },
        {
          "type": "text",
          "content": "Ministryof Defence(DGQA),New Delhi",
          "bbox": [
            32.95,
            600.96,
            161.56,
            611.53
          ],
          "block_id": "b7_27",
          "font_size": 7.9,
          "is_bold": false,
          "is_heading": false
        },
        {
          "type": "text",
          "content": "Ministryof SurfaceTransport(Departmentof SurfaceTransport),New Delhi",
          "bbox": [
            33.19,
            623.52,
            270.52,
            634.09
          ],
          "block_id": "b7_28",
          "font_size": 7.9,
          "is_bold": false,
          "is_heading": false
        },
        {
          "type": "text",
          "content": "SrnuC. C.  BHAmACHARYA\nStarrS.P. .%rms+ (Alternate)",
          "bbox": [
            285.43,
            623.75,
            380.92,
            644.18
          ],
          "block_id": "b7_52",
          "font_size": 7.4,
          "is_bold": true,
          "is_heading": true
        },
        {
          "type": "text",
          "content": "National BuildingOrganization,New Delhi",
          "bbox": [
            32.95,
            645.84,
            168.52,
            656.41
          ],
          "block_id": "b7_29",
          "font_size": 7.9,
          "is_bold": false,
          "is_heading": false
        },
        {
          "type": "text",
          "content": "Ssrru A. K. L&\nSrm A.G. DHONGADE\n(Alterrrde)",
          "bbox": [
            285.67,
            646.55,
            398.69,
            666.98
          ],
          "block_id": "b7_53",
          "font_size": 7.9,
          "is_bold": true,
          "is_heading": true
        },
        {
          "type": "text",
          "content": ".",
          "bbox": [
            434.95,
            664.56,
            437.35,
            676.43
          ],
          "block_id": "b7_55",
          "font_size": 8.6,
          "is_bold": false,
          "is_heading": false
        },
        {
          "type": "text",
          "content": "NationalTest House.Kolkata",
          "bbox": [
            33.19,
            668.64,
            125.54,
            679.21
          ],
          "block_id": "b7_30",
          "font_size": 7.9,
          "is_bold": false,
          "is_heading": false
        },
        {
          "type": "text",
          "content": ".%ttu A.K.Cswm.moaW\nSsiruS.K. AGARWAL (Alternate)",
          "bbox": [
            285.67,
            669.11,
            393.88,
            689.78
          ],
          "block_id": "b7_54",
          "font_size": 7.4,
          "is_bold": true,
          "is_heading": true
        },
        {
          "type": "text",
          "content": "(Continued\non page 6)",
          "bbox": [
            405.43,
            708.37,
            479.25,
            717.38
          ],
          "block_id": "b7_56",
          "font_size": 7.0,
          "is_bold": true,
          "is_heading": true
        },
        {
          "type": "text",
          "content": "5",
          "bbox": [
            253.99,
            728.57,
            258.31,
            739.77
          ],
          "block_id": "b7_57",
          "font_size": 8.6,
          "is_bold": true,
          "is_heading": true
        }
      ],
      "images": [],
      "dimensions": {
        "width": 507.51202392578125,
        "height": 747.3360595703125
      },
      "image_id_map": {}
    },
    {
      "page_num": 8,
      "blocks": [
        {
          "type": "text",
          "content": "Is 15173:2002",
          "bbox": [
            46.54,
            10.71,
            104.84,
            23.51
          ],
          "block_id": "b8_0",
          "font_size": 9.6,
          "is_bold": false,
          "is_heading": false
        },
        {
          "type": "text",
          "content": "(Contmuedfrom\npage 5)",
          "bbox": [
            46.54,
            36.13,
            127.31,
            45.15
          ],
          "block_id": "b8_1",
          "font_size": 7.0,
          "is_bold": true,
          "is_heading": true
        },
        {
          "type": "text",
          "content": "Representative(s)",
          "bbox": [
            359.98,
            59.17,
            409.61,
            68.19
          ],
          "block_id": "b8_11",
          "font_size": 7.0,
          "is_bold": true,
          "is_heading": true
        },
        {
          "type": "text",
          "content": "Organization",
          "bbox": [
            98.86,
            61.09,
            136.97,
            70.11
          ],
          "block_id": "b8_2",
          "font_size": 7.0,
          "is_bold": true,
          "is_heading": true
        },
        {
          "type": "text",
          "content": "%0  AMITAVACIL4TIERJEE",
          "bbox": [
            300.69,
            76.33,
            406.52,
            88.2
          ],
          "block_id": "b8_12",
          "font_size": 7.8,
          "is_bold": true,
          "is_heading": true
        },
        {
          "type": "text",
          "content": "Public WorksDepartment,Governmentof WestBengal,Kolkata",
          "bbox": [
            47.02,
            78.96,
            247.85,
            89.52
          ],
          "block_id": "b8_3",
          "font_size": 7.9,
          "is_bold": false,
          "is_heading": false
        },
        {
          "type": "text",
          "content": "SmaRABSNDRANATHBASW\n(Alternate)",
          "bbox": [
            314.86,
            87.12,
            429.31,
            97.71
          ],
          "block_id": "b8_13",
          "font_size": 7.9,
          "is_bold": true,
          "is_heading": true
        },
        {
          "type": "text",
          "content": "Smu  V.B.  BORGa",
          "bbox": [
            300.93,
            100.08,
            357.76,
            110.67
          ],
          "block_id": "b8_14",
          "font_size": 7.3,
          "is_bold": true,
          "is_heading": true
        },
        {
          "type": "text",
          "content": "PublicWorks Department,Mumbai",
          "bbox": [
            47.26,
            102.0,
            158.33,
            112.56
          ],
          "block_id": "b8_4",
          "font_size": 7.9,
          "is_bold": false,
          "is_heading": false
        },
        {
          "type": "text",
          "content": "Public Works Department.TamilNadu",
          "bbox": [
            47.26,
            114.48,
            169.09,
            125.04
          ],
          "block_id": "b8_5",
          "font_size": 7.9,
          "is_bold": false,
          "is_heading": false
        },
        {
          "type": "text",
          "content": "SmuN.DAYANANDAN\nsHRtp.  JAYARAMAN\n(,4k7rufe)",
          "bbox": [
            300.94,
            115.69,
            402.84,
            133.17
          ],
          "block_id": "b8_15",
          "font_size": 7.0,
          "is_bold": false,
          "is_heading": false
        },
        {
          "type": "text",
          "content": "SrurrV. P. B.ms.a\n~G.\nP. S. CWWN\n(Alternate)",
          "bbox": [
            301.18,
            136.61,
            412.24,
            155.73
          ],
          "block_id": "b8_16",
          "font_size": 7.0,
          "is_bold": false,
          "is_heading": false
        },
        {
          "type": "text",
          "content": "PublicWorksDepartment,UttarPradesh",
          "bbox": [
            47.5,
            137.04,
            174.64,
            147.6
          ],
          "block_id": "b8_6",
          "font_size": 7.9,
          "is_bold": false,
          "is_heading": false
        },
        {
          "type": "text",
          "content": "DrrR. C. BMUM+",
          "bbox": [
            301.18,
            159.17,
            354.69,
            168.45
          ],
          "block_id": "b8_17",
          "font_size": 7.0,
          "is_bold": false,
          "is_heading": false
        },
        {
          "type": "text",
          "content": "RegionalResemchLaboratory,Jorhat",
          "bbox": [
            47.74,
            160.08,
            165.52,
            170.64
          ],
          "block_id": "b8_7",
          "font_size": 7.9,
          "is_bold": false,
          "is_heading": false
        },
        {
          "type": "text",
          "content": "Smu T. K. ROY\nSmu S. B~~\n(Alternate)",
          "bbox": [
            301.42,
            172.13,
            414.43,
            191.79
          ],
          "block_id": "b8_18",
          "font_size": 7.0,
          "is_bold": true,
          "is_heading": true
        },
        {
          "type": "text",
          "content": "STP I,imited, Kolkata",
          "bbox": [
            47.5,
            172.56,
            116.8,
            183.12
          ],
          "block_id": "b8_8",
          "font_size": 7.9,
          "is_bold": false,
          "is_heading": false
        },
        {
          "type": "text",
          "content": "Psw  H.C.h&ll?+OIRA~A",
          "bbox": [
            301.65,
            193.68,
            386.81,
            204.27
          ],
          "block_id": "b8_19",
          "font_size": 7.4,
          "is_bold": true,
          "is_heading": true
        },
        {
          "type": "text",
          "content": "Universityof Roorkee,Roorkee",
          "bbox": [
            48.22,
            195.36,
            147.74,
            205.92
          ],
          "block_id": "b8_9",
          "font_size": 7.9,
          "is_bold": false,
          "is_heading": false
        },
        {
          "type": "text",
          "content": "SrmrANJAN@\nD]rector& Head (PCD)",
          "bbox": [
            301.66,
            206.64,
            429.58,
            217.2
          ],
          "block_id": "b8_20",
          "font_size": 7.9,
          "is_bold": false,
          "is_heading": false
        },
        {
          "type": "text",
          "content": "IHSDirectorateGeneral",
          "bbox": [
            47.98,
            208.08,
            124.0,
            218.65
          ],
          "block_id": "b8_10",
          "font_size": 7.9,
          "is_bold": false,
          "is_heading": false
        },
        {
          "type": "text",
          "content": "~epresenting DirectorGeneral  (E@licio)]",
          "bbox": [
            302.14,
            219.6,
            431.69,
            230.19
          ],
          "block_id": "b8_21",
          "font_size": 7.4,
          "is_bold": true,
          "is_heading": true
        },
        {
          "type": "text",
          "content": "Member Secretary\nSmrr T.K.u.wmwr+\nJoint Director (PCD), BIS",
          "bbox": [
            231.1,
            236.77,
            313.44,
            266.88
          ],
          "block_id": "b8_22",
          "font_size": 7.9,
          "is_bold": true,
          "is_heading": true
        },
        {
          "type": "text",
          "content": "Methods of Test for Bitumen Tar and Their Products Subcommittee, PCD 6:1",
          "bbox": [
            114.22,
            278.55,
            425.51,
            291.35
          ],
          "block_id": "b8_23",
          "font_size": 9.6,
          "is_bold": false,
          "is_heading": false
        },
        {
          "type": "text",
          "content": "SmuSum BOSE(Convener)\nDRP, K. JAtN (Alternate)",
          "bbox": [
            302.62,
            304.56,
            390.87,
            325.23
          ],
          "block_id": "b8_39",
          "font_size": 7.9,
          "is_bold": true,
          "is_heading": true
        },
        {
          "type": "text",
          "content": "Central Road ResearchInstitute,New Delhi",
          "bbox": [
            48.94,
            305.76,
            185.95,
            316.32
          ],
          "block_id": "b8_24",
          "font_size": 7.9,
          "is_bold": false,
          "is_heading": false
        },
        {
          "type": "text",
          "content": "Smu  J. A. J.mw",
          "bbox": [
            302.85,
            327.36,
            350.35,
            337.95
          ],
          "block_id": "b8_40",
          "font_size": 7.4,
          "is_bold": true,
          "is_heading": true
        },
        {
          "type": "text",
          "content": "BharatPctmleum CorporationLimited, Mumbai",
          "bbox": [
            49.42,
            328.32,
            201.05,
            338.88
          ],
          "block_id": "b8_25",
          "font_size": 7.9,
          "is_bold": false,
          "is_heading": false
        },
        {
          "type": "text",
          "content": "DRNOBLEGEORGE (Alternate)",
          "bbox": [
            316.78,
            338.21,
            406.99,
            347.79
          ],
          "block_id": "b8_41",
          "font_size": 7.0,
          "is_bold": true,
          "is_heading": true
        },
        {
          "type": "text",
          "content": "Srrra0,  P. NANGAUSA",
          "bbox": [
            303.1,
            349.92,
            375.75,
            360.51
          ],
          "block_id": "b8_42",
          "font_size": 7.3,
          "is_bold": true,
          "is_heading": true
        },
        {
          "type": "text",
          "content": "13hilai Chemical PrivateLimited, Ranchi",
          "bbox": [
            49.66,
            351.12,
            177.04,
            361.68
          ],
          "block_id": "b8_26",
          "font_size": 7.4,
          "is_bold": false,
          "is_heading": false
        },
        {
          "type": "text",
          "content": "Strruv.  PArLY\nSmuR. VmamoP~  (Akernate)",
          "bbox": [
            303.1,
            362.88,
            408.89,
            383.55
          ],
          "block_id": "b8_43",
          "font_size": 7.4,
          "is_bold": true,
          "is_heading": true
        },
        {
          "type": "text",
          "content": "Cochin RefineriesLimited,Kerala",
          "bbox": [
            49.66,
            363.84,
            156.89,
            374.4
          ],
          "block_id": "b8_27",
          "font_size": 7.9,
          "is_bold": false,
          "is_heading": false
        },
        {
          "type": "text",
          "content": "Drt  H. S. S~",
          "bbox": [
            303.09,
            385.44,
            339.6,
            396.03
          ],
          "block_id": "b8_44",
          "font_size": 7.4,
          "is_bold": true,
          "is_heading": true
        },
        {
          "type": "text",
          "content": "DurgapurProjectsLimited, Durgapur",
          "bbox": [
            50.14,
            386.4,
            168.14,
            396.96
          ],
          "block_id": "b8_28",
          "font_size": 7.9,
          "is_bold": false,
          "is_heading": false
        },
        {
          "type": "text",
          "content": "Highway Research Station, Chennai",
          "bbox": [
            50.14,
            399.12,
            159.76,
            409.68
          ],
          "block_id": "b8_29",
          "font_size": 7.4,
          "is_bold": false,
          "is_heading": false
        },
        {
          "type": "text",
          "content": "DLreEm31r,\nDmm\nDIRECTOR\n(Alternate)",
          "bbox": [
            303.34,
            399.97,
            404.83,
            418.83
          ],
          "block_id": "b8_45",
          "font_size": 7.0,
          "is_bold": true,
          "is_heading": true
        },
        {
          "type": "text",
          "content": "Sma  H,Pwhmtwrwm\nSrrruVUAYK. BHATNW.4R\n(Alternate)",
          "bbox": [
            303.58,
            420.96,
            429.79,
            441.39
          ],
          "block_id": "b8_46",
          "font_size": 7.9,
          "is_bold": true,
          "is_heading": true
        },
        {
          "type": "text",
          "content": "Hindustan Colas Limited, Mumbai",
          "bbox": [
            50.14,
            422.16,
            159.29,
            432.72
          ],
          "block_id": "b8_30",
          "font_size": 7.9,
          "is_bold": false,
          "is_heading": false
        },
        {
          "type": "text",
          "content": "SmrA. S.Ps.mrwnrr\nSsuuS.K.  BHATNAGAR  (Alternate)",
          "bbox": [
            303.82,
            444.0,
            418.99,
            464.19
          ],
          "block_id": "b8_47",
          "font_size": 7.9,
          "is_bold": true,
          "is_heading": true
        },
        {
          "type": "text",
          "content": "HirrdustanPetroleumCorporationLimited,Mumbai",
          "bbox": [
            50.62,
            444.48,
            212.81,
            455.04
          ],
          "block_id": "b8_31",
          "font_size": 7.9,
          "is_bold": false,
          "is_heading": false
        },
        {
          "type": "text",
          "content": "Smu  Mom. hwm\nSsrmU. C. GUPTA (Alternate)",
          "bbox": [
            304.05,
            466.32,
            404.59,
            486.99
          ],
          "block_id": "b8_48",
          "font_size": 7.4,
          "is_bold": true,
          "is_heading": true
        },
        {
          "type": "text",
          "content": "Indian Institute of Petroleum, DebraDun",
          "bbox": [
            50.62,
            467.28,
            178.68,
            477.84
          ],
          "block_id": "b8_32",
          "font_size": 7.9,
          "is_bold": false,
          "is_heading": false
        },
        {
          "type": "text",
          "content": "IndianOil Corporation Limited (MarketingDivision),Mumbai",
          "bbox": [
            51.1,
            489.36,
            247.13,
            499.92
          ],
          "block_id": "b8_33",
          "font_size": 7.9,
          "is_bold": false,
          "is_heading": false
        },
        {
          "type": "text",
          "content": "Smt  R, S. SISODr.4\nSmuV, P.GOPTA(A(ternate)",
          "bbox": [
            304.29,
            489.36,
            406.26,
            509.52
          ],
          "block_id": "b8_49",
          "font_size": 7.9,
          "is_bold": true,
          "is_heading": true
        },
        {
          "type": "text",
          "content": "SmuMOHITKHANNA\nSnruK. K. Mrw\n(Alternate)",
          "bbox": [
            304.54,
            511.92,
            405.31,
            532.35
          ],
          "block_id": "b8_50",
          "font_size": 7.9,
          "is_bold": true,
          "is_heading": true
        },
        {
          "type": "text",
          "content": "Lloyd  Insulations(India)Limited, New Delhi",
          "bbox": [
            51.34,
            512.16,
            192.9,
            522.72
          ],
          "block_id": "b8_34",
          "font_size": 7.4,
          "is_bold": false,
          "is_heading": false
        },
        {
          "type": "text",
          "content": "Smu M. S.  %uY,m Surimrr\nSmu  B. Sm.mr  (Altemrate)",
          "bbox": [
            304.53,
            533.53,
            400.49,
            555.15
          ],
          "block_id": "b8_51",
          "font_size": 7.5,
          "is_bold": true,
          "is_heading": true
        },
        {
          "type": "text",
          "content": "MadrasRefinerylimited, Chennai",
          "bbox": [
            51.58,
            534.72,
            159.99,
            545.28
          ],
          "block_id": "b8_35",
          "font_size": 7.9,
          "is_bold": false,
          "is_heading": false
        },
        {
          "type": "text",
          "content": "Ssaa F\u2019. K.CwuausORW\nSmuS. K.  Aa19UGmw.u(Ahernate)",
          "bbox": [
            305.01,
            557.52,
            423.03,
            577.71
          ],
          "block_id": "b8_52",
          "font_size": 7.4,
          "is_bold": true,
          "is_heading": true
        },
        {
          "type": "text",
          "content": "NationalTmt House, Kolkata",
          "bbox": [
            51.58,
            557.76,
            144.4,
            568.32
          ],
          "block_id": "b8_36",
          "font_size": 7.9,
          "is_bold": false,
          "is_heading": false
        },
        {
          "type": "text",
          "content": "Neyvcli l,ignite Corporation Limited, Neyveli",
          "bbox": [
            52.06,
            581.09,
            191.69,
            590.37
          ],
          "block_id": "b8_37",
          "font_size": 7.0,
          "is_bold": false,
          "is_heading": false
        },
        {
          "type": "text",
          "content": "DRs. sANrHANm",
          "bbox": [
            305.01,
            583.21,
            362.81,
            590.17
          ],
          "block_id": "b8_53",
          "font_size": 7.0,
          "is_bold": false,
          "is_heading": false
        },
        {
          "type": "text",
          "content": "SmuA, B,w.muaruwma.m (Alternate)",
          "bbox": [
            319.42,
            589.92,
            433.39,
            600.51
          ],
          "block_id": "b8_54",
          "font_size": 7.4,
          "is_bold": true,
          "is_heading": true
        },
        {
          "type": "text",
          "content": "Srim S.  K. J.m\nSmuS.C.  DAS Gorz\n(Alternate)",
          "bbox": [
            305.25,
            602.88,
            415.63,
            623.31
          ],
          "block_id": "b8_55",
          "font_size": 7.4,
          "is_bold": true,
          "is_heading": true
        },
        {
          "type": "text",
          "content": "Steel Authority oflndia, New Delhi",
          "bbox": [
            52.3,
            603.41,
            160.98,
            612.69
          ],
          "block_id": "b8_38",
          "font_size": 7.0,
          "is_bold": false,
          "is_heading": false
        },
        {
          "type": "text",
          "content": "6",
          "bbox": [
            274.06,
            707.28,
            278.85,
            720.57
          ],
          "block_id": "b8_56",
          "font_size": 9.6,
          "is_bold": true,
          "is_heading": true
        }
      ],
      "images": [],
      "dimensions": {
        "width": 529.9119873046875,
        "height": 782.2640380859375
      },
      "image_id_map": {}
    },
    {
      "page_num": 9,
      "blocks": [
        {
          "type": "text",
          "content": "Bureau of Indian Standards",
          "bbox": [
            30.31,
            32.5,
            145.01,
            45.3
          ],
          "block_id": "b9_0",
          "font_size": 9.6,
          "is_bold": false,
          "is_heading": false
        },
        {
          "type": "text",
          "content": "BIS is a statutory\ninstitution\nestablished\nunder the  Bureau\nof Indian\nStandards\nAct,\n1986 to promote\nharmonious\ndevelopment\nof the activities of standardization,\nmarking and quality certification\nof goods\nand attending to connected matters in the country.",
          "bbox": [
            30.06,
            56.5,
            477.64,
            92.82
          ],
          "block_id": "b9_1",
          "font_size": 9.6,
          "is_bold": true,
          "is_heading": false
        },
        {
          "type": "text",
          "content": "Copyright",
          "bbox": [
            30.54,
            103.79,
            69.41,
            116.59
          ],
          "block_id": "b9_2",
          "font_size": 9.6,
          "is_bold": false,
          "is_heading": false
        },
        {
          "type": "text",
          "content": "BIS has the copyright of all its publications. No part of these publications may be reproduced in any form\nwithout the prior permission\nin writing of BIS. This does not preclude\nthe free use, in the course of\nimplementing\nthe standard, of necessary details, such as symbols and sizes, type or grade designations.\nEnquiries relating to copyright be addressed to the Director (Publications), BIS.",
          "bbox": [
            30.54,
            127.07,
            479.63,
            174.91
          ],
          "block_id": "b9_3",
          "font_size": 9.6,
          "is_bold": false,
          "is_heading": false
        },
        {
          "type": "text",
          "content": "Review of Indian Standards",
          "bbox": [
            31.02,
            185.87,
            145.96,
            198.67
          ],
          "block_id": "b9_4",
          "font_size": 9.6,
          "is_bold": false,
          "is_heading": false
        },
        {
          "type": "text",
          "content": "Amendments are issued to standards as the need arises on the basis of comments, Standards are also reviewed\nperiodically; a standard along with amendments is reaffirmed when such review indicates that no changes are\nneeded; if the review indicates that changes are needed, it is taken up for revision. Users of Indian Standards\nshould ascertain that they are in possession of the latest amendments or edition by referring to the latest issue of\n\u2018BIS Catalogue\u2019 and \u2018Standards: Monthly Additions\u2019.",
          "bbox": [
            31.02,
            209.39,
            480.59,
            269.71
          ],
          "block_id": "b9_5",
          "font_size": 9.6,
          "is_bold": false,
          "is_heading": false
        },
        {
          "type": "text",
          "content": "This Indian Standard has been developed from Doc : No. PCD 6 (1335).",
          "bbox": [
            31.74,
            280.19,
            327.2,
            292.99
          ],
          "block_id": "b9_6",
          "font_size": 9.6,
          "is_bold": false,
          "is_heading": false
        },
        {
          "type": "text",
          "content": "Amendments Issued Since Publication",
          "bbox": [
            174.79,
            315.8,
            335.61,
            329.09
          ],
          "block_id": "b9_7",
          "font_size": 9.6,
          "is_bold": true,
          "is_heading": true
        },
        {
          "type": "text",
          "content": "Amend No.\nDate of Issue\nText Affected",
          "bbox": [
            56.22,
            343.07,
            479.82,
            356.11
          ],
          "block_id": "b9_8",
          "font_size": 9.6,
          "is_bold": false,
          "is_heading": false
        },
        {
          "type": "text",
          "content": "...",
          "bbox": [
            457.27,
            390.68,
            464.71,
            402.55
          ],
          "block_id": "b9_9",
          "font_size": 8.6,
          "is_bold": false,
          "is_heading": false
        },
        {
          "type": "text",
          "content": "BUREAU OF INDIAN STANDARDS",
          "bbox": [
            179.83,
            422.02,
            332.45,
            434.82
          ],
          "block_id": "b9_10",
          "font_size": 9.6,
          "is_bold": false,
          "is_heading": false
        },
        {
          "type": "text",
          "content": "Headquarters :",
          "bbox": [
            33.19,
            439.54,
            92.74,
            452.34
          ],
          "block_id": "b9_11",
          "font_size": 9.6,
          "is_bold": false,
          "is_heading": false
        },
        {
          "type": "text",
          "content": "Manak Bhavan, 9 Bahadur Shah Zafar Marg, New Delhi 110002\nTelegrams : Manaksanstha\nTelephones :3230131,\n3233375,3239402\n(Common to all offices)",
          "bbox": [
            32.95,
            457.31,
            480.55,
            482.83
          ],
          "block_id": "b9_12",
          "font_size": 9.6,
          "is_bold": false,
          "is_heading": false
        },
        {
          "type": "text",
          "content": "Regional Offices :\nTelephone",
          "bbox": [
            33.43,
            492.83,
            480.78,
            506.83
          ],
          "block_id": "b9_13",
          "font_size": 9.6,
          "is_bold": false,
          "is_heading": false
        },
        {
          "type": "text",
          "content": "Central\n:",
          "bbox": [
            33.19,
            510.59,
            78.58,
            523.39
          ],
          "block_id": "b9_14",
          "font_size": 9.6,
          "is_bold": false,
          "is_heading": false
        },
        {
          "type": "text",
          "content": "Manak Bhavan, 9 Bahadur Shah Zafar Marg",
          "bbox": [
            87.43,
            510.59,
            267.64,
            523.39
          ],
          "block_id": "b9_20",
          "font_size": 9.6,
          "is_bold": false,
          "is_heading": false
        },
        {
          "type": "text",
          "content": "3237617\nNEW DEL~I 110002\n3233841",
          "bbox": [
            87.19,
            512.27,
            475.27,
            536.59
          ],
          "block_id": "b9_22",
          "font_size": 9.6,
          "is_bold": false,
          "is_heading": false
        },
        {
          "type": "text",
          "content": "{",
          "bbox": [
            431.12,
            526.67,
            435.72,
            539.47
          ],
          "block_id": "b9_21",
          "font_size": 9.6,
          "is_bold": false,
          "is_heading": false
        },
        {
          "type": "text",
          "content": "Eastern\n:",
          "bbox": [
            33.91,
            540.11,
            78.82,
            552.91
          ],
          "block_id": "b9_15",
          "font_size": 9.6,
          "is_bold": false,
          "is_heading": false
        },
        {
          "type": "text",
          "content": "1/14 C.I.T. Scheme VII M, V. I. P. Road, Kankurgachi",
          "bbox": [
            88.87,
            540.35,
            304.85,
            553.15
          ],
          "block_id": "b9_23",
          "font_size": 9.6,
          "is_bold": false,
          "is_heading": false
        },
        {
          "type": "text",
          "content": "{\n3378499,3378561\nKOLKATA 700054\n3378626,3379120",
          "bbox": [
            87.67,
            541.31,
            464.93,
            567.55
          ],
          "block_id": "b9_24",
          "font_size": 9.6,
          "is_bold": false,
          "is_heading": false
        },
        {
          "type": "text",
          "content": "Northern\n:",
          "bbox": [
            33.43,
            569.39,
            79.06,
            582.19
          ],
          "block_id": "b9_16",
          "font_size": 9.6,
          "is_bold": false,
          "is_heading": false
        },
        {
          "type": "text",
          "content": "SCO 335-336, Sector 34-A, CHANDIGARH 160022",
          "bbox": [
            88.15,
            569.63,
            301.02,
            582.43
          ],
          "block_id": "b9_25",
          "font_size": 9.6,
          "is_bold": false,
          "is_heading": false
        },
        {
          "type": "text",
          "content": "603843\n602025",
          "bbox": [
            446.96,
            571.07,
            475.75,
            595.87
          ],
          "block_id": "b9_27",
          "font_size": 9.6,
          "is_bold": false,
          "is_heading": false
        },
        {
          "type": "text",
          "content": "{",
          "bbox": [
            436.4,
            586.91,
            441.0,
            599.71
          ],
          "block_id": "b9_26",
          "font_size": 9.6,
          "is_bold": false,
          "is_heading": false
        },
        {
          "type": "text",
          "content": "Southern\n:",
          "bbox": [
            34.15,
            598.91,
            79.3,
            611.71
          ],
          "block_id": "b9_17",
          "font_size": 9.6,
          "is_bold": false,
          "is_heading": false
        },
        {
          "type": "text",
          "content": "C.I.T. Campus, IV Cross Road, CHENNAI 600113",
          "bbox": [
            88.15,
            599.39,
            292.38,
            612.19
          ],
          "block_id": "b9_28",
          "font_size": 9.6,
          "is_bold": false,
          "is_heading": false
        },
        {
          "type": "text",
          "content": "2541216,2541442\n2542519,2541315",
          "bbox": [
            395.6,
            600.59,
            465.17,
            625.15
          ],
          "block_id": "b9_30",
          "font_size": 9.6,
          "is_bold": false,
          "is_heading": false
        },
        {
          "type": "text",
          "content": "{",
          "bbox": [
            385.28,
            616.19,
            389.88,
            628.99
          ],
          "block_id": "b9_29",
          "font_size": 9.6,
          "is_bold": false,
          "is_heading": false
        },
        {
          "type": "text",
          "content": "Western\n:",
          "bbox": [
            34.39,
            628.67,
            79.3,
            641.47
          ],
          "block_id": "b9_18",
          "font_size": 9.6,
          "is_bold": false,
          "is_heading": false
        },
        {
          "type": "text",
          "content": "Manakalaya, E9 MIDC, Marol, Andheri (East)",
          "bbox": [
            88.15,
            628.91,
            277.05,
            641.71
          ],
          "block_id": "b9_31",
          "font_size": 9.6,
          "is_bold": false,
          "is_heading": false
        },
        {
          "type": "text",
          "content": "{\n8329295,8327858\nMUMBAI 400093\n8327891,8327892",
          "bbox": [
            88.15,
            630.35,
            465.65,
            656.83
          ],
          "block_id": "b9_32",
          "font_size": 9.6,
          "is_bold": false,
          "is_heading": false
        },
        {
          "type": "text",
          "content": "Branches :",
          "bbox": [
            34.63,
            658.19,
            79.54,
            670.99
          ],
          "block_id": "b9_19",
          "font_size": 9.6,
          "is_bold": false,
          "is_heading": false
        },
        {
          "type": "text",
          "content": "AHMEDABAD. BANGALORE. BHOPAL. BHUBANESHWAR. COIMBATORE. FARIDABAD.\nGHAZIABAD.\nGUWAHATI.\nHYDERABAD.\nJAIPUR. KANPUR. LUCKNOW.\nNAGPUR.\nNALAGARH. PATNA, PUNE. RAJKOT. THIRUVANANTHAPURAM.\nVISAKHAPATNAM",
          "bbox": [
            85.27,
            658.43,
            480.76,
            694.75
          ],
          "block_id": "b9_33",
          "font_size": 9.6,
          "is_bold": false,
          "is_heading": false
        },
        {
          "type": "text",
          "content": "Reprography Unit, BIS, New Delhi, India",
          "bbox": [
            316.88,
            708.83,
            483.68,
            721.63
          ],
          "block_id": "b9_34",
          "font_size": 9.6,
          "is_bold": false,
          "is_heading": false
        }
      ],
      "images": [],
      "dimensions": {
        "width": 530.2319946289062,
        "height": 752.3360595703125
      },
      "image_id_map": {}
    }
  ],
  "tables": [],
  "images": []
}